Workbook

Sheet Dashboard
A1: DASHBOARD KEUANGAN
A2: PT BIGATRI INDOFLORA PACIFIC
A3: BLOOMORIST
A5: TOTAL PENJUALAN | B5: TOTAL BEBAN (HPP+OPS) | C5: LABA BERSIH | D5: KAS & BANK SAAT INI
A6: ='Laba Rugi'!C8 -> 55819250 | B6: =('Laba Rugi'!C18+'Laba Rugi'!C33) -> 56909911 | C6: ='Laba Rugi'!C42 -> -632661 | D6: ='Neraca Saldo'!C6+'Neraca Saldo'!C7 -> 15641450
A9: RINGKASAN LAPORAN LABA RUGI
A10: Penjualan Bersih | B10: ='Laba Rugi'!C8 -> 55819250
A11: Harga Pokok Penjualan (HPP) | B11: ='Laba Rugi'!C18 -> 35664500
A12: Laba Kotor | B12: ='Laba Rugi'!C20 -> 20154750
A13: Total Beban Operasional | B13: ='Laba Rugi'!C33 -> 21245411
A14: Laba Bersih | B14: ='Laba Rugi'!C42 -> -632661
A16: POSISI KEUANGAN (NERACA)
A17: Total Aktiva | B17: =Neraca!C23 -> 61237339
A18: Total Kewajiban | B18: =Neraca!C27 -> 0
A19: Total Modal | B19: =Neraca!C33 -> 61237339

Sheet Penyusutan Peralatan
A2: Bulan Desember Tahun 2025 | H2: Bulan Agustus Tahun 2026
A3: Nama Aset | B3: Bulan Beli | C3: Harga Perolehan | D3: Penyusutan / Bulan | E3: Akm. Penyusutan | F3: Nilai Buku (Neto) | H3: Nama Aset | I3: Bulan Beli | J3: Harga Perolehan | K3: Penyusutan / Bulan | L3: Akm. Penyusutan | M3: Nilai Buku (Neto)
A4: HP Operasional | B4: September | C4: 5000000 | D4: =C4/48 -> 104166.67 | E4: =D4*4 -> 416666.67 | F4: =C4-E4 -> 4583333.3 | H4: HP Operasional | I4: 45901 | J4: 5000000 | K4: =J4/48 -> 104166.67 | L4: =K4*8 -> 833333.33 | M4: =J4-L4 -> 4166666.7
A5: Meja Kursih | B5: September | C5: 1000000 | D5: =C5/48 -> 20833.333 | E5: =D5*4 -> 83333.333 | F5: =C5-E5 -> 916666.67 | H5: Meja Kursih | I5: 45901 | J5: 1000000 | K5: =J5/48 -> 20833.333 | L5: =K5*8 -> 166666.67 | M5: =J5-L5 -> 833333.33
A6: Komputer | B6: September | C6: 10000000 | D6: =C6/48 -> 208333.33 | E6: =D6*4 -> 833333.33 | F6: =C6-E6 -> 9166666.7 | H6: Komputer | I6: 45901 | J6: 10000000 | K6: =J6/48 -> 208333.33 | L6: =K6*8 -> 1666666.7 | M6: =J6-L6 -> 8333333.3
A7: Tambahan Komputer | B7: Oktober | C7: 686000 | D7: =C7/48 -> 14291.667 | E7: =D7*3 -> 42875 | F7: =C7-E7 -> 643125 | H7: Tambahan Komputer | I7: 45931 | J7: 686000 | K7: =J7/48 -> 14291.667 | L7: =K7*8 -> 114333.33 | M7: =J7-L7 -> 571666.67
A8: CCTV | B8: Oktober | C8: 209000 | D8: =C8/48 -> 4354.1667 | E8: =D8*3 -> 13062.5 | F8: =C8-E8 -> 195937.5 | H8: CCTV | I8: 45931 | J8: 209000 | K8: =J8/48 -> 4354.1667 | L8: =K8*8 -> 34833.333 | M8: =J8-L8 -> 174166.67
A9: Mesin Bor | B9: November | C9: 268909 | D9: =C9/48 -> 5602.2708 | E9: =D9*2 -> 11204.542 | F9: =C9-E9 -> 257704.46 | H9: Mesin Bor | I9: 45962 | J9: 268909 | K9: =J9/48 -> 5602.2708 | L9: =K9*8 -> 44818.167 | M9: =J9-L9 -> 224090.83
A10: Speaker PC | B10: November | C10: 74263 | D10: =C10/48 -> 1547.1458 | E10: =D10*2 -> 3094.2917 | F10: =C10-E10 -> 71168.708 | H10: Speaker PC | I10: 45962 | J10: 74263 | K10: =J10/48 -> 1547.1458 | L10: =K10*8 -> 12377.167 | M10: =J10-L10 -> 61885.833
A11: Gunting Batang | B11: Desember | C11: 61100 | D11: =C11/48 -> 1272.9167 | E11: =D11*1 -> 1272.9167 | F11: =C11-E11 -> 59827.083 | H11: Gunting Batang | I11: 45992 | J11: 61100 | K11: =J11/48 -> 1272.9167 | L11: =K11*8 -> 10183.333 | M11: =J11-L11 -> 50916.667
A12: Tape Dispenser | B12: Desember | C12: 17999 | D12: =C12/48 -> 374.97917 | E12: =D12*1 -> 374.97917 | F12: =C12-E12 -> 17624.021 | H12: Tape Dispenser | I12: 45992 | J12: 17999 | K12: =J12/48 -> 374.97917 | L12: =K12*8 -> 2999.8333 | M12: =J12-L12 -> 14999.167
A13: Tropid | B13: Desember | C13: 151205 | D13: =C13/48 -> 3150.1042 | E13: =D13*1 -> 3150.1042 | F13: =C13-E13 -> 148054.9 | H13: Tropid | I13: 45992 | J13: 151205 | K13: =J13/48 -> 3150.1042 | L13: =K13*8 -> 25200.833 | M13: =J13-L13 -> 126004.17
A14: Total | C14: =SUM(C4:C13) -> 17468476 | D14: =SUM(D4:D13) -> 363926.58 | E14: =SUM(E4:E13) -> 1408367.7 | F14: =SUM(F4:F13) -> 16060108 | H14: Tambahan Tape Dispenser | I14: 46235 | J14: 9500 | K14: =J14/48 -> 197.91667 | L14: =K14*1 -> 197.91667 | M14: =J14-L14 -> 9302.0833
J15: =sum(J4:J14) -> 17477976 | K15: =sum(K4:K14) -> 364124.5 | L15: =sum(L4:L14) -> 2911610.6 | M15: =sum(M4:M14) -> 14566365
H17: Bulan September Tahun 2026
H18: Nama Aset | I18: Bulan Beli | J18: Harga Perolehan | K18: Penyusutan / Bulan | L18: Akm. Penyusutan | M18: Nilai Buku (Neto)
H19: HP Operasional | I19: 45901 | J19: 5000000 | K19: =J19/48 -> 104166.67 | L19: =K19*9 -> 937500 | M19: =J19-L19 -> 4062500
H20: Meja Kursih | I20: 45901 | J20: 1000000 | K20: =J20/48 -> 20833.333 | L20: =K20*9 -> 187500 | M20: =J20-L20 -> 812500
H21: Komputer | I21: 45901 | J21: 10000000 | K21: =J21/48 -> 208333.33 | L21: =K21*9 -> 1875000 | M21: =J21-L21 -> 8125000
H22: Tambahan Komputer | I22: 45931 | J22: 686000 | K22: =J22/48 -> 14291.667 | L22: =K22*9 -> 128625 | M22: =J22-L22 -> 557375
H23: CCTV | I23: 45931 | J23: 209000 | K23: =J23/48 -> 4354.1667 | L23: =K23*9 -> 39187.5 | M23: =J23-L23 -> 169812.5
H24: Mesin Bor | I24: 45962 | J24: 268909 | K24: =J24/48 -> 5602.2708 | L24: =K24*9 -> 50420.438 | M24: =J24-L24 -> 218488.56
H25: Speaker PC | I25: 45962 | J25: 74263 | K25: =J25/48 -> 1547.1458 | L25: =K25*9 -> 13924.312 | M25: =J25-L25 -> 60338.688
H26: Gunting Batang | I26: 45992 | J26: 61100 | K26: =J26/48 -> 1272.9167 | L26: =K26*9 -> 11456.25 | M26: =J26-L26 -> 49643.75
H27: Tape Dispenser | I27: 45992 | J27: 17999 | K27: =J27/48 -> 374.97917 | L27: =K27*9 -> 3374.8125 | M27: =J27-L27 -> 14624.188
H28: Tropid | I28: 45992 | J28: 151205 | K28: =J28/48 -> 3150.1042 | L28: =K28*9 -> 28350.938 | M28: =J28-L28 -> 122854.06
H29: Tambahan Tape Dispenser | I29: 46235 | J29: 9500 | K29: =J29/48 -> 197.91667 | L29: =K29*9 -> 1781.25 | M29: =J29-L29 -> 7718.75
J30: =SUM(J19:J29) -> 17477976 | K30: =SUM(K19:K29) -> 364124.5 | L30: =SUM(L19:L29) -> 3277120.5 | M30: =SUM(M19:M29) -> 14200856
H33: Bulan Oktober Tahun 2026
H34: Nama Aset | I34: Bulan Beli | J34: Harga Perolehan | K34: Penyusutan / Bulan | L34: Akm. Penyusutan | M34: Nilai Buku (Neto)
H35: HP Operasional | I35: 45901 | J35: 5000000 | K35: =J35/48 -> 104166.67 | L35: =K35*10 -> 1041666.7 | M35: =M19-L35 -> 3020833.3
H36: Meja Kursih | I36: 45901 | J36: 1000000 | K36: =J36/48 -> 20833.333 | L36: =K36*10 -> 208333.33 | M36: =M20-L36 -> 604166.67
H37: Komputer | I37: 45901 | J37: 10000000 | K37: =J37/48 -> 208333.33 | L37: =K37*10 -> 2083333.3 | M37: =M21-L37 -> 6041666.7
H38: Tambahan Komputer | I38: 45931 | J38: 686000 | K38: =J38/48 -> 14291.667 | L38: =K38*10 -> 142916.67 | M38: =M22-L38 -> 414458.33
H39: CCTV | I39: 45931 | J39: 209000 | K39: =J39/48 -> 4354.1667 | L39: =K39*10 -> 43541.667 | M39: =M23-L39 -> 126270.83
H40: Mesin Bor | I40: 45962 | J40: 268909 | K40: =J40/48 -> 5602.2708 | L40: =K40*10 -> 56022.708 | M40: =M24-L40 -> 162465.85
H41: Speaker PC | I41: 45962 | J41: 74263 | K41: =J41/48 -> 1547.1458 | L41: =K41*10 -> 15471.458 | M41: =M25-L41 -> 44867.229
H42: Gunting Batang | I42: 45992 | J42: 61100 | K42: =J42/48 -> 1272.9167 | L42: =K42*10 -> 12729.167 | M42: =M26-L42 -> 36914.583
H43: Tape Dispenser | I43: 45992 | J43: 17999 | K43: =J43/48 -> 374.97917 | L43: =K43*10 -> 3749.7917 | M43: =M27-L43 -> 10874.396
H44: Tropid | I44: 45992 | J44: 151205 | K44: =J44/48 -> 3150.1042 | L44: =K44*10 -> 31501.042 | M44: =M28-L44 -> 91353.021
H45: Tambahan Tape Dispenser | I45: 46235 | J45: 9500 | K45: =J45/48 -> 197.91667 | L45: =K45*10 -> 1979.1667 | M45: =M29-L45 -> 5739.5833
J46: =SUM(J35:J45) -> 17477976 | K46: =SUM(K35:K45) -> 364124.5 | L46: =SUM(L35:L45) -> 3641245 | M46: =SUM(M35:M45) -> 10559610
H49: Bulan November Tahun 2026
H50: Nama Aset | I50: Bulan Beli | J50: Harga Perolehan | K50: Penyusutan / Bulan | L50: Akm. Penyusutan | M50: Nilai Buku (Neto)
H51: HP Operasional | I51: 45901 | J51: 5000000 | K51: =J51/48 -> 104166.67 | L51: =K51*11 -> 1145833.3 | M51: =M35-L51 -> 1875000
H52: Meja Kursih | I52: 45901 | J52: 1000000 | K52: =J52/48 -> 20833.333 | L52: =K52*11 -> 229166.67 | M52: =M36-L52 -> 375000
H53: Komputer | I53: 45901 | J53: 10000000 | K53: =J53/48 -> 208333.33 | L53: =K53*11 -> 2291666.7 | M53: =M37-L53 -> 3750000
H54: Tambahan Komputer | I54: 45931 | J54: 686000 | K54: =J54/48 -> 14291.667 | L54: =K54*11 -> 157208.33 | M54: =M38-L54 -> 257250
H55: CCTV | I55: 45931 | J55: 209000 | K55: =J55/48 -> 4354.1667 | L55: =K55*11 -> 47895.833 | M55: =M39-L55 -> 78375
H56: Mesin Bor | I56: 45962 | J56: 268909 | K56: =J56/48 -> 5602.2708 | L56: =K56*11 -> 61624.979 | M56: =M40-L56 -> 100840.88
H57: Speaker PC | I57: 45962 | J57: 74263 | K57: =J57/48 -> 1547.1458 | L57: =K57*11 -> 17018.604 | M57: =M41-L57 -> 27848.625
H58: Gunting Batang | I58: 45992 | J58: 61100 | K58: =J58/48 -> 1272.9167 | L58: =K58*11 -> 14002.083 | M58: =M42-L58 -> 22912.5
H59: Tape Dispenser | I59: 45992 | J59: 17999 | K59: =J59/48 -> 374.97917 | L59: =K59*11 -> 4124.7708 | M59: =M43-L59 -> 6749.625
H60: Tropid | I60: 45992 | J60: 151205 | K60: =J60/48 -> 3150.1042 | L60: =K60*11 -> 34651.146 | M60: =M44-L60 -> 56701.875
H61: Tambahan Tape Dispenser | I61: 46235 | J61: 9500 | K61: =J61/48 -> 197.91667 | L61: =K61*11 -> 2177.0833 | M61: =M45-L61 -> 3562.5
J62: =SUM(J51:J61) -> 17477976 | K62: =SUM(K51:K61) -> 364124.5 | L62: =SUM(L51:L61) -> 4005369.5 | M62: =SUM(M51:M61) -> 6554241
H64: Bulan Desember Tahun 2026
H65: Nama Aset | I65: Bulan Beli | J65: Harga Perolehan | K65: Penyusutan / Bulan | L65: Akm. Penyusutan | M65: Nilai Buku (Neto)
H66: HP Operasional | I66: 45901 | J66: 5000000 | K66: =J66/48 -> 104166.67 | L66: =K66*12 -> 1250000 | M66: =M51-L66 -> 625000
H67: Meja Kursih | I67: 45901 | J67: 1000000 | K67: =J67/48 -> 20833.333 | L67: =K67*12 -> 250000 | M67: =M52-L67 -> 125000
H68: Komputer | I68: 45901 | J68: 10000000 | K68: =J68/48 -> 208333.33 | L68: =K68*12 -> 2500000 | M68: =M53-L68 -> 1250000
H69: Tambahan Komputer | I69: 45931 | J69: 686000 | K69: =J69/48 -> 14291.667 | L69: =K69*12 -> 171500 | M69: =M54-L69 -> 85750
H70: CCTV | I70: 45931 | J70: 209000 | K70: =J70/48 -> 4354.1667 | L70: =K70*12 -> 52250 | M70: =M55-L70 -> 26125
H71: Mesin Bor | I71: 45962 | J71: 268909 | K71: =J71/48 -> 5602.2708 | L71: =K71*12 -> 67227.25 | M71: =M56-L71 -> 33613.625
H72: Speaker PC | I72: 45962 | J72: 74263 | K72: =J72/48 -> 1547.1458 | L72: =K72*12 -> 18565.75 | M72: =M57-L72 -> 9282.875
H73: Gunting Batang | I73: 45992 | J73: 61100 | K73: =J73/48 -> 1272.9167 | L73: =K73*12 -> 15275 | M73: =M58-L73 -> 7637.5
H74: Tape Dispenser | I74: 45992 | J74: 17999 | K74: =J74/48 -> 374.97917 | L74: =K74*12 -> 4499.75 | M74: =M59-L74 -> 2249.875
H75: Tropid | I75: 45992 | J75: 151205 | K75: =J75/48 -> 3150.1042 | L75: =K75*12 -> 37801.25 | M75: =M60-L75 -> 18900.625
H76: Tambahan Tape Dispenser | I76: 46235 | J76: 9500 | K76: =J76/48 -> 197.91667 | L76: =K76*12 -> 2375 | M76: =M61-L76 -> 1187.5
J77: =SUM(J66:J76) -> 17477976 | K77: =SUM(K66:K76) -> 364124.5 | L77: =SUM(L66:L76) -> 4369494 | M77: =SUM(M66:M76) -> 2184747

Sheet Daftar Akun
A1: BLOOMORIST
A3: DAFTAR AKUN (CHART OF ACCOUNTS) — Periode Agustus 2026
A5: Kode Akun | B5: Nama Akun | C5: Kategori | D5: Saldo Normal
A6: 1101 | B6: Kas | C6: Aktiva Lancar | D6: Debit
A7: 1102 | B7: Bank | C7: Aktiva Lancar | D7: Debit
A8: 1103 | B8: Piutang Dagang | C8: Aktiva Lancar | D8: Debit
A9: 1104 | B9: Persediaan Bunga | C9: Aktiva Lancar | D9: Debit
A10: 1105 | B10: Peralatan | C10: Aktiva Tetap | D10: Debit
A11: 1106 | B11: Akumulasi Penyusutan Peralatan | C11: Aktiva Tetap (Kontra) | D11: Kredit
A12: 1107 | B12: Piutang Ongkir | C12: Aktiva Lancar | D12: Debit
A13: 1108 | B13: Perlengkapan | C13: Aktiva Lancar | D13: Debit
A14: 1109 | B14: Piutang Investasi | C14: Aktiva Lancar | D14: Debet
A15: 1110 | B15: Uang Muka Pembelian Petani | C15: Aktiva Lancar | D15: Debit
A16: 1111 | B16: Gaji Bayar di Muka | C16: Aktiva Lancar | D16: Debit
... A39: 6110 | B39: Beban Pesangon | C39: Beban Operasional | D39: Debit

Sheet Jurnal Umum
A1: PT BIGATRI INDOFLORA PACIFIC
A2: BLOOMORIST
A3: JURNAL UMUM — Periode Agustus 2026
A5: Tanggal | B5: No. Bukti | C5: Keterangan | D5: Kode Akun | E5: Nama Akun | F5: Debit (Rp) | G5: Kredit (Rp) | I5: Urutan/Akun | J5: Kunci Pencarian (jangan dihapus) | L5: Kode Akun Lawan
A6: 46235 | C6: Modal Awal Bulan Agustus 2026 | D6: 1102 | E6: =IFERROR(VLOOKUP(D6,'Daftar Akun'!A$6:$B$103,2,FALSE),"") -> Bank | F6: 59266000 | I6: =IF(D6="","",COUNTIF($D$6:D6,D6)) -> 1 | J6: =IF(D6="","",D6&"-"&I6) -> 1102-1 | K6: =E7 -> Modal Pemilik | L6: =IFERROR(INDEX($D$6:$D$909,MATCH(1,($A$6:$A$909=A6)*($C$6:$C$909=C6)*($D$6:$D$909<>D6),0)),"") -> 3101
A7: 46235 | C7: Modal Awal Bulan Agustus 2026 | D7: 3101 | E7: =IFERROR(VLOOKUP(D7,'Daftar Akun'!A$6:$B$103,2,FALSE),"") -> Modal Pemilik | G7: 59266000 | I7: =IF(D7="","",COUNTIF($D$6:D7,D7)) -> 1 | J7: =IF(D7="","",D7&"-"&I7) -> 3101-1 | K7: =E6 -> Bank | L7: =IFERROR(INDEX($D$6:$D$909,MATCH(1,($A$6:$A$909=A7)*($C$6:$C$909=C7)*($D$6:$D$909<>D7),0)),"") -> 1102
A8: 46235 | C8: Pinjaman Modal Greenhouse | D8: 1109 | E8: =IFERROR(VLOOKUP(D8,'Daftar Akun'!A$6:$B$103,2,FALSE),"") -> Piutang Investasi | F8: 33060000 | I8: =IF(D8="","",COUNTIF($D$6:D8,D8)) -> 1 | J8: =IF(D8="","",D8&"-"&I8) -> 1109-1 | K8: =E9 -> Bank | L8: =IFERROR(INDEX($D$6:$D$909,MATCH(1,($A$6:$A$909=A8)*($C$6:$C$909=C8)*($D$6:$D$909<>D8),0)),"") -> 1102
A9: 46235 | C9: Pinjaman Modal Greenhouse | D9: 1102 | E9: =IFERROR(VLOOKUP(D9,'Daftar Akun'!A$6:$B$103,2,FALSE),"") -> Bank | G9: 33060000 | I9: =IF(D9="","",COUNTIF($D$6:D9,D9)) -> 2 | J9: =IF(D9="","",D9&"-"&I9) -> 1102-2 | K9: =E8 -> Piutang Investasi | L9: =IFERROR(INDEX($D$6:$D$909,MATCH(1,($A$6:$A$909=A9)*($C$6:$C$909=C9)*($D$6:$D$909<>D9),0)),"") -> 1109
A10: 46235 | C10: Abunemen Petani Aster - Mas Yuli | D10: 1110 | E10: =IFERROR(VLOOKUP(D10,'Daftar Akun'!A$6:$B$103,2,FALSE),"") -> Uang Muka Pembelian Petani | F10: 7000000 | I10: =IF(D10="","",COUNTIF($D$6:D10,D10)) -> 1 | J10: =IF(D10="","",D10&"-"&I10) -> 1110-1 | K10: =E11 -> Bank | L10: =IFERROR(INDEX($D$6:$D$909,MATCH(1,($A$6:$A$909=A10)*($C$6:$C$909=C10)*($D$6:$D$909<>D10),0)),"") -> 1102
A11: 46235 | C11: Abunemen Petani Aster - Mas Yuli | D11: 1102 | E11: =IFERROR(VLOOKUP(D11,'Daftar Akun'!A$6:$B$103,2,FALSE),"") -> Bank | G11: 7000000 | I11: =IF(D11="","",COUNTIF($D$6:D11,D11)) -> 3 | J11: =IF(D11="","",D11&"-"&I11) -> 1102-3 | K11: =E10 -> Uang Muka Pembelian Petani | L11: =IFERROR(INDEX($D$6:$D$909,MATCH(1,($A$6:$A$909=A11)*($C$6:$C$909=C11)*($D$6:$D$909<>D11),0)),"") -> 1110
A12: 46235 | C12: Talangan Ongkir DMK Cargo | D12: 1107 | E12: =IFERROR(VLOOKUP(D12,'Daftar Akun'!A$6:$B$103,2,FALSE),"") -> Piutang Ongkir | F12: 854295 | I12: =IF(D12="","",COUNTIF($D$6:D12,D12)) -> 1 | J12: =IF(D12="","",D12&"-"&I12) -> 1107-1 | K12: =E13 -> Bank | L12: =IFERROR(INDEX($D$6:$D$909,MATCH(1,($A$6:$A$909=A12)*($C$6:$C$909=C12)*($D$6:$D$909<>D12),0)),"") -> 1102
A13: 46235 | C13: Talangan Ongkir DMK Cargo | D13: 1102 | E13: =IFERROR(VLOOKUP(D13,'Daftar Akun'!A$6:$B$103,2,FALSE),"") -> Bank | G13: 854295 | I13: =IF(D13="","",COUNTIF($D$6:D13,D13)) -> 4 | J13: =IF(D13="","",D13&"-"&I13) -> 1102-4 | K13: =E12 -> Piutang Ongkir | L13: =IFERROR(INDEX($D$6:$D$909,MATCH(1,($A$6:$A$909=A13)*($C$6:$C$909=C13)*($D$6:$D$909<>D13),0)),"") -> 1107
A14: 46235 | C14: Pembayaran Bunga Pikok - Bu Nisa | D14: 5101 | E14: =IFERROR(VLOOKUP(D14,'Daftar Akun'!A$6:$B$103,2,FALSE),"") -> Pembelian Bunga | F14: 1050000 | I14: =IF(D14="","",COUNTIF($D$6:D14,D14)) -> 1 | J14: =IF(D14="","",D14&"-"&I14) -> 5101-1 | K14: =E15 -> Bank | L14: =IFERROR(INDEX($D$6:$D$909,MATCH(1,($A$6:$A$909=A14)*($C$6:$C$909=C14)*($D$6:$D$909<>D14),0)),"") -> 1102
A15: 46235 | C15: Pembayaran Bunga Pikok - Bu Nisa | D15: 1102 | E15: =IFERROR(VLOOKUP(D15,'Daftar Akun'!A$6:$B$103,2,FALSE),"") -> Bank | G15: 1050000 | I15: =IF(D15="","",COUNTIF($D$6:D15,D15)) -> 5 | J15: =IF(D15="","",D15&"-"&I15) -> 1102-5 | K15: =E14 -> Pembelian Bunga | L15: =IFERROR(INDEX($D$6:$D$909,MATCH(1,($A$6:$A$909=A15)*($C$6:$C$909=C15)*($D$6:$D$909<>D15),0)),"") -> 5101
A16: 46235 | C16: Pembayaran Bunga Bromo - Nongkojajar | D16: 5101 | E16: =IFERROR(VLOOKUP(D16,'Daftar Akun'!A$6:$B$103,2,FALSE),"") -> Pembelian Bunga | F16: 1428000 | I16: =IF(D16="","",COUNTIF($D$6:D16,D16)) -> 2 | J16: =IF(D16="","",D16&"-"&I16) -> 5101-2 | K16: =E17 -> Bank | L16: =IFERROR(INDEX($D$6:$D$909,MATCH(1,($A$6:$A$909=A16)*($C$6:$C$909=C16)*($D$6:$D$909<>D16),0)),"") -> 1102
A17: 46235 | C17: Pembayaran Bunga Bromo - Nongkojajar | D17: 1102 | E17: =IFERROR(VLOOKUP(D17,'Daftar Akun'!A$6:$B$103,2,FALSE),"") -> Bank | G17: 1428000 | I17: =IF(D17="","",COUNTIF($D$6:D17,D17)) -> 6 | J17: =IF(D17="","",D17&"-"&I17) -> 1102-6 | K17: =E16 -> Pembelian Bunga | L17: =IFERROR(INDEX($D$6:$D$909,MATCH(1,($A$6:$A$909=A17)*($C$6:$C$909=C17)*($D$6:$D$909<>D17),0)),"") -> 5101
A18: 46235 | C18: Pembelian Bunga di Om Toha | D18: 5101 | E18: =IFERROR(VLOOKUP(D18,'Daftar Akun'!A$6:$B$103,2,FALSE),"") -> Pembelian Bunga | F18: 650000 | I18: =IF(D18="","",COUNTIF($D$6:D18,D18)) -> 3 | J18: =IF(D18="","",D18&"-"&I18) -> 5101-3 | K18: =E19 -> Bank | L18: =IFERROR(INDEX($D$6:$D$909,MATCH(1,($A$6:$A$909=A18)*($C$6:$C$909=C18)*($D$6:$D$909<>D18),0)),"") -> 1102
A19: 46235 | C19: Pembelian Bunga di Om Toha | D19: 1102 | E19: =IFERROR(VLOOKUP(D19,'Daftar Akun'!A$6:$B$103,2,FALSE),"") -> Bank | G19: 650000 | I19: =IF(D19="","",COUNTIF($D$6:D19,D19)) -> 7 | J19: =IF(D19="","",D19&"-"&I19) -> 1102-7 | K19: =E18 -> Pembelian Bunga | L19: =IFERROR(INDEX($D$6:$D$909,MATCH(1,($A$6:$A$909=A19)*($C$6:$C$909=C19)*($D$6:$D$909<>D19),0)),"") -> 5101
A20: 46235 | B20: BK-260801-001 | C20: Pembelian Bunga di WKF | D20: 5101 | E20: =IFERROR(VLOOKUP(D20,'Daftar Akun'!A$6:$B$103,2,FALSE),"") -> Pembelian Bunga | F20: 282000 | I20: =IF(D20="","",COUNTIF($D$6:D20,D20)) -> 4 | J20: =IF(D20="","",D20&"-"&I20) -> 5101-4 | K20: =E21 -> Bank | L20: =IFERROR(INDEX($D$6:$D$909,MATCH(1,($A$6:$A$909=A20)*($C$6:$C$909=C20)*($D$6:$D$909<>D20),0)),"") -> 1102
A21: 46235 | B21: BK-260801-001 | C21: Pembelian Bunga di WKF | D21: 1102 | E21: =IFERROR(VLOOKUP(D21,'Daftar Akun'!A$6:$B$103,2,FALSE),"") -> Bank | G21: 282000 | I21: =IF(D21="","",COUNTIF($D$6:D21,D21)) -> 8 | J21: =IF(D21="","",D21&"-"&I21) -> 1102-8 | K21: =E20 -> Pembelian Bunga | L21: =IFERROR(INDEX($D$6:$D$909,MATCH(1,($A$6:$A$909=A21)*($C$6:$C$909=C21)*($D$6:$D$909<>D21),0)),"") -> 5101
A22: 46235 | C22: Pengembalian Dana Talangan Ongkir | D22: 1102 | E22: =IFERROR(VLOOKUP(D22,'Daftar Akun'!A$6:$B$103,2,FALSE),"") -> Bank | F22: 854295 | I22: =IF(D22="","",COUNTIF($D$6:D22,D22)) -> 9 | J22: =IF(D22="","",D22&"-"&I22) -> 1102-9 | K22: =E23 -> Piutang Ongkir | L22: =IFERROR(INDEX($D$6:$D$909,MATCH(1,($A$6:$A$909=A22)*($C$6:$C$909=C22)*($D$6:$D$909<>D22),0)),"") -> 1107
A23: 46235 | C23: Pengembalian Dana Talangan Ongkir | D23: 1107 | E23: =IFERROR(VLOOKUP(D23,'Daftar Akun'!A$6:$B$103,2,FALSE),"") -> Piutang Ongkir | G23: 854295 | I23: =IF(D23="","",COUNTIF($D$6:D23,D23)) -> 2 | J23: =IF(D23="","",D23&"-"&I23) -> 1107-2 | K23: =E22 -> Bank | L23: =IFERROR(INDEX($D$6:$D$909,MATCH(1,($A$6:$A$909=A23)*($C$6:$C$909=C23)*($D$6:$D$909<>D23),0)),"") -> 1102
A24: 46235 | C24: Tarik Tunai untuk kas operasional | D24: 1101 | E24: =IFERROR(VLOOKUP(D24,'Daftar Akun'!A$6:$B$103,2,FALSE),"") -> Kas | F24: 1437000 | I24: =IF(D24="","",COUNTIF($D$6:D24,D24)) -> 1 | J24: =IF(D24="","",D24&"-"&I24) -> 1101-1 | K24: =E25 -> Bank | L24: =IFERROR(INDEX($D$6:$D$909,MATCH(1,($A$6:$A$909=A24)*($C$6:$C$909=C24)*($D$6:$D$909<>D24),0)),"") -> 1102
A25: 46235 | C25: Tarik Tunai untuk kas operasional | D25: 1102 | E25: =IFERROR(VLOOKUP(D25,'Daftar Akun'!A$6:$B$103,2,FALSE),"") -> Bank | G25: 1437000 | I25: =IF(D25="","",COUNTIF($D$6:D25,D25)) -> 10 | J25: =IF(D25="","",D25&"-"&I25) -> 1102-10 | K25: =E24 -> Kas | L25: =IFERROR(INDEX($D$6:$D$909,MATCH(1,($A$6:$A$909=A25)*($C$6:$C$909=C25)*($D$6:$D$909<>D25),0)),"") -> 1101
A26: 46235 | C26: Ongkir Pembelian Bunga - Mas Pradan | D26: 5103 | E26: =IFERROR(VLOOKUP(D26,'Daftar Akun'!A$6:$B$103,2,FALSE),"") -> Beban Angkut Pembelian | F26: 35000 | I26: =IF(D26="","",COUNTIF($D$6:D26,D26)) -> 1 | J26: =IF(D26="","",D26&"-"&I26) -> 5103-1 | K26: =E27 -> Kas | L26: =IFERROR(INDEX($D$6:$D$909,MATCH(1,($A$6:$A$909=A26)*($C$6:$C$909=C26)*($D$6:$D$909<>D26),0)),"") -> 1101
A27: 46235 | C27: Ongkir Pembelian Bunga - Mas Pradan | D27: 1101 | E27: =IFERROR(VLOOKUP(D27,'Daftar Akun'!A$6:$B$103,2,FALSE),"") -> Kas | G27: 35000 | I27: =IF(D27="","",COUNTIF($D$6:D27,D27)) -> 2 | J27: =IF(D27="","",D27&"-"&I27) -> 1101-2 | K27: =E26 -> Beban Angkut Pembelian | L27: =IFERROR(INDEX($D$6:$D$909,MATCH(1,($A$6:$A$909=A27)*($C$6:$C$909=C27)*($D$6:$D$909<>D27),0)),"") -> 5103
A28: 46235 | C28: Pembelian Bunga oleh tim operasional | D28: 5101 | E28: =IFERROR(VLOOKUP(D28,'Daftar Akun'!A$6:$B$103,2,FALSE),"") -> Pembelian Bunga | F28: 183000 | I28: =IF(D28="","",COUNTIF($D$6:D28,D28)) -> 5 | J28: =IF(D28="","",D28&"-"&I28) -> 5101-5 | K28: =E29 -> Kas | L28: =IFERROR(INDEX($D$6:$D$909,MATCH(1,($A$6:$A$909=A28)*($C$6:$C$909=C28)*($D$6:$D$909<>D28),0)),"") -> 1101
A29: 46235 | C29: Pembelian Bunga oleh tim operasional | D29: 1101 | E29: =IFERROR(VLOOKUP(D29,'Daftar Akun'!A$6:$B$103,2,FALSE),"") -> Kas | G29: 183000 | I29: =IF(D29="","",COUNTIF($D$6:D29,D29)) -> 3 | J29: =IF(D29="","",D29&"-"&I29) -> 1101-3 | K29: =E28 -> Pembelian Bunga | L29: =IFERROR(INDEX($D$6:$D$909,MATCH(1,($A$6:$A$909=A29)*($C$6:$C$909=C29)*($D$6:$D$909<>D29),0)),"") -> 5101
A30: 46235 | B30: KK-260801-002 | C30: Pembayaran Zainul Florist | D30: 5101 | E30: =IFERROR(VLOOKUP(D30,'Daftar Akun'!A$6:$B$103,2,FALSE),"") -> Pembelian Bunga | F30: 17000 | I30: =IF(D30="","",COUNTIF($D$6:D30,D30)) -> 6 | J30: =IF(D30="","",D30&"-"&I30) -> 5101-6 | K30: =E31 -> Kas | L30: =IFERROR(INDEX($D$6:$D$909,MATCH(1,($A$6:$A$909=A30)*($C$6:$C$909=C30)*($D$6:$D$909<>D30),0)),"") -> 1101
A31: 46235 | B31: KK-260801-002 | C31: Pembayaran Zainul Florist | D31: 1101 | E31: =IFERROR(VLOOKUP(D31,'Daftar Akun'!A$6:$B$103,2,FALSE),"") -> Kas | G31: 17000 | I31: =IF(D31="","",COUNTIF($D$6:D31,D31)) -> 4 | J31: =IF(D31="","",D31&"-"&I31) -> 1101-4 | K31: =E30 -> Pembelian Bunga | L31: =IFERROR(INDEX($D$6:$D$909,MATCH(1,($A$6:$A$909=A31)*($C$6:$C$909=C31)*($D$6:$D$909<>D31),0)),"") -> 5101
A32: 46235 | C32: Talangan Ongkir Travel - Pesona Travel - Ngawi | D32: 1107 | E32: =IFERROR(VLOOKUP(D32,'Daftar Akun'!A$6:$B$103,2,FALSE),"") -> Piutang Ongkir | F32: 70000 | I32: =IF(D32="","",COUNTIF($D$6:D32,D32)) -> 3 | J32: =IF(D32="","",D32&"-"&I32) -> 1107-3 | K32: =E33 -> Kas | L32: =IFERROR(INDEX($D$6:$D$909,MATCH(1,($A$6:$A$909=A32)*($C$6:$C$909=C32)*($D$6:$D$909<>D32),0)),"") -> 1101
A33: 46235 | C33: Talangan Ongkir Travel - Pesona Travel - Ngawi | D33: 1101 | E33: =IFERROR(VLOOKUP(D33,'Daftar Akun'!A$6:$B$103,2,FALSE),"") -> Kas | G33: 70000 | I33: =IF(D33="","",COUNTIF($D$6:D33,D33)) -> 5 | J33: =IF(D33="","",D33&"-"&I33) -> 1101-5 | K33: =E32 -> Piutang Ongkir | L33: =IFERROR(INDEX($D$6:$D$909,MATCH(1,($A$6:$A$909=A33)*($C$6:$C$909=C33)*($D$6:$D$909<>D33),0)),"") -> 1107
A34: 46235 | C34: Talangan Ongkir DMK Cargo | D34: 1107 | E34: =IFERROR(VLOOKUP(D34,'Daftar Akun'!A$6:$B$103,2,FALSE),"") -> Piutang Ongkir | F34: 1968519 | I34: =IF(D34="","",COUNTIF($D$6:D34,D34)) -> 4 | J34: =IF(D34="","",D34&"-"&I34) -> 1107-4 | K34: =E35 -> Bank | L34: =IFERROR(INDEX($D$6:$D$909,MATCH(1,($A$6:$A$909=A34)*($C$6:$C$909=C34)*($D$6:$D$909<>D34),0)),"") -> 1102
A35: 46235 | C35: Talangan Ongkir DMK Cargo | D35: 1102 | E35: =IFERROR(VLOOKUP(D35,'Daftar Akun'!A$6:$B$103,2,FALSE),"") -> Bank | G35: 1968519 | I35: =IF(D35="","",COUNTIF($D$6:D35,D35)) -> 11 | J35: =IF(D35="","",D35&"-"&I35) -> 1102-11 | K35: =E34 -> Piutang Ongkir | L35: =IFERROR(INDEX($D$6:$D$909,MATCH(1,($A$6:$A$909=A35)*($C$6:$C$909=C35)*($D$6:$D$909<>D35),0)),"") -> 1107
A36: 46235 | C36: Biaya Admin Kartu BCA | D36: 6108 | E36: =IFERROR(VLOOKUP(D36,'Daftar Akun'!A$6:$B$103,2,FALSE),"") -> Beban Lain-Lain | F36: 10000 | I36: =IF(D36="","",COUNTIF($D$6:D36,D36)) -> 1 | J36: =IF(D36="","",D36&"-"&I36) -> 6108-1 | K36: =E37 -> Bank | L36: =IFERROR(INDEX($D$6:$D$909,MATCH(1,($A$6:$A$909=A36)*($C$6:$C$909=C36)*($D$6:$D$909<>D36),0)),"") -> 1102
A37: 46235 | C37: Biaya Admin Kartu BCA | D37: 1102 | E37: =IFERROR(VLOOKUP(D37,'Daftar Akun'!A$6:$B$103,2,FALSE),"") -> Bank | G37: 10000 | I37: =IF(D37="","",COUNTIF($D$6:D37,D37)) -> 12 | J37: =IF(D37="","",D37&"-"&I37) -> 1102-12 | K37: =E36 -> Beban Lain-Lain | L37: =IFERROR(INDEX($D$6:$D$909,MATCH(1,($A$6:$A$909=A37)*($C$6:$C$909=C37)*($D$6:$D$909<>D37),0)),"") -> 6108
A38: 46235 | B38: INV-108265324 | C38: Penjualan Bunga - Terry | D38: 1103 | E38: =IFERROR(VLOOKUP(D38,'Daftar Akun'!A$6:$B$103,2,FALSE),"") -> Piutang Dagang | F38: 201000 | I38: =IF(D38="","",COUNTIF($D$6:D38,D38)) -> 1 | J38: =IF(D38="","",D38&"-"&I38) -> 1103-1 | K38: =E39 -> Penjualan | L38: =IFERROR(INDEX($D$6:$D$909,MATCH(1,($A$6:$A$909=A38)*($C$6:$C$909=C38)*($D$6:$D$909<>D38),0)),"") -> 4101
A39: 46235 | B39: INV-108265324 | C39: Penjualan Bunga - Terry | D39: 4101 | E39: =IFERROR(VLOOKUP(D39,'Daftar Akun'!A$6:$B$103,2,FALSE),"") -> Penjualan | G39: 201000 | I39: =IF(D39="","",COUNTIF($D$6:D39,D39)) -> 1 | J39: =IF(D39="","",D39&"-"&I39) -> 4101-1 | K39: =E38 -> Piutang Dagang | L39: =IFERROR(INDEX($D$6:$D$909,MATCH(1,($A$6:$A$909=A39)*($C$6:$C$909=C39)*($D$6:$D$909<>D39),0)),"") -> 1103
A40: 46235 | B40: INV-108268980 | C40: Penjualan Bunga - Sunny | D40: 1103 | E40: =IFERROR(VLOOKUP(D40,'Daftar Akun'!A$6:$B$103,2,FALSE),"") -> Piutang Dagang | F40: 715000 | I40: =IF(D40="","",COUNTIF($D$6:D40,D40)) -> 2 | J40: =IF(D40="","",D40&"-"&I40) -> 1103-2 | K40: =E41 -> Penjualan | L40: =IFERROR(INDEX($D$6:$D$909,MATCH(1,($A$6:$A$909=A40)*($C$6:$C$909=C40)*($D$6:$D$909<>D40),0)),"") -> 4101
A41: 46235 | B41: INV-108268980 | C41: Penjualan Bunga - Sunny | D41: 4101 | E41: =IFERROR(VLOOKUP(D41,'Daftar Akun'!A$6:$B$103,2,FALSE),"") -> Penjualan | G41: 715000 | I41: =IF(D41="","",COUNTIF($D$6:D41,D41)) -> 2 | J41: =IF(D41="","",D41&"-"&I41) -> 4101-2 | K41: =E40 -> Piutang Dagang | L41: =IFERROR(INDEX($D$6:$D$909,MATCH(1,($A$6:$A$909=A41)*($C$6:$C$909=C41)*($D$6:$D$909<>D41),0)),"") -> 1103
A42: 46235 | B42: INV-108267202 | C42: Penjualan Bunga - Tiara | D42: 1103 | E42: =IFERROR(VLOOKUP(D42,'Daftar Akun'!A$6:$B$103,2,FALSE),"") -> Piutang Dagang | F42: 1385250 | I42: =IF(D42="","",COUNTIF($D$6:D42,D42)) -> 3 | J42: =IF(D42="","",D42&"-"&I42) -> 1103-3 | K42: =E43 -> Penjualan | L42: =IFERROR(INDEX($D$6:$D$909,MATCH(1,($A$6:$A$909=A42)*($C$6:$C$909=C42)*($D$6:$D$909<>D42),0)),"") -> 4101
A43: 46235 | B43: INV-108267202 | C43: Penjualan Bunga - Tiara | D43: 4101 | E43: =IFERROR(VLOOKUP(D43,'Daftar Akun'!A$6:$B$103,2,FALSE),"") -> Penjualan | G43: 1385250 | I43: =IF(D43="","",COUNTIF($D$6:D43,D43)) -> 3 | J43: =IF(D43="","",D43&"-"&I43) -> 4101-3 | K43: =E42 -> Piutang Dagang | L43: =IFERROR(INDEX($D$6:$D$909,MATCH(1,($A$6:$A$909=A43)*($C$6:$C$909=C43)*($D$6:$D$909<>D43),0)),"") -> 1103
A44: 46235 | B44: BM-260801-001 | C44: Penjualan Bunga Ke Vendor - Mas Abizar | D44: 1102 | E44: =IFERROR(VLOOKUP(D44,'Daftar Akun'!A$6:$B$103,2,FALSE),"") -> Bank | F44: 48000 | I44: =IF(D44="","",COUNTIF($D$6:D44,D44)) -> 13 | J44: =IF(D44="","",D44&"-"&I44) -> 1102-13 | K44: =E45 -> Penjualan | L44: =IFERROR(INDEX($D$6:$D$909,MATCH(1,($A$6:$A$909=A44)*($C$6:$C$909=C44)*($D$6:$D$909<>D44),0)),"") -> 4101
A45: 46235 | B45: BM-260801-001 | C45: Penjualan Bunga Ke Vendor - Mas Abizar | D45: 4101 | E45: =IFERROR(VLOOKUP(D45,'Daftar Akun'!A$6:$B$103,2,FALSE),"") -> Penjualan | G45: 48000 | I45: =IF(D45="","",COUNTIF($D$6:D45,D45)) -> 4 | J45: =IF(D45="","",D45&"-"&I45) -> 4101-4 | K45: =E44 -> Bank | L45: =IFERROR(INDEX($D$6:$D$909,MATCH(1,($A$6:$A$909=A45)*($C$6:$C$909=C45)*($D$6:$D$909<>D45),0)),"") -> 1102
A46: 46235 | B46: PV-007 | C46: Penjualan Bunga Ke Vendor - Mak Pon | D46: 1102 | E46: =IFERROR(VLOOKUP(D46,'Daftar Akun'!A$6:$B$103,2,FALSE),"") -> Bank | F46: 675000 | I46: =IF(D46="","",COUNTIF($D$6:D46,D46)) -> 14 | J46: =IF(D46="","",D46&"-"&I46) -> 1102-14 | K46: =E47 -> Penjualan | L46: =IFERROR(INDEX($D$6:$D$909,MATCH(1,($A$6:$A$909=A46)*($C$6:$C$909=C46)*($D$6:$D$909<>D46),0)),"") -> 4101
A47: 46235 | B47: PV-007 | C47: Penjualan Bunga Ke Vendor - Mak Pon | D47: 4101 | E47: =IFERROR(VLOOKUP(D47,'Daftar Akun'!A$6:$B$103,2,FALSE),"") -> Penjualan | G47: 675000 | I47: =IF(D47="","",COUNTIF($D$6:D47,D47)) -> 5 | J47: =IF(D47="","",D47&"-"&I47) -> 4101-5 | K47: =E46 -> Bank | L47: =IFERROR(INDEX($D$6:$D$909,MATCH(1,($A$6:$A$909=A47)*($C$6:$C$909=C47)*($D$6:$D$909<>D47),0)),"") -> 1102
A48: 46237 | C48: Pengembalian Dana Talangan Ongkir | D48: 1102 | E48: =IFERROR(VLOOKUP(D48,'Daftar Akun'!A$6:$B$103,2,FALSE),"") -> Bank | F48: 2038519 | I48: =IF(D48="","",COUNTIF($D$6:D48,D48)) -> 15 | J48: =IF(D48="","",D48&"-"&I48) -> 1102-15 | K48: =E49 -> Piutang Ongkir | L48: =IFERROR(INDEX($D$6:$D$909,MATCH(1,($A$6:$A$909=A48)*($C$6:$C$909=C48)*($D$6:$D$909<>D48),0)),"") -> 1107
A49: 46237 | C49: Pengembalian Dana Talangan Ongkir | D49: 1107 | E49: =IFERROR(VLOOKUP(D49,'Daftar Akun'!A$6:$B$103,2,FALSE),"") -> Piutang Ongkir | G49: 2038519 | I49: =IF(D49="","",COUNTIF($D$6:D49,D49)) -> 5 | J49: =IF(D49="","",D49&"-"&I49) -> 1107-5 | K49: =E48 -> Bank | L49: =IFERROR(INDEX($D$6:$D$909,MATCH(1,($A$6:$A$909=A49)*($C$6:$C$909=C49)*($D$6:$D$909<>D49),0)),"") -> 1102
A50: 46237 | C50: Pembayaran Penjualan Tanggal 1 | D50: 1102 | E50: =IFERROR(VLOOKUP(D50,'Daftar Akun'!A$6:$B$103,2,FALSE),"") -> Bank | F50: 2301250 | I50: =IF(D50="","",COUNTIF($D$6:D50,D50)) -> 16 | J50: =IF(D50="","",D50&"-"&I50) -> 1102-16 | K50: =E51 -> Piutang Dagang | L50: =IFERROR(INDEX($D$6:$D$909,MATCH(1,($A$6:$A$909=A50)*($C$6:$C$909=C50)*($D$6:$D$909<>D50),0)),"") -> 1103
A51: 46237 | C51: Pembayaran Penjualan Tanggal 1 | D51: 1103 | E51: =IFERROR(VLOOKUP(D51,'Daftar Akun'!A$6:$B$103,2,FALSE),"") -> Piutang Dagang | G51: 2301250 | I51: =IF(D51="","",COUNTIF($D$6:D51,D51)) -> 4 | J51: =IF(D51="","",D51&"-"&I51) -> 1103-4 | K51: =E50 -> Bank | L51: =IFERROR(INDEX($D$6:$D$909,MATCH(1,($A$6:$A$909=A51)*($C$6:$C$909=C51)*($D$6:$D$909<>D51),0)),"") -> 1102
A52: 46237 | B52: BK-260803-001 | C52: Pembayaran Bunga WKF | D52: 5101 | E52: =IFERROR(VLOOKUP(D52,'Daftar Akun'!A$6:$B$103,2,FALSE),"") -> Pembelian Bunga | F52: 180000 | I52: =IF(D52="","",COUNTIF($D$6:D52,D52)) -> 7 | J52: =IF(D52="","",D52&"-"&I52) -> 5101-7 | K52: =E53 -> Bank | L52: =IFERROR(INDEX($D$6:$D$909,MATCH(1,($A$6:$A$909=A52)*($C$6:$C$909=C52)*($D$6:$D$909<>D52),0)),"") -> 1102
A53: 46237 | B53: BK-260803-001 | C53: Pembayaran Bunga WKF | D53: 1102 | E53: =IFERROR(VLOOKUP(D53,'Daftar Akun'!A$6:$B$103,2,FALSE),"") -> Bank | G53: 180000 | I53: =IF(D53="","",COUNTIF($D$6:D53,D53)) -> 17 | J53: =IF(D53="","",D53&"-"&I53) -> 1102-17 | K53: =E52 -> Pembelian Bunga | L53: =IFERROR(INDEX($D$6:$D$909,MATCH(1,($A$6:$A$909=A53)*($C$6:$C$909=C53)*($D$6:$D$909<>D53),0)),"") -> 5101
A54: 46237 | B54: BK-260803-002 | C54: Pembayaran Bunga WKF | D54: 5101 | E54: =IFERROR(VLOOKUP(D54,'Daftar Akun'!A$6:$B$103,2,FALSE),"") -> Pembelian Bunga | F54: 50000 | I54: =IF(D54="","",COUNTIF($D$6:D54,D54)) -> 8 | J54: =IF(D54="","",D54&"-"&I54) -> 5101-8 | K54: =E55 -> Bank | L54: =IFERROR(INDEX($D$6:$D$909,MATCH(1,($A$6:$A$909=A54)*($C$6:$C$909=C54)*($D$6:$D$909<>D54),0)),"") -> 1102
A55: 46237 | B55: BK-260803-002 | C55: Pembayaran Bunga WKF | D55: 1102 | E55: =IFERROR(VLOOKUP(D55,'Daftar Akun'!A$6:$B$103,2,FALSE),"") -> Bank | G55: 50000 | I55: =IF(D55="","",COUNTIF($D$6:D55,D55)) -> 18 | J55: =IF(D55="","",D55&"-"&I55) -> 1102-18 | K55: =E54 -> Pembelian Bunga | L55: =IFERROR(INDEX($D$6:$D$909,MATCH(1,($A$6:$A$909=A55)*($C$6:$C$909=C55)*($D$6:$D$909<>D55),0)),"") -> 5101
A56: 46237 | C56: Pembayaran Bunga di Grace Rose | D56: 5101 | E56: =IFERROR(VLOOKUP(D56,'Daftar Akun'!A$6:$B$103,2,FALSE),"") -> Pembelian Bunga | F56: 418000 | I56: =IF(D56="","",COUNTIF($D$6:D56,D56)) -> 9 | J56: =IF(D56="","",D56&"-"&I56) -> 5101-9 | K56: =E57 -> Bank | L56: =IFERROR(INDEX($D$6:$D$909,MATCH(1,($A$6:$A$909=A56)*($C$6:$C$909=C56)*($D$6:$D$909<>D56),0)),"") -> 1102
A57: 46237 | C57: Pembayaran Bunga di Grace Rose | D57: 1102 | E57: =IFERROR(VLOOKUP(D57,'Daftar Akun'!A$6:$B$103,2,FALSE),"") -> Bank | G57: 418000 | I57: =IF(D57="","",COUNTIF($D$6:D57,D57)) -> 19 | J57: =IF(D57="","",D57&"-"&I57) -> 1102-19 | K57: =E56 -> Pembelian Bunga | L57: =IFERROR(INDEX($D$6:$D$909,MATCH(1,($A$6:$A$909=A57)*($C$6:$C$909=C57)*($D$6:$D$909<>D57),0)),"") -> 5101
A58: 46237 | C58: Pembelian Bunga di Vendor - Mak Pon | D58: 5101 | E58: =IFERROR(VLOOKUP(D58,'Daftar Akun'!A$6:$B$103,2,FALSE),"") -> Pembelian Bunga | F58: 380000 | I58: =IF(D58="","",COUNTIF($D$6:D58,D58)) -> 10 | J58: =IF(D58="","",D58&"-"&I58) -> 5101-10 | K58: =E59 -> Bank | L58: =IFERROR(INDEX($D$6:$D$909,MATCH(1,($A$6:$A$909=A58)*($C$6:$C$909=C58)*($D$6:$D$909<>D58),0)),"") -> 1102
A59: 46237 | C59: Pembelian Bunga di Vendor - Mak Pon | D59: 1102 | E59: =IFERROR(VLOOKUP(D59,'Daftar Akun'!A$6:$B$103,2,FALSE),"") -> Bank | G59: 380000 | I59: =IF(D59="","",COUNTIF($D$6:D59,D59)) -> 20 | J59: =IF(D59="","",D59&"-"&I59) -> 1102-20 | K59: =E58 -> Pembelian Bunga | L59: =IFERROR(INDEX($D$6:$D$909,MATCH(1,($A$6:$A$909=A59)*($C$6:$C$909=C59)*($D$6:$D$909<>D59),0)),"") -> 5101
A60: 46237 | C60: Pembelian Bunga di Vendor - Pak Sumadi | D60: 5101 | E60: =IFERROR(VLOOKUP(D60,'Daftar Akun'!A$6:$B$103,2,FALSE),"") -> Pembelian Bunga | F60: 240000 | I60: =IF(D60="","",COUNTIF($D$6:D60,D60)) -> 11 | J60: =IF(D60="","",D60&"-"&I60) -> 5101-11 | K60: =E61 -> Bank | L60: =IFERROR(INDEX($D$6:$D$909,MATCH(1,($A$6:$A$909=A60)*($C$6:$C$909=C60)*($D$6:$D$909<>D60),0)),"") -> 1102
A61: 46237 | C61: Pembelian Bunga di Vendor - Pak Sumadi | D61: 1102 | E61: =IFERROR(VLOOKUP(D61,'Daftar Akun'!A$6:$B$103,2,FALSE),"") -> Bank | G61: 240000 | I61: =IF(D61="","",COUNTIF($D$6:D61,D61)) -> 21 | J61: =IF(D61="","",D61&"-"&I61) -> 1102-21 | K61: =E60 -> Pembelian Bunga | L61: =IFERROR(INDEX($D$6:$D$909,MATCH(1,($A$6:$A$909=A61)*($C$6:$C$909=C61)*($D$6:$D$909<>D61),0)),"") -> 5101
A62: 46237 | B62: KK-260803-001 | C62: Pembelian Bunga di Vendor - Pak Benung | D62: 5101 | E62: =IFERROR(VLOOKUP(D62,'Daftar Akun'!A$6:$B$103,2,FALSE),"") -> Pembelian Bunga | F62: 250000 | I62: =IF(D62="","",COUNTIF($D$6:D62,D62)) -> 12 | J62: =IF(D62="","",D62&"-"&I62) -> 5101-12 | K62: =E63 -> Kas | L62: =IFERROR(INDEX($D$6:$D$909,MATCH(1,($A$6:$A$909=A62)*($C$6:$C$909=C62)*($D$6:$D$909<>D62),0)),"") -> 1101
A63: 46237 | B63: KK-260803-001 | C63: Pembelian Bunga di Vendor - Pak Benung | D63: 1101 | E63: =IFERROR(VLOOKUP(D63,'Daftar Akun'!A$6:$B$103,2,FALSE),"") -> Kas | G63: 250000 | I63: =IF(D63="","",COUNTIF($D$6:D63,D63)) -> 6 | J63: =IF(D63="","",D63&"-"&I63) -> 1101-6 | K63: =E62 -> Pembelian Bunga | L63: =IFERROR(INDEX($D$6:$D$909,MATCH(1,($A$6:$A$909=A63)*($C$6:$C$909=C63)*($D$6:$D$909<>D63),0)),"") -> 5101
A64: 46237 | B64: KK-260803-002 | C64: Pembelian Bunga oleh tim operasional | D64: 5101 | E64: =IFERROR(VLOOKUP(D64,'Daftar Akun'!A$6:$B$103,2,FALSE),"") -> Pembelian Bunga | F64: 125000 | I64: =IF(D64="","",COUNTIF($D$6:D64,D64)) -> 13 | J64: =IF(D64="","",D64&"-"&I64) -> 5101-13 | K64: =E65 -> Kas | L64: =IFERROR(INDEX($D$6:$D$909,MATCH(1,($A$6:$A$909=A64)*($C$6:$C$909=C64)*($D$6:$D$909<>D64),0)),"") -> 1101
A65: 46237 | B65: KK-260803-002 | C65: Pembelian Bunga oleh tim operasional | D65: 1101 | E65: =IFERROR(VLOOKUP(D65,'Daftar Akun'!A$6:$B$103,2,FALSE),"") -> Kas | G65: 125000 | I65: =IF(D65="","",COUNTIF($D$6:D65,D65)) -> 7 | J65: =IF(D65="","",D65&"-"&I65) -> 1101-7 | K65: =E64 -> Pembelian Bunga | L65: =IFERROR(INDEX($D$6:$D$909,MATCH(1,($A$6:$A$909=A65)*($C$6:$C$909=C65)*($D$6:$D$909<>D65),0)),"") -> 5101
A66: 46237 | B66: KK-260803-003 | C66: Pembelian Bunga ke Vendor - Mas Felix | D66: 5101 | E66: =IFERROR(VLOOKUP(D66,'Daftar Akun'!A$6:$B$103,2,FALSE),"") -> Pembelian Bunga | F66: 100000 | I66: =IF(D66="","",COUNTIF($D$6:D66,D66)) -> 14 | J66: =IF(D66="","",D66&"-"&I66) -> 5101-14 | K66: =E67 -> Kas | L66: =IFERROR(INDEX($D$6:$D$909,MATCH(1,($A$6:$A$909=A66)*($C$6:$C$909=C66)*($D$6:$D$909<>D66),0)),"") -> 1101
A67: 46237 | B67: KK-260803-003 | C67: Pembelian Bunga ke Vendor - Mas Felix | D67: 1101 | E67: =IFERROR(VLOOKUP(D67,'Daftar Akun'!A$6:$B$103,2,FALSE),"") -> Kas | G67: 100000 | I67: =IF(D67="","",COUNTIF($D$6:D67,D67)) -> 8 | J67: =IF(D67="","",D67&"-"&I67) -> 1101-8 | K67: =E66 -> Pembelian Bunga | L67: =IFERROR(INDEX($D$6:$D$909,MATCH(1,($A$6:$A$909=A67)*($C$6:$C$909=C67)*($D$6:$D$909<>D67),0)),"") -> 5101
A68: 46237 | B68: KM-260803-001 | C68: Penjualan Bunga Ke Vendor - Mas Abizar | D68: 1101 | E68: =IFERROR(VLOOKUP(D68,'Daftar Akun'!A$6:$B$103,2,FALSE),"") -> Kas | F68: 16000 | I68: =IF(D68="","",COUNTIF($D$6:D68,D68)) -> 9 | J68: =IF(D68="","",D68&"-"&I68) -> 1101-9 | K68: =E69 -> Penjualan | L68: =IFERROR(INDEX($D$6:$D$909,MATCH(1,($A$6:$A$909=A68)*($C$6:$C$909=C68)*($D$6:$D$909<>D68),0)),"") -> 4101
A69: 46237 | B69: KM-260803-001 | C69: Penjualan Bunga Ke Vendor - Mas Abizar | D69: 4101 | E69: =IFERROR(VLOOKUP(D69,'Daftar Akun'!A$6:$B$103,2,FALSE),"") -> Penjualan | G69: 16000 | I69: =IF(D69="","",COUNTIF($D$6:D69,D69)) -> 6 | J69: =IF(D69="","",D69&"-"&I69) -> 4101-6 | K69: =E68 -> Kas | L69: =IFERROR(INDEX($D$6:$D$909,MATCH(1,($A$6:$A$909=A69)*($C$6:$C$909=C69)*($D$6:$D$909<>D69),0)),"") -> 1101
A70: 46237 | B70: BB-260903-001 | C70: Pembelian Bunga ke Vendor - Bu Yul | D70: 5101 | E70: =IFERROR(VLOOKUP(D70,'Daftar Akun'!A$6:$B$103,2,FALSE),"") -> Pembelian Bunga | F70: 198000 | I70: =IF(D70="","",COUNTIF($D$6:D70,D70)) -> 15 | J70: =IF(D70="","",D70&"-"&I70) -> 5101-15 | K70: =E71 -> Hutang Dagang | L70: =IFERROR(INDEX($D$6:$D$909,MATCH(1,($A$6:$A$909=A70)*($C$6:$C$909=C70)*($D$6:$D$909<>D70),0)),"") -> 2101
A71: 46237 | B71: BB-260903-001 | C71: Pembelian Bunga ke Vendor - Bu Yul | D71: 2101 | E71: =IFERROR(VLOOKUP(D71,'Daftar Akun'!A$6:$B$103,2,FALSE),"") -> Hutang Dagang | G71: 198000 | I71: =IF(D71="","",COUNTIF($D$6:D71,D71)) -> 1 | J71: =IF(D71="","",D71&"-"&I71) -> 2101-1 | K71: =E70 -> Pembelian Bunga | L71: =IFERROR(INDEX($D$6:$D$909,MATCH(1,($A$6:$A$909=A71)*($C$6:$C$909=C71)*($D$6:$D$909<>D71),0)),"") -> 5101
A72: 46237 | C72: Dana Tambahan dari Mas Bintang | D72: 1101 | E72: =IFERROR(VLOOKUP(D72,'Daftar Akun'!A$6:$B$103,2,FALSE),"") -> Kas | F72: 70000 | I72: =IF(D72="","",COUNTIF($D$6:D72,D72)) -> 10 | J72: =IF(D72="","",D72&"-"&I72) -> 1101-10 | K72: =E73 -> Modal Pemilik | L72: =IFERROR(INDEX($D$6:$D$909,MATCH(1,($A$6:$A$909=A72)*($C$6:$C$909=C72)*($D$6:$D$909<>D72),0)),"") -> 3101
A73: 46237 | C73: Dana Tambahan dari Mas Bintang | D73: 3101 | E73: =IFERROR(VLOOKUP(D73,'Daftar Akun'!A$6:$B$103,2,FALSE),"") -> Modal Pemilik | G73: 70000 | I73: =IF(D73="","",COUNTIF($D$6:D73,D73)) -> 2 | J73: =IF(D73="","",D73&"-"&I73) -> 3101-2 | K73: =E72 -> Kas | L73: =IFERROR(INDEX($D$6:$D$909,MATCH(1,($A$6:$A$909=A73)*($C$6:$C$909=C73)*($D$6:$D$909<>D73),0)),"") -> 1101
A74: 46237 | B74: PV-001 | C74: Penjualan Bunga ke Vendor - Bu Yul | D74: 1103 | E74: =IFERROR(VLOOKUP(D74,'Daftar Akun'!A$6:$B$103,2,FALSE),"") -> Piutang Dagang | F74: 810000 | I74: =IF(D74="","",COUNTIF($D$6:D74,D74)) -> 5 | J74: =IF(D74="","",D74&"-"&I74) -> 1103-5 | K74: =E75 -> Penjualan | L74: =IFERROR(INDEX($D$6:$D$909,MATCH(1,($A$6:$A$909=A74)*($C$6:$C$909=C74)*($D$6:$D$909<>D74),0)),"") -> 4101
A75: 46237 | B75: PV-001 | C75: Penjualan Bunga ke Vendor - Bu Yul | D75: 4101 | E75: =IFERROR(VLOOKUP(D75,'Daftar Akun'!A$6:$B$103,2,FALSE),"") -> Penjualan | G75: 810000 | I75: =IF(D75="","",COUNTIF($D$6:D75,D75)) -> 7 | J75: =IF(D75="","",D75&"-"&I75) -> 4101-7 | K75: =E74 -> Piutang Dagang | L75: =IFERROR(INDEX($D$6:$D$909,MATCH(1,($A$6:$A$909=A75)*($C$6:$C$909=C75)*($D$6:$D$909<>D75),0)),"") -> 1103
A76: 46237 | B76: INV-308268185 | C76: Penjualan Bunga - Rinda | D76: 1103 | E76: =IFERROR(VLOOKUP(D76,'Daftar Akun'!A$6:$B$103,2,FALSE),"") -> Piutang Dagang | F76: 645000 | I76: =IF(D76="","",COUNTIF($D$6:D76,D76)) -> 6 | J76: =IF(D76="","",D76&"-"&I76) -> 1103-6 | K76: =E77 -> Penjualan | L76: =IFERROR(INDEX($D$6:$D$909,MATCH(1,($A$6:$A$909=A76)*($C$6:$C$909=C76)*($D$6:$D$909<>D76),0)),"") -> 4101
A77: 46237 | B77: INV-308268185 | C77: Penjualan Bunga - Rinda | D77: 4101 | E77: =IFERROR(VLOOKUP(D77,'Daftar Akun'!A$6:$B$103,2,FALSE),"") -> Penjualan | G77: 645000 | I77: =IF(D77="","",COUNTIF($D$6:D77,D77)) -> 8 | J77: =IF(D77="","",D77&"-"&I77) -> 4101-8 | K77: =E76 -> Piutang Dagang | L77: =IFERROR(INDEX($D$6:$D$909,MATCH(1,($A$6:$A$909=A77)*($C$6:$C$909=C77)*($D$6:$D$909<>D77),0)),"") -> 1103
A78: 46237 | B78: INV-308261228 | C78: Penjualan Bunga - Regina | D78: 1103 | E78: =IFERROR(VLOOKUP(D78,'Daftar Akun'!A$6:$B$103,2,FALSE),"") -> Piutang Dagang | F78: 682250 | I78: =IF(D78="","",COUNTIF($D$6:D78,D78)) -> 7 | J78: =IF(D78="","",D78&"-"&I78) -> 1103-7 | K78: =E79 -> Penjualan | L78: =IFERROR(INDEX($D$6:$D$909,MATCH(1,($A$6:$A$909=A78)*($C$6:$C$909=C78)*($D$6:$D$909<>D78),0)),"") -> 4101
A79: 46237 | B79: INV-308261228 | C79: Penjualan Bunga - Regina | D79: 4101 | E79: =IFERROR(VLOOKUP(D79,'Daftar Akun'!A$6:$B$103,2,FALSE),"") -> Penjualan | G79: 682250 | I79: =IF(D79="","",COUNTIF($D$6:D79,D79)) -> 9 | J79: =IF(D79="","",D79&"-"&I79) -> 4101-9 | K79: =E78 -> Piutang Dagang | L79: =IFERROR(INDEX($D$6:$D$909,MATCH(1,($A$6:$A$909=A79)*($C$6:$C$909=C79)*($D$6:$D$909<>D79),0)),"") -> 1103
A80: 46237 | C80: Pembelian Bunga ke Vendor - Mba Yeti | D80: 5101 | E80: =IFERROR(VLOOKUP(D80,'Daftar Akun'!A$6:$B$103,2,FALSE),"") -> Pembelian Bunga | F80: 390000 | I80: =IF(D80="","",COUNTIF($D$6:D80,D80)) -> 16 | J80: =IF(D80="","",D80&"-"&I80) -> 5101-16 | K80: =E81 -> Bank | L80: =IFERROR(INDEX($D$6:$D$909,MATCH(1,($A$6:$A$909=A80)*($C$6:$C$909=C80)*($D$6:$D$909<>D80),0)),"") -> 1102
A81: 46237 | C81: Pembelian Bunga ke Vendor - Mba Yeti | D81: 1102 | E81: =IFERROR(VLOOKUP(D81,'Daftar Akun'!A$6:$B$103,2,FALSE),"") -> Bank | G81: 390000 | I81: =IF(D81="","",COUNTIF($D$6:D81,D81)) -> 22 | J81: =IF(D81="","",D81&"-"&I81) -> 1102-22 | K81: =E80 -> Pembelian Bunga | L81: =IFERROR(INDEX($D$6:$D$909,MATCH(1,($A$6:$A$909=A81)*($C$6:$C$909=C81)*($D$6:$D$909<>D81),0)),"") -> 5101
A82: 46238 | B82: BK-260804-001 | C82: Pembelian Bunga ke Omniflora | D82: 5101 | E82: =IFERROR(VLOOKUP(D82,'Daftar Akun'!A$6:$B$103,2,FALSE),"") -> Pembelian Bunga | F82: 930000 | I82: =IF(D82="","",COUNTIF($D$6:D82,D82)) -> 17 | J82: =IF(D82="","",D82&"-"&I82) -> 5101-17 | K82: =E83 -> Bank | L82: =IFERROR(INDEX($D$6:$D$909,MATCH(1,($A$6:$A$909=A82)*($C$6:$C$909=C82)*($D$6:$D$909<>D82),0)),"") -> 1102
A83: 46238 | B83: BK-260804-001 | C83: Pembelian Bunga ke Omniflora | D83: 1102 | E83: =IFERROR(VLOOKUP(D83,'Daftar Akun'!A$6:$B$103,2,FALSE),"") -> Bank | G83: 930000 | I83: =IF(D83="","",COUNTIF($D$6:D83,D83)) -> 23 | J83: =IF(D83="","",D83&"-"&I83) -> 1102-23 | K83: =E82 -> Pembelian Bunga | L83: =IFERROR(INDEX($D$6:$D$909,MATCH(1,($A$6:$A$909=A83)*($C$6:$C$909=C83)*($D$6:$D$909<>D83),0)),"") -> 5101
A84: 46238 | C84: Pembayaran Ongkir Pembelian Bunga - Daytrans | D84: 5103 | E84: =IFERROR(VLOOKUP(D84,'Daftar Akun'!A$6:$B$103,2,FALSE),"") -> Beban Angkut Pembelian | F84: 87500 | I84: =IF(D84="","",COUNTIF($D$6:D84,D84)) -> 2 | J84: =IF(D84="","",D84&"-"&I84) -> 5103-2 | K84: =E85 -> Bank | L84: =IFERROR(INDEX($D$6:$D$909,MATCH(1,($A$6:$A$909=A84)*($C$6:$C$909=C84)*($D$6:$D$909<>D84),0)),"") -> 1102
A85: 46238 | C85: Pembayaran Ongkir Pembelian Bunga - Daytrans | D85: 1102 | E85: =IFERROR(VLOOKUP(D85,'Daftar Akun'!A$6:$B$103,2,FALSE),"") -> Bank | G85: 87500 | I85: =IF(D85="","",COUNTIF($D$6:D85,D85)) -> 24 | J85: =IF(D85="","",D85&"-"&I85) -> 1102-24 | K85: =E84 -> Beban Angkut Pembelian | L85: =IFERROR(INDEX($D$6:$D$909,MATCH(1,($A$6:$A$909=A85)*($C$6:$C$909=C85)*($D$6:$D$909<>D85),0)),"") -> 5103
A86: 46238 | B86: KK-260804-002 | C86: Pembelian Bunga oleh tim operasional | D86: 5101 | E86: =IFERROR(VLOOKUP(D86,'Daftar Akun'!A$6:$B$103,2,FALSE),"") -> Pembelian Bunga | F86: 245000 | I86: =IF(D86="","",COUNTIF($D$6:D86,D86)) -> 18 | J86: =IF(D86="","",D86&"-"&I86) -> 5101-18 | K86: =E87 -> Kas | L86: =IFERROR(INDEX($D$6:$D$909,MATCH(1,($A$6:$A$909=A86)*($C$6:$C$909=C86)*($D$6:$D$909<>D86),0)),"") -> 1101
A87: 46238 | B87: KK-260804-002 | C87: Pembelian Bunga oleh tim operasional | D87: 1101 | E87: =IFERROR(VLOOKUP(D87,'Daftar Akun'!A$6:$B$103,2,FALSE),"") -> Kas | G87: 245000 | I87: =IF(D87="","",COUNTIF($D$6:D87,D87)) -> 11 | J87: =IF(D87="","",D87&"-"&I87) -> 1101-11 | K87: =E86 -> Pembelian Bunga | L87: =IFERROR(INDEX($D$6:$D$909,MATCH(1,($A$6:$A$909=A87)*($C$6:$C$909=C87)*($D$6:$D$909<>D87),0)),"") -> 5101
A88: 46238 | B88: KK-260804-003 | C88: Ganti BBM Mas Refan - ambil bunga ke Daytrans | D88: 6108 | E88: =IFERROR(VLOOKUP(D88,'Daftar Akun'!A$6:$B$103,2,FALSE),"") -> Beban Lain-Lain | F88: 36000 | I88: =IF(D88="","",COUNTIF($D$6:D88,D88)) -> 2 | J88: =IF(D88="","",D88&"-"&I88) -> 6108-2 | K88: =E89 -> Kas | L88: =IFERROR(INDEX($D$6:$D$909,MATCH(1,($A$6:$A$909=A88)*($C$6:$C$909=C88)*($D$6:$D$909<>D88),0)),"") -> 1101
A89: 46238 | B89: KK-260804-003 | C89: Ganti BBM Mas Refan - ambil bunga ke Daytrans | D89: 1101 | E89: =IFERROR(VLOOKUP(D89,'Daftar Akun'!A$6:$B$103,2,FALSE),"") -> Kas | G89: 36000 | I89: =IF(D89="","",COUNTIF($D$6:D89,D89)) -> 12 | J89: =IF(D89="","",D89&"-"&I89) -> 1101-12 | K89: =E88 -> Beban Lain-Lain | L89: =IFERROR(INDEX($D$6:$D$909,MATCH(1,($A$6:$A$909=A89)*($C$6:$C$909=C89)*($D$6:$D$909<>D89),0)),"") -> 6108
A90: 46238 | B90: KK-260804-001 | C90: Pembelian BBM Motor untuk Operasional | D90: 6108 | E90: =IFERROR(VLOOKUP(D90,'Daftar Akun'!A$6:$B$103,2,FALSE),"") -> Beban Lain-Lain | F90: 30000 | I90: =IF(D90="","",COUNTIF($D$6:D90,D90)) -> 3 | J90: =IF(D90="","",D90&"-"&I90) -> 6108-3 | K90: =E91 -> Kas | L90: =IFERROR(INDEX($D$6:$D$909,MATCH(1,($A$6:$A$909=A90)*($C$6:$C$909=C90)*($D$6:$D$909<>D90),0)),"") -> 1101
A91: 46238 | B91: KK-260804-001 | C91: Pembelian BBM Motor untuk Operasional | D91: 1101 | E91: =IFERROR(VLOOKUP(D91,'Daftar Akun'!A$6:$B$103,2,FALSE),"") -> Kas | G91: 30000 | I91: =IF(D91="","",COUNTIF($D$6:D91,D91)) -> 13 | J91: =IF(D91="","",D91&"-"&I91) -> 1101-13 | K91: =E90 -> Beban Lain-Lain | L91: =IFERROR(INDEX($D$6:$D$909,MATCH(1,($A$6:$A$909=A91)*($C$6:$C$909=C91)*($D$6:$D$909<>D91),0)),"") -> 6108
A92: 46238 | C92: Pembelian Paket Data - Mas Refan | D92: 6108 | E92: =IFERROR(VLOOKUP(D92,'Daftar Akun'!A$6:$B$103,2,FALSE),"") -> Beban Lain-Lain | F92: 2800 | I92: =IF(D92="","",COUNTIF($D$6:D92,D92)) -> 4 | J92: =IF(D92="","",D92&"-"&I92) -> 6108-4 | K92: =E93 -> Bank | L92: =IFERROR(INDEX($D$6:$D$909,MATCH(1,($A$6:$A$909=A92)*($C$6:$C$909=C92)*($D$6:$D$909<>D92),0)),"") -> 1102
A93: 46238 | C93: Pembelian Paket Data - Mas Refan | D93: 1102 | E93: =IFERROR(VLOOKUP(D93,'Daftar Akun'!A$6:$B$103,2,FALSE),"") -> Bank | G93: 2800 | I93: =IF(D93="","",COUNTIF($D$6:D93,D93)) -> 25 | J93: =IF(D93="","",D93&"-"&I93) -> 1102-25 | K93: =E92 -> Beban Lain-Lain | L93: =IFERROR(INDEX($D$6:$D$909,MATCH(1,($A$6:$A$909=A93)*($C$6:$C$909=C93)*($D$6:$D$909<>D93),0)),"") -> 6108
A94: 46238 | B94: BB-260804-001 | C94: Pembelian Bunga ke Vendor - Bu Yul | D94: 5101 | E94: =IFERROR(VLOOKUP(D94,'Daftar Akun'!A$6:$B$103,2,FALSE),"") -> Pembelian Bunga | F94: 136000 | I94: =IF(D94="","",COUNTIF($D$6:D94,D94)) -> 19 | J94: =IF(D94="","",D94&"-"&I94) -> 5101-19 | K94: =E95 -> Hutang Dagang | L94: =IFERROR(INDEX($D$6:$D$909,MATCH(1,($A$6:$A$909=A94)*($C$6:$C$909=C94)*($D$6:$D$909<>D94),0)),"") -> 2101
A95: 46238 | B95: BB-260804-001 | C95: Pembelian Bunga ke Vendor - Bu Yul | D95: 2101 | E95: =IFERROR(VLOOKUP(D95,'Daftar Akun'!A$6:$B$103,2,FALSE),"") -> Hutang Dagang | G95: 136000 | I95: =IF(D95="","",COUNTIF($D$6:D95,D95)) -> 2 | J95: =IF(D95="","",D95&"-"&I95) -> 2101-2 | K95: =E94 -> Pembelian Bunga | L95: =IFERROR(INDEX($D$6:$D$909,MATCH(1,($A$6:$A$909=A95)*($C$6:$C$909=C95)*($D$6:$D$909<>D95),0)),"") -> 5101
A96: 46238 | C96: Talangan Pembayaran Ongkir DMK Cargo | D96: 1107 | E96: =IFERROR(VLOOKUP(D96,'Daftar Akun'!A$6:$B$103,2,FALSE),"") -> Piutang Ongkir | F96: 1412159 | I96: =IF(D96="","",COUNTIF($D$6:D96,D96)) -> 6 | J96: =IF(D96="","",D96&"-"&I96) -> 1107-6 | K96: =E97 -> Bank | L96: =IFERROR(INDEX($D$6:$D$909,MATCH(1,($A$6:$A$909=A96)*($C$6:$C$909=C96)*($D$6:$D$909<>D96),0)),"") -> 1102
A97: 46238 | C97: Talangan Pembayaran Ongkir DMK Cargo | D97: 1102 | E97: =IFERROR(VLOOKUP(D97,'Daftar Akun'!A$6:$B$103,2,FALSE),"") -> Bank | G97: 1412159 | I97: =IF(D97="","",COUNTIF($D$6:D97,D97)) -> 26 | J97: =IF(D97="","",D97&"-"&I97) -> 1102-26 | K97: =E96 -> Piutang Ongkir | L97: =IFERROR(INDEX($D$6:$D$909,MATCH(1,($A$6:$A$909=A97)*($C$6:$C$909=C97)*($D$6:$D$909<>D97),0)),"") -> 1107
A98: 46238 | C98: Penjualan Bunga Tanggal 3 | D98: 1102 | E98: =IFERROR(VLOOKUP(D98,'Daftar Akun'!A$6:$B$103,2,FALSE),"") -> Bank | F98: 1327250 | I98: =IF(D98="","",COUNTIF($D$6:D98,D98)) -> 27 | J98: =IF(D98="","",D98&"-"&I98) -> 1102-27 | K98: =E99 -> Piutang Dagang | L98: =IFERROR(INDEX($D$6:$D$909,MATCH(1,($A$6:$A$909=A98)*($C$6:$C$909=C98)*($D$6:$D$909<>D98),0)),"") -> 1103
A99: 46238 | C99: Penjualan Bunga Tanggal 3 | D99: 1103 | E99: =IFERROR(VLOOKUP(D99,'Daftar Akun'!A$6:$B$103,2,FALSE),"") -> Piutang Dagang | G99: 1327250 | I99: =IF(D99="","",COUNTIF($D$6:D99,D99)) -> 8 | J99: =IF(D99="","",D99&"-"&I99) -> 1103-8 | K99: =E98 -> Bank | L99: =IFERROR(INDEX($D$6:$D$909,MATCH(1,($A$6:$A$909=A99)*($C$6:$C$909=C99)*($D$6:$D$909<>D99),0)),"") -> 1102
A100: 46238 | C100: Pengembalian Dana Talangan Ongkir | D100: 1102 | E100: =IFERROR(VLOOKUP(D100,'Daftar Akun'!A$6:$B$103,2,FALSE),"") -> Bank | F100: 1412159 | I100: =IF(D100="","",COUNTIF($D$6:D100,D100)) -> 28 | J100: =IF(D100="","",D100&"-"&I100) -> 1102-28 | K100: =E101 -> Piutang Ongkir | L100: =IFERROR(INDEX($D$6:$D$909,MATCH(1,($A$6:$A$909=A100)*($C$6:$C$909=C100)*($D$6:$D$909<>D100),0)),"") -> 1107
A101: 46238 | C101: Pengembalian Dana Talangan Ongkir | D101: 1107 | E101: =IFERROR(VLOOKUP(D101,'Daftar Akun'!A$6:$B$103,2,FALSE),"") -> Piutang Ongkir | G101: 1412159 | I101: =IF(D101="","",COUNTIF($D$6:D101,D101)) -> 7 | J101: =IF(D101="","",D101&"-"&I101) -> 1107-7 | K101: =E100 -> Bank | L101: =IFERROR(INDEX($D$6:$D$909,MATCH(1,($A$6:$A$909=A101)*($C$6:$C$909=C101)*($D$6:$D$909<>D101),0)),"") -> 1102
...

Sheet Buku Besar
A1: PT BIGATRI INDOFLORA PACIFIC
A2: BLOOMORIST
A3: BUKU BESAR Periode Agustus 2026
A5: Pilih Kode Akun: | B5: 1102 | C5: Nama Akun: | D5: {=IFERROR(INDEX('Daftar Akun'!$B$6:$B$62,MATCH($B$5,'Daftar Akun'!$A$6:$A$62,0)),"")} -> Bank
A6: Saldo Normal: | B6: {=IFERROR(INDEX('Daftar Akun'!$D$6:$D$62,MATCH($B$5,'Daftar Akun'!$A$6:$A$62,0)),"")} -> Debit | C6: Saldo Akhir: | D6: =IF($B$6="Debit",SUMIFS('Jurnal Umum'!$F$6:$F$909,'Jurnal Umum'!$D$6:$D$909,$B$5)-SUMIFS('Jurnal Umum'!$G$6:$G$909,'Jurnal Umum'!$D$6:$D$909,$B$5),SUMIFS('Jurnal Umum'!$G$6:$G$909,'Jurnal Umum'!$D$6:$D$909,$B$5)-SUMIFS('Jurnal Umum'!$F$6:$F$909,'Jurnal Umum'!$D$6:$D$909,$B$5)) -> 13450950
A8: Tanggal | B8: Keterangan | C8: No. Bukti | D8: Debit (Rp) | E8: Kredit (Rp) | F8: Saldo (Rp) | H8: Baris JU
A9: {=IF($H9="","",INDEX('Jurnal Umum'!$A$6:$A$2564,$H9-5))} -> 46235 | B9: {=IF($H9="","",IFERROR(INDEX('Jurnal Umum'!$C$6:$C$2564, MATCH(1, ('Jurnal Umum'!$A$6:$A$2564=INDEX('Jurnal Umum'!$A$6:$A$2564,$H9-5)) * ('Jurnal Umum'!$C$6:$C$2564=INDEX('Jurnal Umum'!$C$6:$C$2564,$H9-5)) * ('Jurnal Umum'!$D$6:$D$2564<>$B$5) ,0)),""))} -> Modal Awal Bulan Agustus 2026 | C9: {=IF($H9="","",INDEX('Jurnal Umum'!$B$6:$B$2564,$H9-5))} | D9: {=IF($H9="","",IF(INDEX('Jurnal Umum'!$F$6:$F$2564,$H9-5)="",0,INDEX('Jurnal Umum'!$F$6:$F$2564,$H9-5)))} -> 59266000 | E9: {=IF($H9="","",IF(INDEX('Jurnal Umum'!$G$6:$G$2564,$H9-5)="",0,INDEX('Jurnal Umum'!$G$6:$G$2564,$H9-5)))} -> 0 | F9: =IF($H9="","",IF($B$6="Debit",SUM($D$9:D9)-SUM($E$9:E9),SUM($E$9:E9)-SUM($D$9:D9))) -> 59266000 | H9: =IFERROR(MATCH($B$5&"-"&1,'Jurnal Umum'!$J$6:$J$909,0)+5,"") -> 6
A10: {=IF($H10="","",INDEX('Jurnal Umum'!$A$6:$A$2564,$H10-5))} -> 46235 | B10: {=IF($H10="","",IFERROR(INDEX('Jurnal Umum'!$C$6:$C$2564, MATCH(1, ('Jurnal Umum'!$A$6:$A$2564=INDEX('Jurnal Umum'!$A$6:$A$2564,$H10-5)) * ('Jurnal Umum'!$C$6:$C$2564=INDEX('Jurnal Umum'!$C$6:$C$2564,$H10-5)) * ('Jurnal Umum'!$D$6:$D$2564<>$B$5) ,0)),""))} -> Pinjaman Modal Greenhouse | C10: {=IF($H10="","",INDEX('Jurnal Umum'!$B$6:$B$2564,$H10-5))} | D10: {=IF($H10="","",IF(INDEX('Jurnal Umum'!$F$6:$F$2564,$H10-5)="",0,INDEX('Jurnal Umum'!$F$6:$F$2564,$H10-5)))} -> 0 | E10: {=IF($H10="","",IF(INDEX('Jurnal Umum'!$G$6:$G$2564,$H10-5)="",0,INDEX('Jurnal Umum'!$G$6:$G$2564,$H10-5)))} -> 33060000 | F10: =IF($H10="","",IF($B$6="Debit",SUM($D$9:D10)-SUM($E$9:E10),SUM($E$9:E10)-SUM($D$9:D10))) -> 26206000 | H10: =IFERROR(MATCH($B$5&"-"&2,'Jurnal Umum'!$J$6:$J$909,0)+5,"") -> 9
A11: {=IF($H11="","",INDEX('Jurnal Umum'!$A$6:$A$2564,$H11-5))} -> 46235 | B11: {=IF($H11="","",IFERROR(INDEX('Jurnal Umum'!$C$6:$C$2564, MATCH(1, ('Jurnal Umum'!$A$6:$A$2564=INDEX('Jurnal Umum'!$A$6:$A$2564,$H11-5)) * ('Jurnal Umum'!$C$6:$C$2564=INDEX('Jurnal Umum'!$C$6:$C$2564,$H11-5)) * ('Jurnal Umum'!$D$6:$D$2564<>$B$5) ,0)),""))} -> Abunemen Petani Aster - Mas Yuli | C11: {=IF($H11="","",INDEX('Jurnal Umum'!$B$6:$B$2564,$H11-5))} | D11: {=IF($H11="","",IF(INDEX('Jurnal Umum'!$F$6:$F$2564,$H11-5)="",0,INDEX('Jurnal Umum'!$F$6:$F$2564,$H11-5)))} -> 0 | E11: {=IF($H11="","",IF(INDEX('Jurnal Umum'!$G$6:$G$2564,$H11-5)="",0,INDEX('Jurnal Umum'!$G$6:$G$2564,$H11-5)))} -> 7000000 | F11: =IF($H11="","",IF($B$6="Debit",SUM($D$9:D11)-SUM($E$9:E11),SUM($E$9:E11)-SUM($D$9:D11))) -> 19206000 | H11: =IFERROR(MATCH($B$5&"-"&3,'Jurnal Umum'!$J$6:$J$909,0)+5,"") -> 11
A12: {=IF($H12="","",INDEX('Jurnal Umum'!$A$6:$A$2564,$H12-5))} -> 46235 | B12: {=IF($H12="","",IFERROR(INDEX('Jurnal Umum'!$C$6:$C$2564, MATCH(1, ('Jurnal Umum'!$A$6:$A$2564=INDEX('Jurnal Umum'!$A$6:$A$2564,$H12-5)) * ('Jurnal Umum'!$C$6:$C$2564=INDEX('Jurnal Umum'!$C$6:$C$2564,$H12-5)) * ('Jurnal Umum'!$D$6:$D$2564<>$B$5) ,0)),""))} -> Talangan Ongkir DMK Cargo | C12: {=IF($H12="","",INDEX('Jurnal Umum'!$B$6:$B$2564,$H12-5))} | D12: {=IF($H12="","",IF(INDEX('Jurnal Umum'!$F$6:$F$2564,$H12-5)="",0,INDEX('Jurnal Umum'!$F$6:$F$2564,$H12-5)))} -> 0 | E12: {=IF($H12="","",IF(INDEX('Jurnal Umum'!$G$6:$G$2564,$H12-5)="",0,INDEX('Jurnal Umum'!$G$6:$G$2564,$H12-5)))} -> 854295 | F12: =IF($H12="","",IF($B$6="Debit",SUM($D$9:D12)-SUM($E$9:E12),SUM($E$9:E12)-SUM($D$9:D12))) -> 18351705 | H12: =IFERROR(MATCH($B$5&"-"&4,'Jurnal Umum'!$J$6:$J$909,0)+5,"") -> 13
A13: {=IF($H13="","",INDEX('Jurnal Umum'!$A$6:$A$2564,$H13-5))} -> 46235 | B13: {=IF($H13="","",IFERROR(INDEX('Jurnal Umum'!$C$6:$C$2564, MATCH(1, ('Jurnal Umum'!$A$6:$A$2564=INDEX('Jurnal Umum'!$A$6:$A$2564,$H13-5)) * ('Jurnal Umum'!$C$6:$C$2564=INDEX('Jurnal Umum'!$C$6:$C$2564,$H13-5)) * ('Jurnal Umum'!$D$6:$D$2564<>$B$5) ,0)),""))} -> Pembayaran Bunga Pikok - Bu Nisa | C13: {=IF($H13="","",INDEX('Jurnal Umum'!$B$6:$B$2564,$H13-5))} | D13: {=IF($H13="","",IF(INDEX('Jurnal Umum'!$F$6:$F$2564,$H13-5)="",0,INDEX('Jurnal Umum'!$F$6:$F$2564,$H13-5)))} -> 0 | E13: {=IF($H13="","",IF(INDEX('Jurnal Umum'!$G$6:$G$2564,$H13-5)="",0,INDEX('Jurnal Umum'!$G$6:$G$2564,$H13-5)))} -> 1050000 | F13: =IF($H13="","",IF($B$6="Debit",SUM($D$9:D13)-SUM($E$9:E13),SUM($E$9:E13)-SUM($D$9:D13))) -> 17301705 | H13: =IFERROR(MATCH($B$5&"-"&5,'Jurnal Umum'!$J$6:$J$909,0)+5,"") -> 15
A14: {=IF($H14="","",INDEX('Jurnal Umum'!$A$6:$A$2564,$H14-5))} -> 46235 | B14: {=IF($H14="","",IFERROR(INDEX('Jurnal Umum'!$C$6:$C$2564, MATCH(1, ('Jurnal Umum'!$A$6:$A$2564=INDEX('Jurnal Umum'!$A$6:$A$2564,$H14-5)) * ('Jurnal Umum'!$C$6:$C$2564=INDEX('Jurnal Umum'!$C$6:$C$2564,$H14-5)) * ('Jurnal Umum'!$D$6:$D$2564<>$B$5) ,0)),""))} -> Pembayaran Bunga Bromo - Nongkojajar | C14: {=IF($H14="","",INDEX('Jurnal Umum'!$B$6:$B$2564,$H14-5))} | D14: {=IF($H14="","",IF(INDEX('Jurnal Umum'!$F$6:$F$2564,$H14-5)="",0,INDEX('Jurnal Umum'!$F$6:$F$2564,$H14-5)))} -> 0 | E14: {=IF($H14="","",IF(INDEX('Jurnal Umum'!$G$6:$G$2564,$H14-5)="",0,INDEX('Jurnal Umum'!$G$6:$G$2564,$H14-5)))} -> 1428000 | F14: =IF($H14="","",IF($B$6="Debit",SUM($D$9:D14)-SUM($E$9:E14),SUM($E$9:E14)-SUM($D$9:D14))) -> 15873705 | H14: =IFERROR(MATCH($B$5&"-"&6,'Jurnal Umum'!$J$6:$J$909,0)+5,"") -> 17
A15: {=IF($H15="","",INDEX('Jurnal Umum'!$A$6:$A$2564,$H15-5))} -> 46235 | B15: {=IF($H15="","",IFERROR(INDEX('Jurnal Umum'!$C$6:$C$2564, MATCH(1, ('Jurnal Umum'!$A$6:$A$2564=INDEX('Jurnal Umum'!$A$6:$A$2564,$H15-5)) * ('Jurnal Umum'!$C$6:$C$2564=INDEX('Jurnal Umum'!$C$6:$C$2564,$H15-5)) * ('Jurnal Umum'!$D$6:$D$2564<>$B$5) ,0)),""))} -> Pembelian Bunga di Om Toha | C15: {=IF($H15="","",INDEX('Jurnal Umum'!$B$6:$B$2564,$H15-5))} | D15: {=IF($H15="","",IF(INDEX('Jurnal Umum'!$F$6:$F$2564,$H15-5)="",0,INDEX('Jurnal Umum'!$F$6:$F$2564,$H15-5)))} -> 0 | E15: {=IF($H15="","",IF(INDEX('Jurnal Umum'!$G$6:$G$2564,$H15-5)="",0,INDEX('Jurnal Umum'!$G$6:$G$2564,$H15-5)))} -> 650000 | F15: =IF($H15="","",IF($B$6="Debit",SUM($D$9:D15)-SUM($E$9:E15),SUM($E$9:E15)-SUM($D$9:D15))) -> 15223705 | H15: =IFERROR(MATCH($B$5&"-"&7,'Jurnal Umum'!$J$6:$J$909,0)+5,"") -> 19
A16: {=IF($H16="","",INDEX('Jurnal Umum'!$A$6:$A$2564,$H16-5))} -> 46235 | B16: {=IF($H16="","",IFERROR(INDEX('Jurnal Umum'!$C$6:$C$2564, MATCH(1, ('Jurnal Umum'!$A$6:$A$2564=INDEX('Jurnal Umum'!$A$6:$A$2564,$H16-5)) * ('Jurnal Umum'!$C$6:$C$2564=INDEX('Jurnal Umum'!$C$6:$C$2564,$H16-5)) * ('Jurnal Umum'!$D$6:$D$2564<>$B$5) ,0)),""))} -> Pembelian Bunga di WKF | C16: {=IF($H16="","",INDEX('Jurnal Umum'!$B$6:$B$2564,$H16-5))} -> BK-260801-001 | D16: {=IF($H16="","",IF(INDEX('Jurnal Umum'!$F$6:$F$2564,$H16-5)="",0,INDEX('Jurnal Umum'!$F$6:$F$2564,$H16-5)))} -> 0 | E16: {=IF($H16="","",IF(INDEX('Jurnal Umum'!$G$6:$G$2564,$H16-5)="",0,INDEX('Jurnal Umum'!$G$6:$G$2564,$H16-5)))} -> 282000 | F16: =IF($H16="","",IF($B$6="Debit",SUM($D$9:D16)-SUM($E$9:E16),SUM($E$9:E16)-SUM($D$9:D16))) -> 14941705 | H16: =IFERROR(MATCH($B$5&"-"&8,'Jurnal Umum'!$J$6:$J$909,0)+5,"") -> 21
A17: {=IF($H17="","",INDEX('Jurnal Umum'!$A$6:$A$2564,$H17-5))} -> 46235 | B17: {=IF($H17="","",IFERROR(INDEX('Jurnal Umum'!$C$6:$C$2564, MATCH(1, ('Jurnal Umum'!$A$6:$A$2564=INDEX('Jurnal Umum'!$A$6:$A$2564,$H17-5)) * ('Jurnal Umum'!$C$6:$C$2564=INDEX('Jurnal Umum'!$C$6:$C$2564,$H17-5)) * ('Jurnal Umum'!$D$6:$D$2564<>$B$5) ,0)),""))} -> Pengembalian Dana Talangan Ongkir | C17: {=IF($H17="","",INDEX('Jurnal Umum'!$B$6:$B$2564,$H17-5))} | D17: {=IF($H17="","",IF(INDEX('Jurnal Umum'!$F$6:$F$2564,$H17-5)="",0,INDEX('Jurnal Umum'!$F$6:$F$2564,$H17-5)))} -> 854295 | E17: {=IF($H17="","",IF(INDEX('Jurnal Umum'!$G$6:$G$2564,$H17-5)="",0,INDEX('Jurnal Umum'!$G$6:$G$2564,$H17-5)))} -> 0 | F17: =IF($H17="","",IF($B$6="Debit",SUM($D$9:D17)-SUM($E$9:E17),SUM($E$9:E17)-SUM($D$9:D17))) -> 15796000 | H17: =IFERROR(MATCH($B$5&"-"&9,'Jurnal Umum'!$J$6:$J$909,0)+5,"") -> 22
A18: {=IF($H18="","",INDEX('Jurnal Umum'!$A$6:$A$2564,$H18-5))} -> 46235 | B18: {=IF($H18="","",IFERROR(INDEX('Jurnal Umum'!$C$6:$C$2564, MATCH(1, ('Jurnal Umum'!$A$6:$A$2564=INDEX('Jurnal Umum'!$A$6:$A$2564,$H18-5)) * ('Jurnal Umum'!$C$6:$C$2564=INDEX('Jurnal Umum'!$C$6:$C$2564,$H18-5)) * ('Jurnal Umum'!$D$6:$D$2564<>$B$5) ,0)),""))} -> Tarik Tunai untuk kas operasional | C18: {=IF($H18="","",INDEX('Jurnal Umum'!$B$6:$B$2564,$H18-5))} | D18: {=IF($H18="","",IF(INDEX('Jurnal Umum'!$F$6:$F$2564,$H18-5)="",0,INDEX('Jurnal Umum'!$F$6:$F$2564,$H18-5)))} -> 0 | E18: {=IF($H18="","",IF(INDEX('Jurnal Umum'!$G$6:$G$2564,$H18-5)="",0,INDEX('Jurnal Umum'!$G$6:$G$2564,$H18-5)))} -> 1437000 | F18: =IF($H18="","",IF($B$6="Debit",SUM($D$9:D18)-SUM($E$9:E18),SUM($E$9:E18)-SUM($D$9:D18))) -> 14359000 | H18: =IFERROR(MATCH($B$5&"-"&10,'Jurnal Umum'!$J$6:$J$909,0)+5,"") -> 25
A19: {=IF($H19="","",INDEX('Jurnal Umum'!$A$6:$A$2564,$H19-5))} -> 46235 | B19: {=IF($H19="","",IFERROR(INDEX('Jurnal Umum'!$C$6:$C$2564, MATCH(1, ('Jurnal Umum'!$A$6:$A$2564=INDEX('Jurnal Umum'!$A$6:$A$2564,$H19-5)) * ('Jurnal Umum'!$C$6:$C$2564=INDEX('Jurnal Umum'!$C$6:$C$2564,$H19-5)) * ('Jurnal Umum'!$D$6:$D$2564<>$B$5) ,0)),""))} -> Talangan Ongkir DMK Cargo | C19: {=IF($H19="","",INDEX('Jurnal Umum'!$B$6:$B$2564,$H19-5))} | D19: {=IF($H19="","",IF(INDEX('Jurnal Umum'!$F$6:$F$2564,$H19-5)="",0,INDEX('Jurnal Umum'!$F$6:$F$2564,$H19-5)))} -> 0 | E19: {=IF($H19="","",IF(INDEX('Jurnal Umum'!$G$6:$G$2564,$H19-5)="",0,INDEX('Jurnal Umum'!$G$6:$G$2564,$H19-5)))} -> 1968519 | F19: =IF($H19="","",IF($B$6="Debit",SUM($D$9:D19)-SUM($E$9:E19),SUM($E$9:E19)-SUM($D$9:D19))) -> 12390481 | H19: =IFERROR(MATCH($B$5&"-"&11,'Jurnal Umum'!$J$6:$J$909,0)+5,"") -> 35
A20: {=IF($H20="","",INDEX('Jurnal Umum'!$A$6:$A$2564,$H20-5))} -> 46235 | B20: {=IF($H20="","",IFERROR(INDEX('Jurnal Umum'!$C$6:$C$2564, MATCH(1, ('Jurnal Umum'!$A$6:$A$2564=INDEX('Jurnal Umum'!$A$6:$A$2564,$H20-5)) * ('Jurnal Umum'!$C$6:$C$2564=INDEX('Jurnal Umum'!$C$6:$C$2564,$H20-5)) * ('Jurnal Umum'!$D$6:$D$2564<>$B$5) ,0)),""))} -> Biaya Admin Kartu BCA | C20: {=IF($H20="","",INDEX('Jurnal Umum'!$B$6:$B$2564,$H20-5))} | D20: {=IF($H20="","",IF(INDEX('Jurnal Umum'!$F$6:$F$2564,$H20-5)="",0,INDEX('Jurnal Umum'!$F$6:$F$2564,$H20-5)))} -> 0 | E20: {=IF($H20="","",IF(INDEX('Jurnal Umum'!$G$6:$G$2564,$H20-5)="",0,INDEX('Jurnal Umum'!$G$6:$G$2564,$H20-5)))} -> 10000 | F20: =IF($H20="","",IF($B$6="Debit",SUM($D$9:D20)-SUM($E$9:E20),SUM($E$9:E20)-SUM($D$9:D20))) -> 12380481 | H20: =IFERROR(MATCH($B$5&"-"&12,'Jurnal Umum'!$J$6:$J$909,0)+5,"") -> 37
A21: {=IF($H21="","",INDEX('Jurnal Umum'!$A$6:$A$2564,$H21-5))} -> 46235 | B21: {=IF($H21="","",IFERROR(INDEX('Jurnal Umum'!$C$6:$C$2564, MATCH(1, ('Jurnal Umum'!$A$6:$A$2564=INDEX('Jurnal Umum'!$A$6:$A$2564,$H21-5)) * ('Jurnal Umum'!$C$6:$C$2564=INDEX('Jurnal Umum'!$C$6:$C$2564,$H21-5)) * ('Jurnal Umum'!$D$6:$D$2564<>$B$5) ,0)),""))} -> Penjualan Bunga Ke Vendor - Mas Abizar | C21: {=IF($H21="","",INDEX('Jurnal Umum'!$B$6:$B$2564,$H21-5))} -> BM-260801-001 | D21: {=IF($H21="","",IF(INDEX('Jurnal Umum'!$F$6:$F$2564,$H21-5)="",0,INDEX('Jurnal Umum'!$F$6:$F$2564,$H21-5)))} -> 48000 | E21: {=IF($H21="","",IF(INDEX('Jurnal Umum'!$G$6:$G$2564,$H21-5)="",0,INDEX('Jurnal Umum'!$G$6:$G$2564,$H21-5)))} -> 0 | F21: =IF($H21="","",IF($B$6="Debit",SUM($D$9:D21)-SUM($E$9:E21),SUM($E$9:E21)-SUM($D$9:D21))) -> 12428481 | H21: =IFERROR(MATCH($B$5&"-"&13,'Jurnal Umum'!$J$6:$J$909,0)+5,"") -> 44
A22: {=IF($H22="","",INDEX('Jurnal Umum'!$A$6:$A$2564,$H22-5))} -> 46235 | B22: {=IF($H22="","",IFERROR(INDEX('Jurnal Umum'!$C$6:$C$2564, MATCH(1, ('Jurnal Umum'!$A$6:$A$2564=INDEX('Jurnal Umum'!$A$6:$A$2564,$H22-5)) * ('Jurnal Umum'!$C$6:$C$2564=INDEX('Jurnal Umum'!$C$6:$C$2564,$H22-5)) * ('Jurnal Umum'!$D$6:$D$2564<>$B$5) ,0)),""))} -> Penjualan Bunga Ke Vendor - Mak Pon | C22: {=IF($H22="","",INDEX('Jurnal Umum'!$B$6:$B$2564,$H22-5))} -> PV-007 | D22: {=IF($H22="","",IF(INDEX('Jurnal Umum'!$F$6:$F$2564,$H22-5)="",0,INDEX('Jurnal Umum'!$F$6:$F$2564,$H22-5)))} -> 675000 | E22: {=IF($H22="","",IF(INDEX('Jurnal Umum'!$G$6:$G$2564,$H22-5)="",0,INDEX('Jurnal Umum'!$G$6:$G$2564,$H22-5)))} -> 0 | F22: =IF($H22="","",IF($B$6="Debit",SUM($D$9:D22)-SUM($E$9:E22),SUM($E$9:E22)-SUM($D$9:D22))) -> 13103481 | H22: =IFERROR(MATCH($B$5&"-"&14,'Jurnal Umum'!$J$6:$J$909,0)+5,"") -> 46
A23: {=IF($H23="","",INDEX('Jurnal Umum'!$A$6:$A$2564,$H23-5))} -> 46237 | B23: {=IF($H23="","",IFERROR(INDEX('Jurnal Umum'!$C$6:$C$2564, MATCH(1, ('Jurnal Umum'!$A$6:$A$2564=INDEX('Jurnal Umum'!$A$6:$A$2564,$H23-5)) * ('Jurnal Umum'!$C$6:$C$2564=INDEX('Jurnal Umum'!$C$6:$C$2564,$H23-5)) * ('Jurnal Umum'!$D$6:$D$2564<>$B$5) ,0)),""))} -> Pengembalian Dana Talangan Ongkir | C23: {=IF($H23="","",INDEX('Jurnal Umum'!$B$6:$B$2564,$H23-5))} | D23: {=IF($H23="","",IF(INDEX('Jurnal Umum'!$F$6:$F$2564,$H23-5)="",0,INDEX('Jurnal Umum'!$F$6:$F$2564,$H23-5)))} -> 2038519 | E23: {=IF($H23="","",IF(INDEX('Jurnal Umum'!$G$6:$G$2564,$H23-5)="",0,INDEX('Jurnal Umum'!$G$6:$G$2564,$H23-5)))} -> 0 | F23: =IF($H23="","",IF($B$6="Debit",SUM($D$9:D23)-SUM($E$9:E23),SUM($E$9:E23)-SUM($D$9:D23))) -> 15142000 | H23: =IFERROR(MATCH($B$5&"-"&15,'Jurnal Umum'!$J$6:$J$909,0)+5,"") -> 48
A24: {=IF($H24="","",INDEX('Jurnal Umum'!$A$6:$A$2564,$H24-5))} -> 46237 | B24: {=IF($H24="","",IFERROR(INDEX('Jurnal Umum'!$C$6:$C$2564, MATCH(1, ('Jurnal Umum'!$A$6:$A$2564=INDEX('Jurnal Umum'!$A$6:$A$2564,$H24-5)) * ('Jurnal Umum'!$C$6:$C$2564=INDEX('Jurnal Umum'!$C$6:$C$2564,$H24-5)) * ('Jurnal Umum'!$D$6:$D$2564<>$B$5) ,0)),""))} -> Pembayaran Penjualan Tanggal 1 | C24: {=IF($H24="","",INDEX('Jurnal Umum'!$B$6:$B$2564,$H24-5))} | D24: {=IF($H24="","",IF(INDEX('Jurnal Umum'!$F$6:$F$2564,$H24-5)="",0,INDEX('Jurnal Umum'!$F$6:$F$2564,$H24-5)))} -> 2301250 | E24: {=IF($H24="","",IF(INDEX('Jurnal Umum'!$G$6:$G$2564,$H24-5)="",0,INDEX('Jurnal Umum'!$G$6:$G$2564,$H24-5)))} -> 0 | F24: =IF($H24="","",IF($B$6="Debit",SUM($D$9:D24)-SUM($E$9:E24),SUM($E$9:E24)-SUM($D$9:D24))) -> 17443250 | H24: =IFERROR(MATCH($B$5&"-"&16,'Jurnal Umum'!$J$6:$J$909,0)+5,"") -> 50
A25: {=IF($H25="","",INDEX('Jurnal Umum'!$A$6:$A$2564,$H25-5))} -> 46237 | B25: {=IF($H25="","",IFERROR(INDEX('Jurnal Umum'!$C$6:$C$2564, MATCH(1, ('Jurnal Umum'!$A$6:$A$2564=INDEX('Jurnal Umum'!$A$6:$A$2564,$H25-5)) * ('Jurnal Umum'!$C$6:$C$2564=INDEX('Jurnal Umum'!$C$6:$C$2564,$H25-5)) * ('Jurnal Umum'!$D$6:$D$2564<>$B$5) ,0)),""))} -> Pembayaran Bunga WKF | C25: {=IF($H25="","",INDEX('Jurnal Umum'!$B$6:$B$2564,$H25-5))} -> BK-260803-001 | D25: {=IF($H25="","",IF(INDEX('Jurnal Umum'!$F$6:$F$2564,$H25-5)="",0,INDEX('Jurnal Umum'!$F$6:$F$2564,$H25-5)))} -> 0 | E25: {=IF($H25="","",IF(INDEX('Jurnal Umum'!$G$6:$G$2564,$H25-5)="",0,INDEX('Jurnal Umum'!$G$6:$G$2564,$H25-5)))} -> 180000 | F25: =IF($H25="","",IF($B$6="Debit",SUM($D$9:D25)-SUM($E$9:E25),SUM($E$9:E25)-SUM($D$9:D25))) -> 17263250 | H25: =IFERROR(MATCH($B$5&"-"&17,'Jurnal Umum'!$J$6:$J$909,0)+5,"") -> 53
A26: {=IF($H26="","",INDEX('Jurnal Umum'!$A$6:$A$2564,$H26-5))} -> 46237 | B26: {=IF($H26="","",IFERROR(INDEX('Jurnal Umum'!$C$6:$C$2564, MATCH(1, ('Jurnal Umum'!$A$6:$A$2564=INDEX('Jurnal Umum'!$A$6:$A$2564,$H26-5)) * ('Jurnal Umum'!$C$6:$C$2564=INDEX('Jurnal Umum'!$C$6:$C$2564,$H26-5)) * ('Jurnal Umum'!$D$6:$D$2564<>$B$5) ,0)),""))} -> Pembayaran Bunga WKF | C26: {=IF($H26="","",INDEX('Jurnal Umum'!$B$6:$B$2564,$H26-5))} -> BK-260803-002 | D26: {=IF($H26="","",IF(INDEX('Jurnal Umum'!$F$6:$F$2564,$H26-5)="",0,INDEX('Jurnal Umum'!$F$6:$F$2564,$H26-5)))} -> 0 | E26: {=IF($H26="","",IF(INDEX('Jurnal Umum'!$G$6:$G$2564,$H26-5)="",0,INDEX('Jurnal Umum'!$G$6:$G$2564,$H26-5)))} -> 50000 | F26: =IF($H26="","",IF($B$6="Debit",SUM($D$9:D26)-SUM($E$9:E26),SUM($E$9:E26)-SUM($D$9:D26))) -> 17213250 | H26: =IFERROR(MATCH($B$5&"-"&18,'Jurnal Umum'!$J$6:$J$909,0)+5,"") -> 55
A27: {=IF($H27="","",INDEX('Jurnal Umum'!$A$6:$A$2564,$H27-5))} -> 46237 | B27: {=IF($H27="","",IFERROR(INDEX('Jurnal Umum'!$C$6:$C$2564, MATCH(1, ('Jurnal Umum'!$A$6:$A$2564=INDEX('Jurnal Umum'!$A$6:$A$2564,$H27-5)) * ('Jurnal Umum'!$C$6:$C$2564=INDEX('Jurnal Umum'!$C$6:$C$2564,$H27-5)) * ('Jurnal Umum'!$D$6:$D$2564<>$B$5) ,0)),""))} -> Pembayaran Bunga di Grace Rose | C27: {=IF($H27="","",INDEX('Jurnal Umum'!$B$6:$B$2564,$H27-5))} | D27: {=IF($H27="","",IF(INDEX('Jurnal Umum'!$F$6:$F$2564,$H27-5)="",0,INDEX('Jurnal Umum'!$F$6:$F$2564,$H27-5)))} -> 0 | E27: {=IF($H27="","",IF(INDEX('Jurnal Umum'!$G$6:$G$2564,$H27-5)="",0,INDEX('Jurnal Umum'!$G$6:$G$2564,$H27-5)))} -> 418000 | F27: =IF($H27="","",IF($B$6="Debit",SUM($D$9:D27)-SUM($E$9:E27),SUM($E$9:E27)-SUM($D$9:D27))) -> 16795250 | H27: =IFERROR(MATCH($B$5&"-"&19,'Jurnal Umum'!$J$6:$J$909,0)+5,"") -> 57
A28: {=IF($H28="","",INDEX('Jurnal Umum'!$A$6:$A$2564,$H28-5))} -> 46237 | B28: {=IF($H28="","",IFERROR(INDEX('Jurnal Umum'!$C$6:$C$2564, MATCH(1, ('Jurnal Umum'!$A$6:$A$2564=INDEX('Jurnal Umum'!$A$6:$A$2564,$H28-5)) * ('Jurnal Umum'!$C$6:$C$2564=INDEX('Jurnal Umum'!$C$6:$C$2564,$H28-5)) * ('Jurnal Umum'!$D$6:$D$2564<>$B$5) ,0)),""))} -> Pembelian Bunga di Vendor - Mak Pon | C28: {=IF($H28="","",INDEX('Jurnal Umum'!$B$6:$B$2564,$H28-5))} | D28: {=IF($H28="","",IF(INDEX('Jurnal Umum'!$F$6:$F$2564,$H28-5)="",0,INDEX('Jurnal Umum'!$F$6:$F$2564,$H28-5)))} -> 0 | E28: {=IF($H28="","",IF(INDEX('Jurnal Umum'!$G$6:$G$2564,$H28-5)="",0,INDEX('Jurnal Umum'!$G$6:$G$2564,$H28-5)))} -> 380000 | F28: =IF($H28="","",IF($B$6="Debit",SUM($D$9:D28)-SUM($E$9:E28),SUM($E$9:E28)-SUM($D$9:D28))) -> 16415250 | H28: =IFERROR(MATCH($B$5&"-"&20,'Jurnal Umum'!$J$6:$J$909,0)+5,"") -> 59
A29: {=IF($H29="","",INDEX('Jurnal Umum'!$A$6:$A$2564,$H29-5))} -> 46237 | B29: {=IF($H29="","",IFERROR(INDEX('Jurnal Umum'!$C$6:$C$2564, MATCH(1, ('Jurnal Umum'!$A$6:$A$2564=INDEX('Jurnal Umum'!$A$6:$A$2564,$H29-5)) * ('Jurnal Umum'!$C$6:$C$2564=INDEX('Jurnal Umum'!$C$6:$C$2564,$H29-5)) * ('Jurnal Umum'!$D$6:$D$2564<>$B$5) ,0)),""))} -> Pembelian Bunga di Vendor - Pak Sumadi | C29: {=IF($H29="","",INDEX('Jurnal Umum'!$B$6:$B$2564,$H29-5))} | D29: {=IF($H29="","",IF(INDEX('Jurnal Umum'!$F$6:$F$2564,$H29-5)="",0,INDEX('Jurnal Umum'!$F$6:$F$2564,$H29-5)))} -> 0 | E29: {=IF($H29="","",IF(INDEX('Jurnal Umum'!$G$6:$G$2564,$H29-5)="",0,INDEX('Jurnal Umum'!$G$6:$G$2564,$H29-5)))} -> 240000 | F29: =IF($H29="","",IF($B$6="Debit",SUM($D$9:D29)-SUM($E$9:E29),SUM($E$9:E29)-SUM($D$9:D29))) -> 16175250 | H29: =IFERROR(MATCH($B$5&"-"&21,'Jurnal Umum'!$J$6:$J$909,0)+5,"") -> 61
A30: {=IF($H30="","",INDEX('Jurnal Umum'!$A$6:$A$2564,$H30-5))} -> 46237 | B30: {=IF($H30="","",IFERROR(INDEX('Jurnal Umum'!$C$6:$C$2564, MATCH(1, ('Jurnal Umum'!$A$6:$A$2564=INDEX('Jurnal Umum'!$A$6:$A$2564,$H30-5)) * ('Jurnal Umum'!$C$6:$C$2564=INDEX('Jurnal Umum'!$C$6:$C$2564,$H30-5)) * ('Jurnal Umum'!$D$6:$D$2564<>$B$5) ,0)),""))} -> Pembelian Bunga ke Vendor - Mba Yeti | C30: {=IF($H30="","",INDEX('Jurnal Umum'!$B$6:$B$2564,$H30-5))} | D30: {=IF($H30="","",IF(INDEX('Jurnal Umum'!$F$6:$F$2564,$H30-5)="",0,INDEX('Jurnal Umum'!$F$6:$F$2564,$H30-5)))} -> 0 | E30: {=IF($H30="","",IF(INDEX('Jurnal Umum'!$G$6:$G$2564,$H30-5)="",0,INDEX('Jurnal Umum'!$G$6:$G$2564,$H30-5)))} -> 390000 | F30: =IF($H30="","",IF($B$6="Debit",SUM($D$9:D30)-SUM($E$9:E30),SUM($E$9:E30)-SUM($D$9:D30))) -> 15785250 | H30: =IFERROR(MATCH($B$5&"-"&22,'Jurnal Umum'!$J$6:$J$909,0)+5,"") -> 81
A31: {=IF($H31="","",INDEX('Jurnal Umum'!$A$6:$A$2564,$H31-5))} -> 46238 | B31: {=IF($H31="","",IFERROR(INDEX('Jurnal Umum'!$C$6:$C$2564, MATCH(1, ('Jurnal Umum'!$A$6:$A$2564=INDEX('Jurnal Umum'!$A$6:$A$2564,$H31-5)) * ('Jurnal Umum'!$C$6:$C$2564=INDEX('Jurnal Umum'!$C$6:$C$2564,$H31-5)) * ('Jurnal Umum'!$D$6:$D$2564<>$B$5) ,0)),""))} -> Pembelian Bunga ke Omniflora | C31: {=IF($H31="","",INDEX('Jurnal Umum'!$B$6:$B$2564,$H31-5))} -> BK-260804-001 | D31: {=IF($H31="","",IF(INDEX('Jurnal Umum'!$F$6:$F$2564,$H31-5)="",0,INDEX('Jurnal Umum'!$F$6:$F$2564,$H31-5)))} -> 0 | E31: {=IF($H31="","",IF(INDEX('Jurnal Umum'!$G$6:$G$2564,$H31-5)="",0,INDEX('Jurnal Umum'!$G$6:$G$2564,$H31-5)))} -> 930000 | F31: =IF($H31="","",IF($B$6="Debit",SUM($D$9:D31)-SUM($E$9:E31),SUM($E$9:E31)-SUM($D$9:D31))) -> 14855250 | H31: =IFERROR(MATCH($B$5&"-"&23,'Jurnal Umum'!$J$6:$J$909,0)+5,"") -> 83
A32: {=IF($H32="","",INDEX('Jurnal Umum'!$A$6:$A$2564,$H32-5))} -> 46238 | B32: {=IF($H32="","",IFERROR(INDEX('Jurnal Umum'!$C$6:$C$2564, MATCH(1, ('Jurnal Umum'!$A$6:$A$2564=INDEX('Jurnal Umum'!$A$6:$A$2564,$H32-5)) * ('Jurnal Umum'!$C$6:$C$2564=INDEX('Jurnal Umum'!$C$6:$C$2564,$H32-5)) * ('Jurnal Umum'!$D$6:$D$2564<>$B$5) ,0)),""))} -> Pembayaran Ongkir Pembelian Bunga - Daytrans | C32: {=IF($H32="","",INDEX('Jurnal Umum'!$B$6:$B$2564,$H32-5))} | D32: {=IF($H32="","",IF(INDEX('Jurnal Umum'!$F$6:$F$2564,$H32-5)="",0,INDEX('Jurnal Umum'!$F$6:$F$2564,$H32-5)))} -> 0 | E32: {=IF($H32="","",IF(INDEX('Jurnal Umum'!$G$6:$G$2564,$H32-5)="",0,INDEX('Jurnal Umum'!$G$6:$G$2564,$H32-5)))} -> 87500 | F32: =IF($H32="","",IF($B$6="Debit",SUM($D$9:D32)-SUM($E$9:E32),SUM($E$9:E32)-SUM($D$9:D32))) -> 14767750 | H32: =IFERROR(MATCH($B$5&"-"&24,'Jurnal Umum'!$J$6:$J$909,0)+5,"") -> 85
A33: {=IF($H33="","",INDEX('Jurnal Umum'!$A$6:$A$2564,$H33-5))} -> 46238 | B33: {=IF($H33="","",IFERROR(INDEX('Jurnal Umum'!$C$6:$C$2564, MATCH(1, ('Jurnal Umum'!$A$6:$A$2564=INDEX('Jurnal Umum'!$A$6:$A$2564,$H33-5)) * ('Jurnal Umum'!$C$6:$C$2564=INDEX('Jurnal Umum'!$C$6:$C$2564,$H33-5)) * ('Jurnal Umum'!$D$6:$D$2564<>$B$5) ,0)),""))} -> Pembelian Paket Data - Mas Refan | C33: {=IF($H33="","",INDEX('Jurnal Umum'!$B$6:$B$2564,$H33-5))} | D33: {=IF($H33="","",IF(INDEX('Jurnal Umum'!$F$6:$F$2564,$H33-5)="",0,INDEX('Jurnal Umum'!$F$6:$F$2564,$H33-5)))} -> 0 | E33: {=IF($H33="","",IF(INDEX('Jurnal Umum'!$G$6:$G$2564,$H33-5)="",0,INDEX('Jurnal Umum'!$G$6:$G$2564,$H33-5)))} -> 2800 | F33: =IF($H33="","",IF($B$6="Debit",SUM($D$9:D33)-SUM($E$9:E33),SUM($E$9:E33)-SUM($D$9:D33))) -> 14764950 | H33: =IFERROR(MATCH($B$5&"-"&25,'Jurnal Umum'!$J$6:$J$909,0)+5,"") -> 93
A34: {=IF($H34="","",INDEX('Jurnal Umum'!$A$6:$A$2564,$H34-5))} -> 46238 | B34: {=IF($H34="","",IFERROR(INDEX('Jurnal Umum'!$C$6:$C$2564, MATCH(1, ('Jurnal Umum'!$A$6:$A$2564=INDEX('Jurnal Umum'!$A$6:$A$2564,$H34-5)) * ('Jurnal Umum'!$C$6:$C$2564=INDEX('Jurnal Umum'!$C$6:$C$2564,$H34-5)) * ('Jurnal Umum'!$D$6:$D$2564<>$B$5) ,0)),""))} -> Talangan Pembayaran Ongkir DMK Cargo | C34: {=IF($H34="","",INDEX('Jurnal Umum'!$B$6:$B$2564,$H34-5))} | D34: {=IF($H34="","",IF(INDEX('Jurnal Umum'!$F$6:$F$2564,$H34-5)="",0,INDEX('Jurnal Umum'!$F$6:$F$2564,$H34-5)))} -> 0 | E34: {=IF($H34="","",IF(INDEX('Jurnal Umum'!$G$6:$G$2564,$H34-5)="",0,INDEX('Jurnal Umum'!$G$6:$G$2564,$H34-5)))} -> 1412159 | F34: =IF($H34="","",IF($B$6="Debit",SUM($D$9:D34)-SUM($E$9:E34),SUM($E$9:E34)-SUM($D$9:D34))) -> 13352791 | H34: =IFERROR(MATCH($B$5&"-"&26,'Jurnal Umum'!$J$6:$J$909,0)+5,"") -> 97
A35: {=IF($H35="","",INDEX('Jurnal Umum'!$A$6:$A$2564,$H35-5))} -> 46238 | B35: {=IF($H35="","",IFERROR(INDEX('Jurnal Umum'!$C$6:$C$2564, MATCH(1, ('Jurnal Umum'!$A$6:$A$2564=INDEX('Jurnal Umum'!$A$6:$A$2564,$H35-5)) * ('Jurnal Umum'!$C$6:$C$2564=INDEX('Jurnal Umum'!$C$6:$C$2564,$H35-5)) * ('Jurnal Umum'!$D$6:$D$2564<>$B$5) ,0)),""))} -> Penjualan Bunga Tanggal 3 | C35: {=IF($H35="","",INDEX('Jurnal Umum'!$B$6:$B$2564,$H35-5))} | D35: {=IF($H35="","",IF(INDEX('Jurnal Umum'!$F$6:$F$2564,$H35-5)="",0,INDEX('Jurnal Umum'!$F$6:$F$2564,$H35-5)))} -> 1327250 | E35: {=IF($H35="","",IF(INDEX('Jurnal Umum'!$G$6:$G$2564,$H35-5)="",0,INDEX('Jurnal Umum'!$G$6:$G$2564,$H35-5)))} -> 0 | F35: =IF($H35="","",IF($B$6="Debit",SUM($D$9:D35)-SUM($E$9:E35),SUM($E$9:E35)-SUM($D$9:D35))) -> 14680041 | H35: =IFERROR(MATCH($B$5&"-"&27,'Jurnal Umum'!$J$6:$J$909,0)+5,"") -> 98
A36: {=IF($H36="","",INDEX('Jurnal Umum'!$A$6:$A$2564,$H36-5))} -> 46238 | B36: {=IF($H36="","",IFERROR(INDEX('Jurnal Umum'!$C$6:$C$2564, MATCH(1, ('Jurnal Umum'!$A$6:$A$2564=INDEX('Jurnal Umum'!$A$6:$A$2564,$H36-5)) * ('Jurnal Umum'!$C$6:$C$2564=INDEX('Jurnal Umum'!$C$6:$C$2564,$H36-5)) * ('Jurnal Umum'!$D$6:$D$2564<>$B$5) ,0)),""))} -> Pengembalian Dana Talangan Ongkir | C36: {=IF($H36="","",INDEX('Jurnal Umum'!$B$6:$B$2564,$H36-5))} | D36: {=IF($H36="","",IF(INDEX('Jurnal Umum'!$F$6:$F$2564,$H36-5)="",0,INDEX('Jurnal Umum'!$F$6:$F$2564,$H36-5)))} -> 1412159 | E36: {=IF($H36="","",IF(INDEX('Jurnal Umum'!$G$6:$G$2564,$H36-5)="",0,INDEX('Jurnal Umum'!$G$6:$G$2564,$H36-5)))} -> 0 | F36: =IF($H36="","",IF($B$6="Debit",SUM($D$9:D36)-SUM($E$9:E36),SUM($E$9:E36)-SUM($D$9:D36))) -> 16092200 | H36: =IFERROR(MATCH($B$5&"-"&28,'Jurnal Umum'!$J$6:$J$909,0)+5,"") -> 100
A37: {=IF($H37="","",INDEX('Jurnal Umum'!$A$6:$A$2564,$H37-5))} -> 46238 | B37: {=IF($H37="","",IFERROR(INDEX('Jurnal Umum'!$C$6:$C$2564, MATCH(1, ('Jurnal Umum'!$A$6:$A$2564=INDEX('Jurnal Umum'!$A$6:$A$2564,$H37-5)) * ('Jurnal Umum'!$C$6:$C$2564=INDEX('Jurnal Umum'!$C$6:$C$2564,$H37-5)) * ('Jurnal Umum'!$D$6:$D$2564<>$B$5) ,0)),""))} -> Pembelian Bunga Pikok di Mas Dana | C37: {=IF($H37="","",INDEX('Jurnal Umum'!$B$6:$B$2564,$H37-5))} | D37: {=IF($H37="","",IF(INDEX('Jurnal Umum'!$F$6:$F$2564,$H37-5)="",0,INDEX('Jurnal Umum'!$F$6:$F$2564,$H37-5)))} -> 0 | E37: {=IF($H37="","",IF(INDEX('Jurnal Umum'!$G$6:$G$2564,$H37-5)="",0,INDEX('Jurnal Umum'!$G$6:$G$2564,$H37-5)))} -> 300000 | F37: =IF($H37="","",IF($B$6="Debit",SUM($D$9:D37)-SUM($E$9:E37),SUM($E$9:E37)-SUM($D$9:D37))) -> 15792200 | H37: =IFERROR(MATCH($B$5&"-"&29,'Jurnal Umum'!$J$6:$J$909,0)+5,"") -> 109
A38: {=IF($H38="","",INDEX('Jurnal Umum'!$A$6:$A$2564,$H38-5))} -> 46239 | B38: {=IF($H38="","",IFERROR(INDEX('Jurnal Umum'!$C$6:$C$2564, MATCH(1, ('Jurnal Umum'!$A$6:$A$2564=INDEX('Jurnal Umum'!$A$6:$A$2564,$H38-5)) * ('Jurnal Umum'!$C$6:$C$2564=INDEX('Jurnal Umum'!$C$6:$C$2564,$H38-5)) * ('Jurnal Umum'!$D$6:$D$2564<>$B$5) ,0)),""))} -> Talangan Ongkir DMK Cargo tanggal 4 | C38: {=IF($H38="","",INDEX('Jurnal Umum'!$B$6:$B$2564,$H38-5))} | D38: {=IF($H38="","",IF(INDEX('Jurnal Umum'!$F$6:$F$2564,$H38-5)="",0,INDEX('Jurnal Umum'!$F$6:$F$2564,$H38-5)))} -> 0 | E38: {=IF($H38="","",IF(INDEX('Jurnal Umum'!$G$6:$G$2564,$H38-5)="",0,INDEX('Jurnal Umum'!$G$6:$G$2564,$H38-5)))} -> 2211476 | F38: =IF($H38="","",IF($B$6="Debit",SUM($D$9:D38)-SUM($E$9:E38),SUM($E$9:E38)-SUM($D$9:D38))) -> 13580724 | H38: =IFERROR(MATCH($B$5&"-"&30,'Jurnal Umum'!$J$6:$J$909,0)+5,"") -> 113
A39: {=IF($H39="","",INDEX('Jurnal Umum'!$A$6:$A$2564,$H39-5))} -> 46239 | B39: {=IF($H39="","",IFERROR(INDEX('Jurnal Umum'!$C$6:$C$2564, MATCH(1, ('Jurnal Umum'!$A$6:$A$2564=INDEX('Jurnal Umum'!$A$6:$A$2564,$H39-5)) * ('Jurnal Umum'!$C$6:$C$2564=INDEX('Jurnal Umum'!$C$6:$C$2564,$H39-5)) * ('Jurnal Umum'!$D$6:$D$2564<>$B$5) ,0)),""))} -> Penjualan Bunga Tanggal 4 | C39: {=IF($H39="","",INDEX('Jurnal Umum'!$B$6:$B$2564,$H39-5))} | D39: {=IF($H39="","",IF(INDEX('Jurnal Umum'!$F$6:$F$2564,$H39-5)="",0,INDEX('Jurnal Umum'!$F$6:$F$2564,$H39-5)))} -> 4075000 | E39: {=IF($H39="","",IF(INDEX('Jurnal Umum'!$G$6:$G$2564,$H39-5)="",0,INDEX('Jurnal Umum'!$G$6:$G$2564,$H39-5)))} -> 0 | F39: =IF($H39="","",IF($B$6="Debit",SUM($D$9:D39)-SUM($E$9:E39),SUM($E$9:E39)-SUM($D$9:D39))) -> 17655724 | H39: =IFERROR(MATCH($B$5&"-"&31,'Jurnal Umum'!$J$6:$J$909,0)+5,"") -> 114
A40: {=IF($H40="","",INDEX('Jurnal Umum'!$A$6:$A$2564,$H40-5))} -> 46239 | B40: {=IF($H40="","",IFERROR(INDEX('Jurnal Umum'!$C$6:$C$2564, MATCH(1, ('Jurnal Umum'!$A$6:$A$2564=INDEX('Jurnal Umum'!$A$6:$A$2564,$H40-5)) * ('Jurnal Umum'!$C$6:$C$2564=INDEX('Jurnal Umum'!$C$6:$C$2564,$H40-5)) * ('Jurnal Umum'!$D$6:$D$2564<>$B$5) ,0)),""))} -> Pengembalian Dana Talangan Ongkir tanggal 4 | C40: {=IF($H40="","",INDEX('Jurnal Umum'!$B$6:$B$2564,$H40-5))} | D40: {=IF($H40="","",IF(INDEX('Jurnal Umum'!$F$6:$F$2564,$H40-5)="",0,INDEX('Jurnal Umum'!$F$6:$F$2564,$H40-5)))} -> 2211476 | E40: {=IF($H40="","",IF(INDEX('Jurnal Umum'!$G$6:$G$2564,$H40-5)="",0,INDEX('Jurnal Umum'!$G$6:$G$2564,$H40-5)))} -> 0 | F40: =IF($H40="","",IF($B$6="Debit",SUM($D$9:D40)-SUM($E$9:E40),SUM($E$9:E40)-SUM($D$9:D40))) -> 19867200 | H40: =IFERROR(MATCH($B$5&"-"&32,'Jurnal Umum'!$J$6:$J$909,0)+5,"") -> 116
A41: {=IF($H41="","",INDEX('Jurnal Umum'!$A$6:$A$2564,$H41-5))} -> 46239 | B41: {=IF($H41="","",IFERROR(INDEX('Jurnal Umum'!$C$6:$C$2564, MATCH(1, ('Jurnal Umum'!$A$6:$A$2564=INDEX('Jurnal Umum'!$A$6:$A$2564,$H41-5)) * ('Jurnal Umum'!$C$6:$C$2564=INDEX('Jurnal Umum'!$C$6:$C$2564,$H41-5)) * ('Jurnal Umum'!$D$6:$D$2564<>$B$5) ,0)),""))} -> Pembelian Bunga di Pro Florist | C41: {=IF($H41="","",INDEX('Jurnal Umum'!$B$6:$B$2564,$H41-5))} | D41: {=IF($H41="","",IF(INDEX('Jurnal Umum'!$F$6:$F$2564,$H41-5)="",0,INDEX('Jurnal Umum'!$F$6:$F$2564,$H41-5)))} -> 0 | E41: {=IF($H41="","",IF(INDEX('Jurnal Umum'!$G$6:$G$2564,$H41-5)="",0,INDEX('Jurnal Umum'!$G$6:$G$2564,$H41-5)))} -> 20000 | F41: =IF($H41="","",IF($B$6="Debit",SUM($D$9:D41)-SUM($E$9:E41),SUM($E$9:E41)-SUM($D$9:D41))) -> 19847200 | H41: =IFERROR(MATCH($B$5&"-"&33,'Jurnal Umum'!$J$6:$J$909,0)+5,"") -> 125
A42: {=IF($H42="","",INDEX('Jurnal Umum'!$A$6:$A$2564,$H42-5))} -> 46239 | B42: {=IF($H42="","",IFERROR(INDEX('Jurnal Umum'!$C$6:$C$2564, MATCH(1, ('Jurnal Umum'!$A$6:$A$2564=INDEX('Jurnal Umum'!$A$6:$A$2564,$H42-5)) * ('Jurnal Umum'!$C$6:$C$2564=INDEX('Jurnal Umum'!$C$6:$C$2564,$H42-5)) * ('Jurnal Umum'!$D$6:$D$2564<>$B$5) ,0)),""))} -> Pembelian Bunga di Vendor - Om Toha | C42: {=IF($H42="","",INDEX('Jurnal Umum'!$B$6:$B$2564,$H42-5))} | D42: {=IF($H42="","",IF(INDEX('Jurnal Umum'!$F$6:$F$2564,$H42-5)="",0,INDEX('Jurnal Umum'!$F$6:$F$2564,$H42-5)))} -> 0 | E42: {=IF($H42="","",IF(INDEX('Jurnal Umum'!$G$6:$G$2564,$H42-5)="",0,INDEX('Jurnal Umum'!$G$6:$G$2564,$H42-5)))} -> 420000 | F42: =IF($H42="","",IF($B$6="Debit",SUM($D$9:D42)-SUM($E$9:E42),SUM($E$9:E42)-SUM($D$9:D42))) -> 19427200 | H42: =IFERROR(MATCH($B$5&"-"&34,'Jurnal Umum'!$J$6:$J$909,0)+5,"") -> 127
A43: {=IF($H43="","",INDEX('Jurnal Umum'!$A$6:$A$2564,$H43-5))} -> 46239 | B43: {=IF($H43="","",IFERROR(INDEX('Jurnal Umum'!$C$6:$C$2564, MATCH(1, ('Jurnal Umum'!$A$6:$A$2564=INDEX('Jurnal Umum'!$A$6:$A$2564,$H43-5)) * ('Jurnal Umum'!$C$6:$C$2564=INDEX('Jurnal Umum'!$C$6:$C$2564,$H43-5)) * ('Jurnal Umum'!$D$6:$D$2564<>$B$5) ,0)),""))} -> Pembelian Bunga di Vendor - Mba Ciput | C43: {=IF($H43="","",INDEX('Jurnal Umum'!$B$6:$B$2564,$H43-5))} | D43: {=IF($H43="","",IF(INDEX('Jurnal Umum'!$F$6:$F$2564,$H43-5)="",0,INDEX('Jurnal Umum'!$F$6:$F$2564,$H43-5)))} -> 0 | E43: {=IF($H43="","",IF(INDEX('Jurnal Umum'!$G$6:$G$2564,$H43-5)="",0,INDEX('Jurnal Umum'!$G$6:$G$2564,$H43-5)))} -> 475000 | F43: =IF($H43="","",IF($B$6="Debit",SUM($D$9:D43)-SUM($E$9:E43),SUM($E$9:E43)-SUM($D$9:D43))) -> 18952200 | H43: =IFERROR(MATCH($B$5&"-"&35,'Jurnal Umum'!$J$6:$J$909,0)+5,"") -> 129
A44: {=IF($H44="","",INDEX('Jurnal Umum'!$A$6:$A$2564,$H44-5))} -> 46239 | B44: {=IF($H44="","",IFERROR(INDEX('Jurnal Umum'!$C$6:$C$2564, MATCH(1, ('Jurnal Umum'!$A$6:$A$2564=INDEX('Jurnal Umum'!$A$6:$A$2564,$H44-5)) * ('Jurnal Umum'!$C$6:$C$2564=INDEX('Jurnal Umum'!$C$6:$C$2564,$H44-5)) * ('Jurnal Umum'!$D$6:$D$2564<>$B$5) ,0)),""))} -> Pembelian Bunga di WKF | C44: {=IF($H44="","",INDEX('Jurnal Umum'!$B$6:$B$2564,$H44-5))} -> BK-2608050001 | D44: {=IF($H44="","",IF(INDEX('Jurnal Umum'!$F$6:$F$2564,$H44-5)="",0,INDEX('Jurnal Umum'!$F$6:$F$2564,$H44-5)))} -> 0 | E44: {=IF($H44="","",IF(INDEX('Jurnal Umum'!$G$6:$G$2564,$H44-5)="",0,INDEX('Jurnal Umum'!$G$6:$G$2564,$H44-5)))} -> 380000 | F44: =IF($H44="","",IF($B$6="Debit",SUM($D$9:D44)-SUM($E$9:E44),SUM($E$9:E44)-SUM($D$9:D44))) -> 18572200 | H44: =IFERROR(MATCH($B$5&"-"&36,'Jurnal Umum'!$J$6:$J$909,0)+5,"") -> 139
A45: {=IF($H45="","",INDEX('Jurnal Umum'!$A$6:$A$2564,$H45-5))} -> 46240 | B45: {=IF($H45="","",IFERROR(INDEX('Jurnal Umum'!$C$6:$C$2564, MATCH(1, ('Jurnal Umum'!$A$6:$A$2564=INDEX('Jurnal Umum'!$A$6:$A$2564,$H45-5)) * ('Jurnal Umum'!$C$6:$C$2564=INDEX('Jurnal Umum'!$C$6:$C$2564,$H45-5)) * ('Jurnal Umum'!$D$6:$D$2564<>$B$5) ,0)),""))} -> Talangan Ongkir DMK Cargo tgl 5 | C45: {=IF($H45="","",INDEX('Jurnal Umum'!$B$6:$B$2564,$H45-5))} | D45: {=IF($H45="","",IF(INDEX('Jurnal Umum'!$F$6:$F$2564,$H45-5)="",0,INDEX('Jurnal Umum'!$F$6:$F$2564,$H45-5)))} -> 0 | E45: {=IF($H45="","",IF(INDEX('Jurnal Umum'!$G$6:$G$2564,$H45-5)="",0,INDEX('Jurnal Umum'!$G$6:$G$2564,$H45-5)))} -> 1018280 | F45: =IF($H45="","",IF($B$6="Debit",SUM($D$9:D45)-SUM($E$9:E45),SUM($E$9:E45)-SUM($D$9:D45))) -> 17553920 | H45: =IFERROR(MATCH($B$5&"-"&37,'Jurnal Umum'!$J$6:$J$909,0)+5,"") -> 143
A46: {=IF($H46="","",INDEX('Jurnal Umum'!$A$6:$A$2564,$H46-5))} -> 46240 | B46: {=IF($H46="","",IFERROR(INDEX('Jurnal Umum'!$C$6:$C$2564, MATCH(1, ('Jurnal Umum'!$A$6:$A$2564=INDEX('Jurnal Umum'!$A$6:$A$2564,$H46-5)) * ('Jurnal Umum'!$C$6:$C$2564=INDEX('Jurnal Umum'!$C$6:$C$2564,$H46-5)) * ('Jurnal Umum'!$D$6:$D$2564<>$B$5) ,0)),""))} -> Tarik Tunai untuk kas operasional | C46: {=IF($H46="","",INDEX('Jurnal Umum'!$B$6:$B$2564,$H46-5))} | D46: {=IF($H46="","",IF(INDEX('Jurnal Umum'!$F$6:$F$2564,$H46-5)="",0,INDEX('Jurnal Umum'!$F$6:$F$2564,$H46-5)))} -> 0 | E46: {=IF($H46="","",IF(INDEX('Jurnal Umum'!$G$6:$G$2564,$H46-5)="",0,INDEX('Jurnal Umum'!$G$6:$G$2564,$H46-5)))} -> 2000000 | F46: =IF($H46="","",IF($B$6="Debit",SUM($D$9:D46)-SUM($E$9:E46),SUM($E$9:E46)-SUM($D$9:D46))) -> 15553920 | H46: =IFERROR(MATCH($B$5&"-"&38,'Jurnal Umum'!$J$6:$J$909,0)+5,"") -> 145
A47: {=IF($H47="","",INDEX('Jurnal Umum'!$A$6:$A$2564,$H47-5))} -> 46240 | B47: {=IF($H47="","",IFERROR(INDEX('Jurnal Umum'!$C$6:$C$2564, MATCH(1, ('Jurnal Umum'!$A$6:$A$2564=INDEX('Jurnal Umum'!$A$6:$A$2564,$H47-5)) * ('Jurnal Umum'!$C$6:$C$2564=INDEX('Jurnal Umum'!$C$6:$C$2564,$H47-5)) * ('Jurnal Umum'!$D$6:$D$2564<>$B$5) ,0)),""))} -> Penjualan tgl 5 | C47: {=IF($H47="","",INDEX('Jurnal Umum'!$B$6:$B$2564,$H47-5))} | D47: {=IF($H47="","",IF(INDEX('Jurnal Umum'!$F$6:$F$2564,$H47-5)="",0,INDEX('Jurnal Umum'!$F$6:$F$2564,$H47-5)))} -> 2002750 | E47: {=IF($H47="","",IF(INDEX('Jurnal Umum'!$G$6:$G$2564,$H47-5)="",0,INDEX('Jurnal Umum'!$G$6:$G$2564,$H47-5)))} -> 0 | F47: =IF($H47="","",IF($B$6="Debit",SUM($D$9:D47)-SUM($E$9:E47),SUM($E$9:E47)-SUM($D$9:D47))) -> 17556670 | H47: =IFERROR(MATCH($B$5&"-"&39,'Jurnal Umum'!$J$6:$J$909,0)+5,"") -> 146
A48: {=IF($H48="","",INDEX('Jurnal Umum'!$A$6:$A$2564,$H48-5))} -> 46240 | B48: {=IF($H48="","",IFERROR(INDEX('Jurnal Umum'!$C$6:$C$2564, MATCH(1, ('Jurnal Umum'!$A$6:$A$2564=INDEX('Jurnal Umum'!$A$6:$A$2564,$H48-5)) * ('Jurnal Umum'!$C$6:$C$2564=INDEX('Jurnal Umum'!$C$6:$C$2564,$H48-5)) * ('Jurnal Umum'!$D$6:$D$2564<>$B$5) ,0)),""))} -> Pengembalian Talangan Ongkir DMK Tgl 5 | C48: {=IF($H48="","",INDEX('Jurnal Umum'!$B$6:$B$2564,$H48-5))} | D48: {=IF($H48="","",IF(INDEX('Jurnal Umum'!$F$6:$F$2564,$H48-5)="",0,INDEX('Jurnal Umum'!$F$6:$F$2564,$H48-5)))} -> 1078280 | E48: {=IF($H48="","",IF(INDEX('Jurnal Umum'!$G$6:$G$2564,$H48-5)="",0,INDEX('Jurnal Umum'!$G$6:$G$2564,$H48-5)))} -> 0 | F48: =IF($H48="","",IF($B$6="Debit",SUM($D$9:D48)-SUM($E$9:E48),SUM($E$9:E48)-SUM($D$9:D48))) -> 18634950 | H48: =IFERROR(MATCH($B$5&"-"&40,'Jurnal Umum'!$J$6:$J$909,0)+5,"") -> 148
A49: {=IF($H49="","",INDEX('Jurnal Umum'!$A$6:$A$2564,$H49-5))} -> 46241 | B49: {=IF($H49="","",IFERROR(INDEX('Jurnal Umum'!$C$6:$C$2564, MATCH(1, ('Jurnal Umum'!$A$6:$A$2564=INDEX('Jurnal Umum'!$A$6:$A$2564,$H49-5)) * ('Jurnal Umum'!$C$6:$C$2564=INDEX('Jurnal Umum'!$C$6:$C$2564,$H49-5)) * ('Jurnal Umum'!$D$6:$D$2564<>$B$5) ,0)),""))} -> Talangan Ongkir DMK Cargo tgl 6 | C49: {=IF($H49="","",INDEX('Jurnal Umum'!$B$6:$B$2564,$H49-5))} | D49: {=IF($H49="","",IF(INDEX('Jurnal Umum'!$F$6:$F$2564,$H49-5)="",0,INDEX('Jurnal Umum'!$F$6:$F$2564,$H49-5)))} -> 0 | E49: {=IF($H49="","",IF(INDEX('Jurnal Umum'!$G$6:$G$2564,$H49-5)="",0,INDEX('Jurnal Umum'!$G$6:$G$2564,$H49-5)))} -> 2002388 | F49: =IF($H49="","",IF($B$6="Debit",SUM($D$9:D49)-SUM($E$9:E49),SUM($E$9:E49)-SUM($D$9:D49))) -> 16632562 | H49: =IFERROR(MATCH($B$5&"-"&41,'Jurnal Umum'!$J$6:$J$909,0)+5,"") -> 169
A50: {=IF($H50="","",INDEX('Jurnal Umum'!$A$6:$A$2564,$H50-5))} -> 46241 | B50: {=IF($H50="","",IFERROR(INDEX('Jurnal Umum'!$C$6:$C$2564, MATCH(1, ('Jurnal Umum'!$A$6:$A$2564=INDEX('Jurnal Umum'!$A$6:$A$2564,$H50-5)) * ('Jurnal Umum'!$C$6:$C$2564=INDEX('Jurnal Umum'!$C$6:$C$2564,$H50-5)) * ('Jurnal Umum'!$D$6:$D$2564<>$B$5) ,0)),""))} -> Pengembalian Talangan Ongkir DMK Tgl 6 | C50: {=IF($H50="","",INDEX('Jurnal Umum'!$B$6:$B$2564,$H50-5))} | D50: {=IF($H50="","",IF(INDEX('Jurnal Umum'!$F$6:$F$2564,$H50-5)="",0,INDEX('Jurnal Umum'!$F$6:$F$2564,$H50-5)))} -> 2002388 | E50: {=IF($H50="","",IF(INDEX('Jurnal Umum'!$G$6:$G$2564,$H50-5)="",0,INDEX('Jurnal Umum'!$G$6:$G$2564,$H50-5)))} -> 0 | F50: =IF($H50="","",IF($B$6="Debit",SUM($D$9:D50)-SUM($E$9:E50),SUM($E$9:E50)-SUM($D$9:D50))) -> 18634950 | H50: =IFERROR(MATCH($B$5&"-"&42,'Jurnal Umum'!$J$6:$J$909,0)+5,"") -> 174
A51: {=IF($H51="","",INDEX('Jurnal Umum'!$A$6:$A$2564,$H51-5))} -> 46241 | B51: {=IF($H51="","",IFERROR(INDEX('Jurnal Umum'!$C$6:$C$2564, MATCH(1, ('Jurnal Umum'!$A$6:$A$2564=INDEX('Jurnal Umum'!$A$6:$A$2564,$H51-5)) * ('Jurnal Umum'!$C$6:$C$2564=INDEX('Jurnal Umum'!$C$6:$C$2564,$H51-5)) * ('Jurnal Umum'!$D$6:$D$2564<>$B$5) ,0)),""))} -> Penjualan tgl 6 | C51: {=IF($H51="","",INDEX('Jurnal Umum'!$B$6:$B$2564,$H51-5))} | D51: {=IF($H51="","",IF(INDEX('Jurnal Umum'!$F$6:$F$2564,$H51-5)="",0,INDEX('Jurnal Umum'!$F$6:$F$2564,$H51-5)))} -> 2164250 | E51: {=IF($H51="","",IF(INDEX('Jurnal Umum'!$G$6:$G$2564,$H51-5)="",0,INDEX('Jurnal Umum'!$G$6:$G$2564,$H51-5)))} -> 0 | F51: =IF($H51="","",IF($B$6="Debit",SUM($D$9:D51)-SUM($E$9:E51),SUM($E$9:E51)-SUM($D$9:D51))) -> 20799200 | H51: =IFERROR(MATCH($B$5&"-"&43,'Jurnal Umum'!$J$6:$J$909,0)+5,"") -> 176
A52: {=IF($H52="","",INDEX('Jurnal Umum'!$A$6:$A$2564,$H52-5))} -> 46241 | B52: {=IF($H52="","",IFERROR(INDEX('Jurnal Umum'!$C$6:$C$2564, MATCH(1, ('Jurnal Umum'!$A$6:$A$2564=INDEX('Jurnal Umum'!$A$6:$A$2564,$H52-5)) * ('Jurnal Umum'!$C$6:$C$2564=INDEX('Jurnal Umum'!$C$6:$C$2564,$H52-5)) * ('Jurnal Umum'!$D$6:$D$2564<>$B$5) ,0)),""))} -> Penjualan Bunga Matahari ke Vendor - Mba Ciput | C52: {=IF($H52="","",INDEX('Jurnal Umum'!$B$6:$B$2564,$H52-5))} -> PV-004 | D52: {=IF($H52="","",IF(INDEX('Jurnal Umum'!$F$6:$F$2564,$H52-5)="",0,INDEX('Jurnal Umum'!$F$6:$F$2564,$H52-5)))} -> 50000 | E52: {=IF($H52="","",IF(INDEX('Jurnal Umum'!$G$6:$G$2564,$H52-5)="",0,INDEX('Jurnal Umum'!$G$6:$G$2564,$H52-5)))} -> 0 | F52: =IF($H52="","",IF($B$6="Debit",SUM($D$9:D52)-SUM($E$9:E52),SUM($E$9:E52)-SUM($D$9:D52))) -> 20849200 | H52: =IFERROR(MATCH($B$5&"-"&44,'Jurnal Umum'!$J$6:$J$909,0)+5,"") -> 186
A53: {=IF($H53="","",INDEX('Jurnal Umum'!$A$6:$A$2564,$H53-5))} -> 46242 | B53: {=IF($H53="","",IFERROR(INDEX('Jurnal Umum'!$C$6:$C$2564, MATCH(1, ('Jurnal Umum'!$A$6:$A$2564=INDEX('Jurnal Umum'!$A$6:$A$2564,$H53-5)) * ('Jurnal Umum'!$C$6:$C$2564=INDEX('Jurnal Umum'!$C$6:$C$2564,$H53-5)) * ('Jurnal Umum'!$D$6:$D$2564<>$B$5) ,0)),""))} -> Pembayaran Bunga ke Atha Flora | C53: {=IF($H53="","",INDEX('Jurnal Umum'!$B$6:$B$2564,$H53-5))} -> BK-260807-001 | D53: {=IF($H53="","",IF(INDEX('Jurnal Umum'!$F$6:$F$2564,$H53-5)="",0,INDEX('Jurnal Umum'!$F$6:$F$2564,$H53-5)))} -> 0 | E53: {=IF($H53="","",IF(INDEX('Jurnal Umum'!$G$6:$G$2564,$H53-5)="",0,INDEX('Jurnal Umum'!$G$6:$G$2564,$H53-5)))} -> 90000 | F53: =IF($H53="","",IF($B$6="Debit",SUM($D$9:D53)-SUM($E$9:E53),SUM($E$9:E53)-SUM($D$9:D53))) -> 20759200 | H53: =IFERROR(MATCH($B$5&"-"&45,'Jurnal Umum'!$J$6:$J$909,0)+5,"") -> 199
A54: {=IF($H54="","",INDEX('Jurnal Umum'!$A$6:$A$2564,$H54-5))} -> 46242 | B54: {=IF($H54="","",IFERROR(INDEX('Jurnal Umum'!$C$6:$C$2564, MATCH(1, ('Jurnal Umum'!$A$6:$A$2564=INDEX('Jurnal Umum'!$A$6:$A$2564,$H54-5)) * ('Jurnal Umum'!$C$6:$C$2564=INDEX('Jurnal Umum'!$C$6:$C$2564,$H54-5)) * ('Jurnal Umum'!$D$6:$D$2564<>$B$5) ,0)),""))} -> Pembelian Bunga ke Vendor - Mba Yeti | C54: {=IF($H54="","",INDEX('Jurnal Umum'!$B$6:$B$2564,$H54-5))} | D54: {=IF($H54="","",IF(INDEX('Jurnal Umum'!$F$6:$F$2564,$H54-5)="",0,INDEX('Jurnal Umum'!$F$6:$F$2564,$H54-5)))} -> 0 | E54: {=IF($H54="","",IF(INDEX('Jurnal Umum'!$G$6:$G$2564,$H54-5)="",0,INDEX('Jurnal Umum'!$G$6:$G$2564,$H54-5)))} -> 285000 | F54: =IF($H54="","",IF($B$6="Debit",SUM($D$9:D54)-SUM($E$9:E54),SUM($E$9:E54)-SUM($D$9:D54))) -> 20474200 | H54: =IFERROR(MATCH($B$5&"-"&46,'Jurnal Umum'!$J$6:$J$909,0)+5,"") -> 201
A55: {=IF($H55="","",INDEX('Jurnal Umum'!$A$6:$A$2564,$H55-5))} -> 46242 | B55: {=IF($H55="","",IFERROR(INDEX('Jurnal Umum'!$C$6:$C$2564, MATCH(1, ('Jurnal Umum'!$A$6:$A$2564=INDEX('Jurnal Umum'!$A$6:$A$2564,$H55-5)) * ('Jurnal Umum'!$C$6:$C$2564=INDEX('Jurnal Umum'!$C$6:$C$2564,$H55-5)) * ('Jurnal Umum'!$D$6:$D$2564<>$B$5) ,0)),""))} -> Pembelian Bunga di Rasty | C55: {=IF($H55="","",INDEX('Jurnal Umum'!$B$6:$B$2564,$H55-5))} | D55: {=IF($H55="","",IF(INDEX('Jurnal Umum'!$F$6:$F$2564,$H55-5)="",0,INDEX('Jurnal Umum'!$F$6:$F$2564,$H55-5)))} -> 0 | E55: {=IF($H55="","",IF(INDEX('Jurnal Umum'!$G$6:$G$2564,$H55-5)="",0,INDEX('Jurnal Umum'!$G$6:$G$2564,$H55-5)))} -> 10000 | F55: =IF($H55="","",IF($B$6="Debit",SUM($D$9:D55)-SUM($E$9:E55),SUM($E$9:E55)-SUM($D$9:D55))) -> 20464200 | H55: =IFERROR(MATCH($B$5&"-"&47,'Jurnal Umum'!$J$6:$J$909,0)+5,"") -> 203
A56: {=IF($H56="","",INDEX('Jurnal Umum'!$A$6:$A$2564,$H56-5))} -> 46242 | B56: {=IF($H56="","",IFERROR(INDEX('Jurnal Umum'!$C$6:$C$2564, MATCH(1, ('Jurnal Umum'!$A$6:$A$2564=INDEX('Jurnal Umum'!$A$6:$A$2564,$H56-5)) * ('Jurnal Umum'!$C$6:$C$2564=INDEX('Jurnal Umum'!$C$6:$C$2564,$H56-5)) * ('Jurnal Umum'!$D$6:$D$2564<>$B$5) ,0)),""))} -> Talangan Ongkir DMK Cargo Tgl 7 | C56: {=IF($H56="","",INDEX('Jurnal Umum'!$B$6:$B$2564,$H56-5))} | D56: {=IF($H56="","",IF(INDEX('Jurnal Umum'!$F$6:$F$2564,$H56-5)="",0,INDEX('Jurnal Umum'!$F$6:$F$2564,$H56-5)))} -> 0 | E56: {=IF($H56="","",IF(INDEX('Jurnal Umum'!$G$6:$G$2564,$H56-5)="",0,INDEX('Jurnal Umum'!$G$6:$G$2564,$H56-5)))} -> 886717 | F56: =IF($H56="","",IF($B$6="Debit",SUM($D$9:D56)-SUM($E$9:E56),SUM($E$9:E56)-SUM($D$9:D56))) -> 19577483 | H56: =IFERROR(MATCH($B$5&"-"&48,'Jurnal Umum'!$J$6:$J$909,0)+5,"") -> 205
A57: {=IF($H57="","",INDEX('Jurnal Umum'!$A$6:$A$2564,$H57-5))} -> 46242 | B57: {=IF($H57="","",IFERROR(INDEX('Jurnal Umum'!$C$6:$C$2564, MATCH(1, ('Jurnal Umum'!$A$6:$A$2564=INDEX('Jurnal Umum'!$A$6:$A$2564,$H57-5)) * ('Jurnal Umum'!$C$6:$C$2564=INDEX('Jurnal Umum'!$C$6:$C$2564,$H57-5)) * ('Jurnal Umum'!$D$6:$D$2564<>$B$5) ,0)),""))} -> Kasbon Karyawan - Mba Dinda | C57: {=IF($H57="","",INDEX('Jurnal Umum'!$B$6:$B$2564,$H57-5))} | D57: {=IF($H57="","",IF(INDEX('Jurnal Umum'!$F$6:$F$2564,$H57-5)="",0,INDEX('Jurnal Umum'!$F$6:$F$2564,$H57-5)))} -> 0 | E57: {=IF($H57="","",IF(INDEX('Jurnal Umum'!$G$6:$G$2564,$H57-5)="",0,INDEX('Jurnal Umum'!$G$6:$G$2564,$H57-5)))} -> 500000 | F57: =IF($H57="","",IF($B$6="Debit",SUM($D$9:D57)-SUM($E$9:E57),SUM($E$9:E57)-SUM($D$9:D57))) -> 19077483 | H57: =IFERROR(MATCH($B$5&"-"&49,'Jurnal Umum'!$J$6:$J$909,0)+5,"") -> 207
A58: {=IF($H58="","",INDEX('Jurnal Umum'!$A$6:$A$2564,$H58-5))} -> 46242 | B58: {=IF($H58="","",IFERROR(INDEX('Jurnal Umum'!$C$6:$C$2564, MATCH(1, ('Jurnal Umum'!$A$6:$A$2564=INDEX('Jurnal Umum'!$A$6:$A$2564,$H58-5)) * ('Jurnal Umum'!$C$6:$C$2564=INDEX('Jurnal Umum'!$C$6:$C$2564,$H58-5)) * ('Jurnal Umum'!$D$6:$D$2564<>$B$5) ,0)),""))} -> Pembayaran Gaji Mingguan - Mas Sandi | C58: {=IF($H58="","",INDEX('Jurnal Umum'!$B$6:$B$2564,$H58-5))} | D58: {=IF($H58="","",IF(INDEX('Jurnal Umum'!$F$6:$F$2564,$H58-5)="",0,INDEX('Jurnal Umum'!$F$6:$F$2564,$H58-5)))} -> 0 | E58: {=IF($H58="","",IF(INDEX('Jurnal Umum'!$G$6:$G$2564,$H58-5)="",0,INDEX('Jurnal Umum'!$G$6:$G$2564,$H58-5)))} -> 500000 | F58: =IF($H58="","",IF($B$6="Debit",SUM($D$9:D58)-SUM($E$9:E58),SUM($E$9:E58)-SUM($D$9:D58))) -> 18577483 | H58: =IFERROR(MATCH($B$5&"-"&50,'Jurnal Umum'!$J$6:$J$909,0)+5,"") -> 209
A59: {=IF($H59="","",INDEX('Jurnal Umum'!$A$6:$A$2564,$H59-5))} -> 46242 | B59: {=IF($H59="","",IFERROR(INDEX('Jurnal Umum'!$C$6:$C$2564, MATCH(1, ('Jurnal Umum'!$A$6:$A$2564=INDEX('Jurnal Umum'!$A$6:$A$2564,$H59-5)) * ('Jurnal Umum'!$C$6:$C$2564=INDEX('Jurnal Umum'!$C$6:$C$2564,$H59-5)) * ('Jurnal Umum'!$D$6:$D$2564<>$B$5) ,0)),""))} -> Pengembalian Talangan Ongkir DMK Cargo tgl 7 | C59: {=IF($H59="","",INDEX('Jurnal Umum'!$B$6:$B$2564,$H59-5))} | D59: {=IF($H59="","",IF(INDEX('Jurnal Umum'!$F$6:$F$2564,$H59-5)="",0,INDEX('Jurnal Umum'!$F$6:$F$2564,$H59-5)))} -> 886717 | E59: {=IF($H59="","",IF(INDEX('Jurnal Umum'!$G$6:$G$2564,$H59-5)="",0,INDEX('Jurnal Umum'!$G$6:$G$2564,$H59-5)))} -> 0 | F59: =IF($H59="","",IF($B$6="Debit",SUM($D$9:D59)-SUM($E$9:E59),SUM($E$9:E59)-SUM($D$9:D59))) -> 19464200 | H59: =IFERROR(MATCH($B$5&"-"&51,'Jurnal Umum'!$J$6:$J$909,0)+5,"") -> 210
A60: {=IF($H60="","",INDEX('Jurnal Umum'!$A$6:$A$2564,$H60-5))} -> 46242 | B60: {=IF($H60="","",IFERROR(INDEX('Jurnal Umum'!$C$6:$C$2564, MATCH(1, ('Jurnal Umum'!$A$6:$A$2564=INDEX('Jurnal Umum'!$A$6:$A$2564,$H60-5)) * ('Jurnal Umum'!$C$6:$C$2564=INDEX('Jurnal Umum'!$C$6:$C$2564,$H60-5)) * ('Jurnal Umum'!$D$6:$D$2564<>$B$5) ,0)),""))} -> Penjualan tgl 7 | C60: {=IF($H60="","",INDEX('Jurnal Umum'!$B$6:$B$2564,$H60-5))} | D60: {=IF($H60="","",IF(INDEX('Jurnal Umum'!$F$6:$F$2564,$H60-5)="",0,INDEX('Jurnal Umum'!$F$6:$F$2564,$H60-5)))} -> 2085000 | E60: {=IF($H60="","",IF(INDEX('Jurnal Umum'!$G$6:$G$2564,$H60-5)="",0,INDEX('Jurnal Umum'!$G$6:$G$2564,$H60-5)))} -> 0 | F60: =IF($H60="","",IF($B$6="Debit",SUM($D$9:D60)-SUM($E$9:E60),SUM($E$9:E60)-SUM($D$9:D60))) -> 21549200 | H60: =IFERROR(MATCH($B$5&"-"&52,'Jurnal Umum'!$J$6:$J$909,0)+5,"") -> 212
A61: {=IF($H61="","",INDEX('Jurnal Umum'!$A$6:$A$2564,$H61-5))} -> 46243 | B61: {=IF($H61="","",IFERROR(INDEX('Jurnal Umum'!$C$6:$C$2564, MATCH(1, ('Jurnal Umum'!$A$6:$A$2564=INDEX('Jurnal Umum'!$A$6:$A$2564,$H61-5)) * ('Jurnal Umum'!$C$6:$C$2564=INDEX('Jurnal Umum'!$C$6:$C$2564,$H61-5)) * ('Jurnal Umum'!$D$6:$D$2564<>$B$5) ,0)),""))} -> Talangan Ongkir DMK Cargo tgl 08 | C61: {=IF($H61="","",INDEX('Jurnal Umum'!$B$6:$B$2564,$H61-5))} | D61: {=IF($H61="","",IF(INDEX('Jurnal Umum'!$F$6:$F$2564,$H61-5)="",0,INDEX('Jurnal Umum'!$F$6:$F$2564,$H61-5)))} -> 0 | E61: {=IF($H61="","",IF(INDEX('Jurnal Umum'!$G$6:$G$2564,$H61-5)="",0,INDEX('Jurnal Umum'!$G$6:$G$2564,$H61-5)))} -> 1154360 | F61: =IF($H61="","",IF($B$6="Debit",SUM($D$9:D61)-SUM($E$9:E61),SUM($E$9:E61)-SUM($D$9:D61))) -> 20394840 | H61: =IFERROR(MATCH($B$5&"-"&53,'Jurnal Umum'!$J$6:$J$909,0)+5,"") -> 229
A62: {=IF($H62="","",INDEX('Jurnal Umum'!$A$6:$A$2564,$H62-5))} -> 46243 | B62: {=IF($H62="","",IFERROR(INDEX('Jurnal Umum'!$C$6:$C$2564, MATCH(1, ('Jurnal Umum'!$A$6:$A$2564=INDEX('Jurnal Umum'!$A$6:$A$2564,$H62-5)) * ('Jurnal Umum'!$C$6:$C$2564=INDEX('Jurnal Umum'!$C$6:$C$2564,$H62-5)) * ('Jurnal Umum'!$D$6:$D$2564<>$B$5) ,0)),""))} -> Penjualan Bunga ke Vendor - Mas Abizar | C62: {=IF($H62="","",INDEX('Jurnal Umum'!$B$6:$B$2564,$H62-5))} -> PV-006 | D62: {=IF($H62="","",IF(INDEX('Jurnal Umum'!$F$6:$F$2564,$H62-5)="",0,INDEX('Jurnal Umum'!$F$6:$F$2564,$H62-5)))} -> 32000 | E62: {=IF($H62="","",IF(INDEX('Jurnal Umum'!$G$6:$G$2564,$H62-5)="",0,INDEX('Jurnal Umum'!$G$6:$G$2564,$H62-5)))} -> 0 | F62: =IF($H62="","",IF($B$6="Debit",SUM($D$9:D62)-SUM($E$9:E62),SUM($E$9:E62)-SUM($D$9:D62))) -> 20426840 | H62: =IFERROR(MATCH($B$5&"-"&54,'Jurnal Umum'!$J$6:$J$909,0)+5,"") -> 230
A63: {=IF($H63="","",INDEX('Jurnal Umum'!$A$6:$A$2564,$H63-5))} -> 46243 | B63: {=IF($H63="","",IFERROR(INDEX('Jurnal Umum'!$C$6:$C$2564, MATCH(1, ('Jurnal Umum'!$A$6:$A$2564=INDEX('Jurnal Umum'!$A$6:$A$2564,$H63-5)) * ('Jurnal Umum'!$C$6:$C$2564=INDEX('Jurnal Umum'!$C$6:$C$2564,$H63-5)) * ('Jurnal Umum'!$D$6:$D$2564<>$B$5) ,0)),""))} -> Pengembalian Talangan Ongkir tgl 08 | C63: {=IF($H63="","",INDEX('Jurnal Umum'!$B$6:$B$2564,$H63-5))} | D63: {=IF($H63="","",IF(INDEX('Jurnal Umum'!$F$6:$F$2564,$H63-5)="",0,INDEX('Jurnal Umum'!$F$6:$F$2564,$H63-5)))} -> 1154360 | E63: {=IF($H63="","",IF(INDEX('Jurnal Umum'!$G$6:$G$2564,$H63-5)="",0,INDEX('Jurnal Umum'!$G$6:$G$2564,$H63-5)))} -> 0 | F63: =IF($H63="","",IF($B$6="Debit",SUM($D$9:D63)-SUM($E$9:E63),SUM($E$9:E63)-SUM($D$9:D63))) -> 21581200 | H63: =IFERROR(MATCH($B$5&"-"&55,'Jurnal Umum'!$J$6:$J$909,0)+5,"") -> 232
A64: {=IF($H64="","",INDEX('Jurnal Umum'!$A$6:$A$2564,$H64-5))} -> 46243 | B64: {=IF($H64="","",IFERROR(INDEX('Jurnal Umum'!$C$6:$C$2564, MATCH(1, ('Jurnal Umum'!$A$6:$A$2564=INDEX('Jurnal Umum'!$A$6:$A$2564,$H64-5)) * ('Jurnal Umum'!$C$6:$C$2564=INDEX('Jurnal Umum'!$C$6:$C$2564,$H64-5)) * ('Jurnal Umum'!$D$6:$D$2564<>$B$5) ,0)),""))} -> Penjualan tanggal 8 | C64: {=IF($H64="","",INDEX('Jurnal Umum'!$B$6:$B$2564,$H64-5))} | D64: {=IF($H64="","",IF(INDEX('Jurnal Umum'!$F$6:$F$2564,$H64-5)="",0,INDEX('Jurnal Umum'!$F$6:$F$2564,$H64-5)))} -> 1176250 | E64: {=IF($H64="","",IF(INDEX('Jurnal Umum'!$G$6:$G$2564,$H64-5)="",0,INDEX('Jurnal Umum'!$G$6:$G$2564,$H64-5)))} -> 0 | F64: =IF($H64="","",IF($B$6="Debit",SUM($D$9:D64)-SUM($E$9:E64),SUM($E$9:E64)-SUM($D$9:D64))) -> 22757450 | H64: =IFERROR(MATCH($B$5&"-"&56,'Jurnal Umum'!$J$6:$J$909,0)+5,"") -> 234
A65: {=IF($H65="","",INDEX('Jurnal Umum'!$A$6:$A$2564,$H65-5))} -> 46244 | B65: {=IF($H65="","",IFERROR(INDEX('Jurnal Umum'!$C$6:$C$2564, MATCH(1, ('Jurnal Umum'!$A$6:$A$2564=INDEX('Jurnal Umum'!$A$6:$A$2564,$H65-5)) * ('Jurnal Umum'!$C$6:$C$2564=INDEX('Jurnal Umum'!$C$6:$C$2564,$H65-5)) * ('Jurnal Umum'!$D$6:$D$2564<>$B$5) ,0)),""))} -> Pembelian token PLN Cold Storage | C65: {=IF($H65="","",INDEX('Jurnal Umum'!$B$6:$B$2564,$H65-5))} | D65: {=IF($H65="","",IF(INDEX('Jurnal Umum'!$F$6:$F$2564,$H65-5)="",0,INDEX('Jurnal Umum'!$F$6:$F$2564,$H65-5)))} -> 0 | E65: {=IF($H65="","",IF(INDEX('Jurnal Umum'!$G$6:$G$2564,$H65-5)="",0,INDEX('Jurnal Umum'!$G$6:$G$2564,$H65-5)))} -> 503000 | F65: =IF($H65="","",IF($B$6="Debit",SUM($D$9:D65)-SUM($E$9:E65),SUM($E$9:E65)-SUM($D$9:D65))) -> 22254450 | H65: =IFERROR(MATCH($B$5&"-"&57,'Jurnal Umum'!$J$6:$J$909,0)+5,"") -> 245
A66: {=IF($H66="","",INDEX('Jurnal Umum'!$A$6:$A$2564,$H66-5))} -> 46244 | B66: {=IF($H66="","",IFERROR(INDEX('Jurnal Umum'!$C$6:$C$2564, MATCH(1, ('Jurnal Umum'!$A$6:$A$2564=INDEX('Jurnal Umum'!$A$6:$A$2564,$H66-5)) * ('Jurnal Umum'!$C$6:$C$2564=INDEX('Jurnal Umum'!$C$6:$C$2564,$H66-5)) * ('Jurnal Umum'!$D$6:$D$2564<>$B$5) ,0)),""))} -> Pembelian Bunga di Vendor - Mba Yeti | C66: {=IF($H66="","",INDEX('Jurnal Umum'!$B$6:$B$2564,$H66-5))} | D66: {=IF($H66="","",IF(INDEX('Jurnal Umum'!$F$6:$F$2564,$H66-5)="",0,INDEX('Jurnal Umum'!$F$6:$F$2564,$H66-5)))} -> 0 | E66: {=IF($H66="","",IF(INDEX('Jurnal Umum'!$G$6:$G$2564,$H66-5)="",0,INDEX('Jurnal Umum'!$G$6:$G$2564,$H66-5)))} -> 839000 | F66: =IF($H66="","",IF($B$6="Debit",SUM($D$9:D66)-SUM($E$9:E66),SUM($E$9:E66)-SUM($D$9:D66))) -> 21415450 | H66: =IFERROR(MATCH($B$5&"-"&58,'Jurnal Umum'!$J$6:$J$909,0)+5,"") -> 247
A67: {=IF($H67="","",INDEX('Jurnal Umum'!$A$6:$A$2564,$H67-5))} -> 46244 | B67: {=IF($H67="","",IFERROR(INDEX('Jurnal Umum'!$C$6:$C$2564, MATCH(1, ('Jurnal Umum'!$A$6:$A$2564=INDEX('Jurnal Umum'!$A$6:$A$2564,$H67-5)) * ('Jurnal Umum'!$C$6:$C$2564=INDEX('Jurnal Umum'!$C$6:$C$2564,$H67-5)) * ('Jurnal Umum'!$D$6:$D$2564<>$B$5) ,0)),""))} -> Pembelian Bunga di WKF | C67: {=IF($H67="","",INDEX('Jurnal Umum'!$B$6:$B$2564,$H67-5))} -> BK-260810-001 | D67: {=IF($H67="","",IF(INDEX('Jurnal Umum'!$F$6:$F$2564,$H67-5)="",0,INDEX('Jurnal Umum'!$F$6:$F$2564,$H67-5)))} -> 0 | E67: {=IF($H67="","",IF(INDEX('Jurnal Umum'!$G$6:$G$2564,$H67-5)="",0,INDEX('Jurnal Umum'!$G$6:$G$2564,$H67-5)))} -> 835000 | F67: =IF($H67="","",IF($B$6="Debit",SUM($D$9:D67)-SUM($E$9:E67),SUM($E$9:E67)-SUM($D$9:D67))) -> 20580450 | H67: =IFERROR(MATCH($B$5&"-"&59,'Jurnal Umum'!$J$6:$J$909,0)+5,"") -> 249
A68: {=IF($H68="","",INDEX('Jurnal Umum'!$A$6:$A$2564,$H68-5))} -> 46245 | B68: {=IF($H68="","",IFERROR(INDEX('Jurnal Umum'!$C$6:$C$2564, MATCH(1, ('Jurnal Umum'!$A$6:$A$2564=INDEX('Jurnal Umum'!$A$6:$A$2564,$H68-5)) * ('Jurnal Umum'!$C$6:$C$2564=INDEX('Jurnal Umum'!$C$6:$C$2564,$H68-5)) * ('Jurnal Umum'!$D$6:$D$2564<>$B$5) ,0)),""))} -> Talangan Ongkir DMK Cargo tgl 11 | C68: {=IF($H68="","",INDEX('Jurnal Umum'!$B$6:$B$2564,$H68-5))} | D68: {=IF($H68="","",IF(INDEX('Jurnal Umum'!$F$6:$F$2564,$H68-5)="",0,INDEX('Jurnal Umum'!$F$6:$F$2564,$H68-5)))} -> 0 | E68: {=IF($H68="","",IF(INDEX('Jurnal Umum'!$G$6:$G$2564,$H68-5)="",0,INDEX('Jurnal Umum'!$G$6:$G$2564,$H68-5)))} -> 3402396 | F68: =IF($H68="","",IF($B$6="Debit",SUM($D$9:D68)-SUM($E$9:E68),SUM($E$9:E68)-SUM($D$9:D68))) -> 17178054 | H68: =IFERROR(MATCH($B$5&"-"&60,'Jurnal Umum'!$J$6:$J$909,0)+5,"") -> 263
A69: {=IF($H69="","",INDEX('Jurnal Umum'!$A$6:$A$2564,$H69-5))} -> 46245 | B69: {=IF($H69="","",IFERROR(INDEX('Jurnal Umum'!$C$6:$C$2564, MATCH(1, ('Jurnal Umum'!$A$6:$A$2564=INDEX('Jurnal Umum'!$A$6:$A$2564,$H69-5)) * ('Jurnal Umum'!$C$6:$C$2564=INDEX('Jurnal Umum'!$C$6:$C$2564,$H69-5)) * ('Jurnal Umum'!$D$6:$D$2564<>$B$5) ,0)),""))} -> Pembayaran Kardus Packing | C69: {=IF($H69="","",INDEX('Jurnal Umum'!$B$6:$B$2564,$H69-5))} | D69: {=IF($H69="","",IF(INDEX('Jurnal Umum'!$F$6:$F$2564,$H69-5)="",0,INDEX('Jurnal Umum'!$F$6:$F$2564,$H69-5)))} -> 0 | E69: {=IF($H69="","",IF(INDEX('Jurnal Umum'!$G$6:$G$2564,$H69-5)="",0,INDEX('Jurnal Umum'!$G$6:$G$2564,$H69-5)))} -> 1000000 | F69: =IF($H69="","",IF($B$6="Debit",SUM($D$9:D69)-SUM($E$9:E69),SUM($E$9:E69)-SUM($D$9:D69))) -> 16178054 | H69: =IFERROR(MATCH($B$5&"-"&61,'Jurnal Umum'!$J$6:$J$909,0)+5,"") -> 265
A70: {=IF($H70="","",INDEX('Jurnal Umum'!$A$6:$A$2564,$H70-5))} -> 46245 | B70: {=IF($H70="","",IFERROR(INDEX('Jurnal Umum'!$C$6:$C$2564, MATCH(1, ('Jurnal Umum'!$A$6:$A$2564=INDEX('Jurnal Umum'!$A$6:$A$2564,$H70-5)) * ('Jurnal Umum'!$C$6:$C$2564=INDEX('Jurnal Umum'!$C$6:$C$2564,$H70-5)) * ('Jurnal Umum'!$D$6:$D$2564<>$B$5) ,0)),""))} -> Tarik Tunai untuk kas operasional | C70: {=IF($H70="","",INDEX('Jurnal Umum'!$B$6:$B$2564,$H70-5))} | D70: {=IF($H70="","",IF(INDEX('Jurnal Umum'!$F$6:$F$2564,$H70-5)="",0,INDEX('Jurnal Umum'!$F$6:$F$2564,$H70-5)))} -> 0 | E70: {=IF($H70="","",IF(INDEX('Jurnal Umum'!$G$6:$G$2564,$H70-5)="",0,INDEX('Jurnal Umum'!$G$6:$G$2564,$H70-5)))} -> 600000 | F70: =IF($H70="","",IF($B$6="Debit",SUM($D$9:D70)-SUM($E$9:E70),SUM($E$9:E70)-SUM($D$9:D70))) -> 15578054 | H70: =IFERROR(MATCH($B$5&"-"&62,'Jurnal Umum'!$J$6:$J$909,0)+5,"") -> 267
A71: {=IF($H71="","",INDEX('Jurnal Umum'!$A$6:$A$2564,$H71-5))} -> 46245 | B71: {=IF($H71="","",IFERROR(INDEX('Jurnal Umum'!$C$6:$C$2564, MATCH(1, ('Jurnal Umum'!$A$6:$A$2564=INDEX('Jurnal Umum'!$A$6:$A$2564,$H71-5)) * ('Jurnal Umum'!$C$6:$C$2564=INDEX('Jurnal Umum'!$C$6:$C$2564,$H71-5)) * ('Jurnal Umum'!$D$6:$D$2564<>$B$5) ,0)),""))} -> Pembayaran penjualan tanggal 10 | C71: {=IF($H71="","",INDEX('Jurnal Umum'!$B$6:$B$2564,$H71-5))} | D71: {=IF($H71="","",IF(INDEX('Jurnal Umum'!$F$6:$F$2564,$H71-5)="",0,INDEX('Jurnal Umum'!$F$6:$F$2564,$H71-5)))} -> 3727000 | E71: {=IF($H71="","",IF(INDEX('Jurnal Umum'!$G$6:$G$2564,$H71-5)="",0,INDEX('Jurnal Umum'!$G$6:$G$2564,$H71-5)))} -> 0 | F71: =IF($H71="","",IF($B$6="Debit",SUM($D$9:D71)-SUM($E$9:E71),SUM($E$9:E71)-SUM($D$9:D71))) -> 19305054 | H71: =IFERROR(MATCH($B$5&"-"&63,'Jurnal Umum'!$J$6:$J$909,0)+5,"") -> 280
A72: {=IF($H72="","",INDEX('Jurnal Umum'!$A$6:$A$2564,$H72-5))} -> 46245 | B72: {=IF($H72="","",IFERROR(INDEX('Jurnal Umum'!$C$6:$C$2564, MATCH(1, ('Jurnal Umum'!$A$6:$A$2564=INDEX('Jurnal Umum'!$A$6:$A$2564,$H72-5)) * ('Jurnal Umum'!$C$6:$C$2564=INDEX('Jurnal Umum'!$C$6:$C$2564,$H72-5)) * ('Jurnal Umum'!$D$6:$D$2564<>$B$5) ,0)),""))} -> Pengembalian talangan DMK Cargo tgl 10 | C72: {=IF($H72="","",INDEX('Jurnal Umum'!$B$6:$B$2564,$H72-5))} | D72: {=IF($H72="","",IF(INDEX('Jurnal Umum'!$F$6:$F$2564,$H72-5)="",0,INDEX('Jurnal Umum'!$F$6:$F$2564,$H72-5)))} -> 3402396 | E72: {=IF($H72="","",IF(INDEX('Jurnal Umum'!$G$6:$G$2564,$H72-5)="",0,INDEX('Jurnal Umum'!$G$6:$G$2564,$H72-5)))} -> 0 | F72: =IF($H72="","",IF($B$6="Debit",SUM($D$9:D72)-SUM($E$9:E72),SUM($E$9:E72)-SUM($D$9:D72))) -> 22707450 | H72: =IFERROR(MATCH($B$5&"-"&64,'Jurnal Umum'!$J$6:$J$909,0)+5,"") -> 282
A73: {=IF($H73="","",INDEX('Jurnal Umum'!$A$6:$A$2564,$H73-5))} -> 46246 | B73: {=IF($H73="","",IFERROR(INDEX('Jurnal Umum'!$C$6:$C$2564, MATCH(1, ('Jurnal Umum'!$A$6:$A$2564=INDEX('Jurnal Umum'!$A$6:$A$2564,$H73-5)) * ('Jurnal Umum'!$C$6:$C$2564=INDEX('Jurnal Umum'!$C$6:$C$2564,$H73-5)) * ('Jurnal Umum'!$D$6:$D$2564<>$B$5) ,0)),""))} -> Pembelian Bunga ke WKF | C73: {=IF($H73="","",INDEX('Jurnal Umum'!$B$6:$B$2564,$H73-5))} -> BK-260812-001 | D73: {=IF($H73="","",IF(INDEX('Jurnal Umum'!$F$6:$F$2564,$H73-5)="",0,INDEX('Jurnal Umum'!$F$6:$F$2564,$H73-5)))} -> 0 | E73: {=IF($H73="","",IF(INDEX('Jurnal Umum'!$G$6:$G$2564,$H73-5)="",0,INDEX('Jurnal Umum'!$G$6:$G$2564,$H73-5)))} -> 215000 | F73: =IF($H73="","",IF($B$6="Debit",SUM($D$9:D73)-SUM($E$9:E73),SUM($E$9:E73)-SUM($D$9:D73))) -> 22492450 | H73: =IFERROR(MATCH($B$5&"-"&65,'Jurnal Umum'!$J$6:$J$909,0)+5,"") -> 287
A74: {=IF($H74="","",INDEX('Jurnal Umum'!$A$6:$A$2564,$H74-5))} -> 46246 | B74: {=IF($H74="","",IFERROR(INDEX('Jurnal Umum'!$C$6:$C$2564, MATCH(1, ('Jurnal Umum'!$A$6:$A$2564=INDEX('Jurnal Umum'!$A$6:$A$2564,$H74-5)) * ('Jurnal Umum'!$C$6:$C$2564=INDEX('Jurnal Umum'!$C$6:$C$2564,$H74-5)) * ('Jurnal Umum'!$D$6:$D$2564<>$B$5) ,0)),""))} -> Talangan Ongkir DMK Cargo tanggal 11 | C74: {=IF($H74="","",INDEX('Jurnal Umum'!$B$6:$B$2564,$H74-5))} | D74: {=IF($H74="","",IF(INDEX('Jurnal Umum'!$F$6:$F$2564,$H74-5)="",0,INDEX('Jurnal Umum'!$F$6:$F$2564,$H74-5)))} -> 0 | E74: {=IF($H74="","",IF(INDEX('Jurnal Umum'!$G$6:$G$2564,$H74-5)="",0,INDEX('Jurnal Umum'!$G$6:$G$2564,$H74-5)))} -> 1295496 | F74: =IF($H74="","",IF($B$6="Debit",SUM($D$9:D74)-SUM($E$9:E74),SUM($E$9:E74)-SUM($D$9:D74))) -> 21196954 | H74: =IFERROR(MATCH($B$5&"-"&66,'Jurnal Umum'!$J$6:$J$909,0)+5,"") -> 289
A75: {=IF($H75="","",INDEX('Jurnal Umum'!$A$6:$A$2564,$H75-5))} -> 46246 | B75: {=IF($H75="","",IFERROR(INDEX('Jurnal Umum'!$C$6:$C$2564, MATCH(1, ('Jurnal Umum'!$A$6:$A$2564=INDEX('Jurnal Umum'!$A$6:$A$2564,$H75-5)) * ('Jurnal Umum'!$C$6:$C$2564=INDEX('Jurnal Umum'!$C$6:$C$2564,$H75-5)) * ('Jurnal Umum'!$D$6:$D$2564<>$B$5) ,0)),""))} -> Pembelian Bunga di Vendor - Mba Yeti | C75: {=IF($H75="","",INDEX('Jurnal Umum'!$B$6:$B$2564,$H75-5))} | D75: {=IF($H75="","",IF(INDEX('Jurnal Umum'!$F$6:$F$2564,$H75-5)="",0,INDEX('Jurnal Umum'!$F$6:$F$2564,$H75-5)))} -> 0 | E75: {=IF($H75="","",IF(INDEX('Jurnal Umum'!$G$6:$G$2564,$H75-5)="",0,INDEX('Jurnal Umum'!$G$6:$G$2564,$H75-5)))} -> 275000 | F75: =IF($H75="","",IF($B$6="Debit",SUM($D$9:D75)-SUM($E$9:E75),SUM($E$9:E75)-SUM($D$9:D75))) -> 20921954 | H75: =IFERROR(MATCH($B$5&"-"&67,'Jurnal Umum'!$J$6:$J$909,0)+5,"") -> 291
A76: {=IF($H76="","",INDEX('Jurnal Umum'!$A$6:$A$2564,$H76-5))} -> 46246 | B76: {=IF($H76="","",IFERROR(INDEX('Jurnal Umum'!$C$6:$C$2564, MATCH(1, ('Jurnal Umum'!$A$6:$A$2564=INDEX('Jurnal Umum'!$A$6:$A$2564,$H76-5)) * ('Jurnal Umum'!$C$6:$C$2564=INDEX('Jurnal Umum'!$C$6:$C$2564,$H76-5)) * ('Jurnal Umum'!$D$6:$D$2564<>$B$5) ,0)),""))} -> Pembayaran Gaji Karyawan - Mba Dinda | C76: {=IF($H76="","",INDEX('Jurnal Umum'!$B$6:$B$2564,$H76-5))} | D76: {=IF($H76="","",IF(INDEX('Jurnal Umum'!$F$6:$F$2564,$H76-5)="",0,INDEX('Jurnal Umum'!$F$6:$F$2564,$H76-5)))} -> 0 | E76: {=IF($H76="","",IF(INDEX('Jurnal Umum'!$G$6:$G$2564,$H76-5)="",0,INDEX('Jurnal Umum'!$G$6:$G$2564,$H76-5)))} -> 750000 | F76: =IF($H76="","",IF($B$6="Debit",SUM($D$9:D76)-SUM($E$9:E76),SUM($E$9:E76)-SUM($D$9:D76))) -> 20171954 | H76: =IFERROR(MATCH($B$5&"-"&68,'Jurnal Umum'!$J$6:$J$909,0)+5,"") -> 293
A77: {=IF($H77="","",INDEX('Jurnal Umum'!$A$6:$A$2564,$H77-5))} -> 46246 | B77: {=IF($H77="","",IFERROR(INDEX('Jurnal Umum'!$C$6:$C$2564, MATCH(1, ('Jurnal Umum'!$A$6:$A$2564=INDEX('Jurnal Umum'!$A$6:$A$2564,$H77-5)) * ('Jurnal Umum'!$C$6:$C$2564=INDEX('Jurnal Umum'!$C$6:$C$2564,$H77-5)) * ('Jurnal Umum'!$D$6:$D$2564<>$B$5) ,0)),""))} -> Pengembalian talangan Ongkir DMK Cargo tgl 11 | C77: {=IF($H77="","",INDEX('Jurnal Umum'!$B$6:$B$2564,$H77-5))} | D77: {=IF($H77="","",IF(INDEX('Jurnal Umum'!$F$6:$F$2564,$H77-5)="",0,INDEX('Jurnal Umum'!$F$6:$F$2564,$H77-5)))} -> 1295496 | E77: {=IF($H77="","",IF(INDEX('Jurnal Umum'!$G$6:$G$2564,$H77-5)="",0,INDEX('Jurnal Umum'!$G$6:$G$2564,$H77-5)))} -> 0 | F77: =IF($H77="","",IF($B$6="Debit",SUM($D$9:D77)-SUM($E$9:E77),SUM($E$9:E77)-SUM($D$9:D77))) -> 21467450 | H77: =IFERROR(MATCH($B$5&"-"&69,'Jurnal Umum'!$J$6:$J$909,0)+5,"") -> 310
A78: {=IF($H78="","",INDEX('Jurnal Umum'!$A$6:$A$2564,$H78-5))} -> 46246 | B78: {=IF($H78="","",IFERROR(INDEX('Jurnal Umum'!$C$6:$C$2564, MATCH(1, ('Jurnal Umum'!$A$6:$A$2564=INDEX('Jurnal Umum'!$A$6:$A$2564,$H78-5)) * ('Jurnal Umum'!$C$6:$C$2564=INDEX('Jurnal Umum'!$C$6:$C$2564,$H78-5)) * ('Jurnal Umum'!$D$6:$D$2564<>$B$5) ,0)),""))} -> Pembayaran Penjualan tanggal 11 | C78: {=IF($H78="","",INDEX('Jurnal Umum'!$B$6:$B$2564,$H78-5))} | D78: {=IF($H78="","",IF(INDEX('Jurnal Umum'!$F$6:$F$2564,$H78-5)="",0,INDEX('Jurnal Umum'!$F$6:$F$2564,$H78-5)))} -> 1827000 | E78: {=IF($H78="","",IF(INDEX('Jurnal Umum'!$G$6:$G$2564,$H78-5)="",0,INDEX('Jurnal Umum'!$G$6:$G$2564,$H78-5)))} -> 0 | F78: =IF($H78="","",IF($B$6="Debit",SUM($D$9:D78)-SUM($E$9:E78),SUM($E$9:E78)-SUM($D$9:D78))) -> 23294450 | H78: =IFERROR(MATCH($B$5&"-"&70,'Jurnal Umum'!$J$6:$J$909,0)+5,"") -> 312
A79: {=IF($H79="","",INDEX('Jurnal Umum'!$A$6:$A$2564,$H79-5))} -> 46247 | B79: {=IF($H79="","",IFERROR(INDEX('Jurnal Umum'!$C$6:$C$2564, MATCH(1, ('Jurnal Umum'!$A$6:$A$2564=INDEX('Jurnal Umum'!$A$6:$A$2564,$H79-5)) * ('Jurnal Umum'!$C$6:$C$2564=INDEX('Jurnal Umum'!$C$6:$C$2564,$H79-5)) * ('Jurnal Umum'!$D$6:$D$2564<>$B$5) ,0)),""))} -> Talangan Ongkir DMK Cargo tanggal 12 | C79: {=IF($H79="","",INDEX('Jurnal Umum'!$B$6:$B$2564,$H79-5))} | D79: {=IF($H79="","",IF(INDEX('Jurnal Umum'!$F$6:$F$2564,$H79-5)="",0,INDEX('Jurnal Umum'!$F$6:$F$2564,$H79-5)))} -> 0 | E79: {=IF($H79="","",IF(INDEX('Jurnal Umum'!$G$6:$G$2564,$H79-5)="",0,INDEX('Jurnal Umum'!$G$6:$G$2564,$H79-5)))} -> 1561995 | F79: =IF($H79="","",IF($B$6="Debit",SUM($D$9:D79)-SUM($E$9:E79),SUM($E$9:E79)-SUM($D$9:D79))) -> 21732455 | H79: =IFERROR(MATCH($B$5&"-"&71,'Jurnal Umum'!$J$6:$J$909,0)+5,"") -> 325
A80: {=IF($H80="","",INDEX('Jurnal Umum'!$A$6:$A$2564,$H80-5))} -> 46247 | B80: {=IF($H80="","",IFERROR(INDEX('Jurnal Umum'!$C$6:$C$2564, MATCH(1, ('Jurnal Umum'!$A$6:$A$2564=INDEX('Jurnal Umum'!$A$6:$A$2564,$H80-5)) * ('Jurnal Umum'!$C$6:$C$2564=INDEX('Jurnal Umum'!$C$6:$C$2564,$H80-5)) * ('Jurnal Umum'!$D$6:$D$2564<>$B$5) ,0)),""))} -> Pembelian Bunga di Bu Nisa | C80: {=IF($H80="","",INDEX('Jurnal Umum'!$B$6:$B$2564,$H80-5))} | D80: {=IF($H80="","",IF(INDEX('Jurnal Umum'!$F$6:$F$2564,$H80-5)="",0,INDEX('Jurnal Umum'!$F$6:$F$2564,$H80-5)))} -> 0 | E80: {=IF($H80="","",IF(INDEX('Jurnal Umum'!$G$6:$G$2564,$H80-5)="",0,INDEX('Jurnal Umum'!$G$6:$G$2564,$H80-5)))} -> 150000 | F80: =IF($H80="","",IF($B$6="Debit",SUM($D$9:D80)-SUM($E$9:E80),SUM($E$9:E80)-SUM($D$9:D80))) -> 21582455 | H80: =IFERROR(MATCH($B$5&"-"&72,'Jurnal Umum'!$J$6:$J$909,0)+5,"") -> 327
A81: {=IF($H81="","",INDEX('Jurnal Umum'!$A$6:$A$2564,$H81-5))} -> 46247 | B81: {=IF($H81="","",IFERROR(INDEX('Jurnal Umum'!$C$6:$C$2564, MATCH(1, ('Jurnal Umum'!$A$6:$A$2564=INDEX('Jurnal Umum'!$A$6:$A$2564,$H81-5)) * ('Jurnal Umum'!$C$6:$C$2564=INDEX('Jurnal Umum'!$C$6:$C$2564,$H81-5)) * ('Jurnal Umum'!$D$6:$D$2564<>$B$5) ,0)),""))} -> Refund ke Sekar | C81: {=IF($H81="","",INDEX('Jurnal Umum'!$B$6:$B$2564,$H81-5))} | D81: {=IF($H81="","",IF(INDEX('Jurnal Umum'!$F$6:$F$2564,$H81-5)="",0,INDEX('Jurnal Umum'!$F$6:$F$2564,$H81-5)))} -> 0 | E81: {=IF($H81="","",IF(INDEX('Jurnal Umum'!$G$6:$G$2564,$H81-5)="",0,INDEX('Jurnal Umum'!$G$6:$G$2564,$H81-5)))} -> 100000 | F81: =IF($H81="","",IF($B$6="Debit",SUM($D$9:D81)-SUM($E$9:E81),SUM($E$9:E81)-SUM($D$9:D81))) -> 21482455 | H81: =IFERROR(MATCH($B$5&"-"&73,'Jurnal Umum'!$J$6:$J$909,0)+5,"") -> 329
A82: {=IF($H82="","",INDEX('Jurnal Umum'!$A$6:$A$2564,$H82-5))} -> 46247 | B82: {=IF($H82="","",IFERROR(INDEX('Jurnal Umum'!$C$6:$C$2564, MATCH(1, ('Jurnal Umum'!$A$6:$A$2564=INDEX('Jurnal Umum'!$A$6:$A$2564,$H82-5)) * ('Jurnal Umum'!$C$6:$C$2564=INDEX('Jurnal Umum'!$C$6:$C$2564,$H82-5)) * ('Jurnal Umum'!$D$6:$D$2564<>$B$5) ,0)),""))} -> Pembelian Bunga di WKF | C82: {=IF($H82="","",INDEX('Jurnal Umum'!$B$6:$B$2564,$H82-5))} | D82: {=IF($H82="","",IF(INDEX('Jurnal Umum'!$F$6:$F$2564,$H82-5)="",0,INDEX('Jurnal Umum'!$F$6:$F$2564,$H82-5)))} -> 0 | E82: {=IF($H82="","",IF(INDEX('Jurnal Umum'!$G$6:$G$2564,$H82-5)="",0,INDEX('Jurnal Umum'!$G$6:$G$2564,$H82-5)))} -> 700000 | F82: =IF($H82="","",IF($B$6="Debit",SUM($D$9:D82)-SUM($E$9:E82),SUM($E$9:E82)-SUM($D$9:D82))) -> 20782455 | H82: =IFERROR(MATCH($B$5&"-"&74,'Jurnal Umum'!$J$6:$J$909,0)+5,"") -> 331
A83: {=IF($H83="","",INDEX('Jurnal Umum'!$A$6:$A$2564,$H83-5))} -> 46247 | B83: {=IF($H83="","",IFERROR(INDEX('Jurnal Umum'!$C$6:$C$2564, MATCH(1, ('Jurnal Umum'!$A$6:$A$2564=INDEX('Jurnal Umum'!$A$6:$A$2564,$H83-5)) * ('Jurnal Umum'!$C$6:$C$2564=INDEX('Jurnal Umum'!$C$6:$C$2564,$H83-5)) * ('Jurnal Umum'!$D$6:$D$2564<>$B$5) ,0)),""))} -> Tarik Tunai untuk kas operasional | C83: {=IF($H83="","",INDEX('Jurnal Umum'!$B$6:$B$2564,$H83-5))} | D83: {=IF($H83="","",IF(INDEX('Jurnal Umum'!$F$6:$F$2564,$H83-5)="",0,INDEX('Jurnal Umum'!$F$6:$F$2564,$H83-5)))} -> 0 | E83: {=IF($H83="","",IF(INDEX('Jurnal Umum'!$G$6:$G$2564,$H83-5)="",0,INDEX('Jurnal Umum'!$G$6:$G$2564,$H83-5)))} -> 2000000 | F83: =IF($H83="","",IF($B$6="Debit",SUM($D$9:D83)-SUM($E$9:E83),SUM($E$9:E83)-SUM($D$9:D83))) -> 18782455 | H83: =IFERROR(MATCH($B$5&"-"&75,'Jurnal Umum'!$J$6:$J$909,0)+5,"") -> 335
A84: {=IF($H84="","",INDEX('Jurnal Umum'!$A$6:$A$2564,$H84-5))} -> 46247 | B84: {=IF($H84="","",IFERROR(INDEX('Jurnal Umum'!$C$6:$C$2564, MATCH(1, ('Jurnal Umum'!$A$6:$A$2564=INDEX('Jurnal Umum'!$A$6:$A$2564,$H84-5)) * ('Jurnal Umum'!$C$6:$C$2564=INDEX('Jurnal Umum'!$C$6:$C$2564,$H84-5)) * ('Jurnal Umum'!$D$6:$D$2564<>$B$5) ,0)),""))} -> Talangan Ongkir Mas Pradan - Ojek | C84: {=IF($H84="","",INDEX('Jurnal Umum'!$B$6:$B$2564,$H84-5))} | D84: {=IF($H84="","",IF(INDEX('Jurnal Umum'!$F$6:$F$2564,$H84-5)="",0,INDEX('Jurnal Umum'!$F$6:$F$2564,$H84-5)))} -> 0 | E84: {=IF($H84="","",IF(INDEX('Jurnal Umum'!$G$6:$G$2564,$H84-5)="",0,INDEX('Jurnal Umum'!$G$6:$G$2564,$H84-5)))} -> 60000 | F84: =IF($H84="","",IF($B$6="Debit",SUM($D$9:D84)-SUM($E$9:E84),SUM($E$9:E84)-SUM($D$9:D84))) -> 18722455 | H84: =IFERROR(MATCH($B$5&"-"&76,'Jurnal Umum'!$J$6:$J$909,0)+5,"") -> 341
A85: {=IF($H85="","",INDEX('Jurnal Umum'!$A$6:$A$2564,$H85-5))} -> 46247 | B85: {=IF($H85="","",IFERROR(INDEX('Jurnal Umum'!$C$6:$C$2564, MATCH(1, ('Jurnal Umum'!$A$6:$A$2564=INDEX('Jurnal Umum'!$A$6:$A$2564,$H85-5)) * ('Jurnal Umum'!$C$6:$C$2564=INDEX('Jurnal Umum'!$C$6:$C$2564,$H85-5)) * ('Jurnal Umum'!$D$6:$D$2564<>$B$5) ,0)),""))} -> Penjualan Bunga ke Vendor - Mba CIput | C85: {=IF($H85="","",INDEX('Jurnal Umum'!$B$6:$B$2564,$H85-5))} -> PV-011 | D85: {=IF($H85="","",IF(INDEX('Jurnal Umum'!$F$6:$F$2564,$H85-5)="",0,INDEX('Jurnal Umum'!$F$6:$F$2564,$H85-5)))} -> 50000 | E85: {=IF($H85="","",IF(INDEX('Jurnal Umum'!$G$6:$G$2564,$H85-5)="",0,INDEX('Jurnal Umum'!$G$6:$G$2564,$H85-5)))} -> 0 | F85: =IF($H85="","",IF($B$6="Debit",SUM($D$9:D85)-SUM($E$9:E85),SUM($E$9:E85)-SUM($D$9:D85))) -> 18772455 | H85: =IFERROR(MATCH($B$5&"-"&77,'Jurnal Umum'!$J$6:$J$909,0)+5,"") -> 350
A86: {=IF($H86="","",INDEX('Jurnal Umum'!$A$6:$A$2564,$H86-5))} -> 46247 | B86: {=IF($H86="","",IFERROR(INDEX('Jurnal Umum'!$C$6:$C$2564, MATCH(1, ('Jurnal Umum'!$A$6:$A$2564=INDEX('Jurnal Umum'!$A$6:$A$2564,$H86-5)) * ('Jurnal Umum'!$C$6:$C$2564=INDEX('Jurnal Umum'!$C$6:$C$2564,$H86-5)) * ('Jurnal Umum'!$D$6:$D$2564<>$B$5) ,0)),""))} -> Pengembalian talangan Ongkir DMK Cargo tgl 12 | C86: {=IF($H86="","",INDEX('Jurnal Umum'!$B$6:$B$2564,$H86-5))} | D86: {=IF($H86="","",IF(INDEX('Jurnal Umum'!$F$6:$F$2564,$H86-5)="",0,INDEX('Jurnal Umum'!$F$6:$F$2564,$H86-5)))} -> 1561995 | E86: {=IF($H86="","",IF(INDEX('Jurnal Umum'!$G$6:$G$2564,$H86-5)="",0,INDEX('Jurnal Umum'!$G$6:$G$2564,$H86-5)))} -> 0 | F86: =IF($H86="","",IF($B$6="Debit",SUM($D$9:D86)-SUM($E$9:E86),SUM($E$9:E86)-SUM($D$9:D86))) -> 20334450 | H86: =IFERROR(MATCH($B$5&"-"&78,'Jurnal Umum'!$J$6:$J$909,0)+5,"") -> 352
A87: {=IF($H87="","",INDEX('Jurnal Umum'!$A$6:$A$2564,$H87-5))} -> 46247 | B87: {=IF($H87="","",IFERROR(INDEX('Jurnal Umum'!$C$6:$C$2564, MATCH(1, ('Jurnal Umum'!$A$6:$A$2564=INDEX('Jurnal Umum'!$A$6:$A$2564,$H87-5)) * ('Jurnal Umum'!$C$6:$C$2564=INDEX('Jurnal Umum'!$C$6:$C$2564,$H87-5)) * ('Jurnal Umum'!$D$6:$D$2564<>$B$5) ,0)),""))} -> Pembayaran Penjualan tgl 12 | C87: {=IF($H87="","",INDEX('Jurnal Umum'!$B$6:$B$2564,$H87-5))} | D87: {=IF($H87="","",IF(INDEX('Jurnal Umum'!$F$6:$F$2564,$H87-5)="",0,INDEX('Jurnal Umum'!$F$6:$F$2564,$H87-5)))} -> 2222500 | E87: {=IF($H87="","",IF(INDEX('Jurnal Umum'!$G$6:$G$2564,$H87-5)="",0,INDEX('Jurnal Umum'!$G$6:$G$2564,$H87-5)))} -> 0 | F87: =IF($H87="","",IF($B$6="Debit",SUM($D$9:D87)-SUM($E$9:E87),SUM($E$9:E87)-SUM($D$9:D87))) -> 22556950 | H87: =IFERROR(MATCH($B$5&"-"&79,'Jurnal Umum'!$J$6:$J$909,0)+5,"") -> 354
A88: {=IF($H88="","",INDEX('Jurnal Umum'!$A$6:$A$2564,$H88-5))} -> 46248 | B88: {=IF($H88="","",IFERROR(INDEX('Jurnal Umum'!$C$6:$C$2564, MATCH(1, ('Jurnal Umum'!$A$6:$A$2564=INDEX('Jurnal Umum'!$A$6:$A$2564,$H88-5)) * ('Jurnal Umum'!$C$6:$C$2564=INDEX('Jurnal Umum'!$C$6:$C$2564,$H88-5)) * ('Jurnal Umum'!$D$6:$D$2564<>$B$5) ,0)),""))} -> Pembelian Bunga di Freesia | C88: {=IF($H88="","",INDEX('Jurnal Umum'!$B$6:$B$2564,$H88-5))} -> BK-260814-001 | D88: {=IF($H88="","",IF(INDEX('Jurnal Umum'!$F$6:$F$2564,$H88-5)="",0,INDEX('Jurnal Umum'!$F$6:$F$2564,$H88-5)))} -> 0 | E88: {=IF($H88="","",IF(INDEX('Jurnal Umum'!$G$6:$G$2564,$H88-5)="",0,INDEX('Jurnal Umum'!$G$6:$G$2564,$H88-5)))} -> 440000 | F88: =IF($H88="","",IF($B$6="Debit",SUM($D$9:D88)-SUM($E$9:E88),SUM($E$9:E88)-SUM($D$9:D88))) -> 22116950 | H88: =IFERROR(MATCH($B$5&"-"&80,'Jurnal Umum'!$J$6:$J$909,0)+5,"") -> 359
A89: {=IF($H89="","",INDEX('Jurnal Umum'!$A$6:$A$2564,$H89-5))} -> 46248 | B89: {=IF($H89="","",IFERROR(INDEX('Jurnal Umum'!$C$6:$C$2564, MATCH(1, ('Jurnal Umum'!$A$6:$A$2564=INDEX('Jurnal Umum'!$A$6:$A$2564,$H89-5)) * ('Jurnal Umum'!$C$6:$C$2564=INDEX('Jurnal Umum'!$C$6:$C$2564,$H89-5)) * ('Jurnal Umum'!$D$6:$D$2564<>$B$5) ,0)),""))} -> Pembayaran penjualan tanggal 13 | C89: {=IF($H89="","",INDEX('Jurnal Umum'!$B$6:$B$2564,$H89-5))} | D89: {=IF($H89="","",IF(INDEX('Jurnal Umum'!$F$6:$F$2564,$H89-5)="",0,INDEX('Jurnal Umum'!$F$6:$F$2564,$H89-5)))} -> 550000 | E89: {=IF($H89="","",IF(INDEX('Jurnal Umum'!$G$6:$G$2564,$H89-5)="",0,INDEX('Jurnal Umum'!$G$6:$G$2564,$H89-5)))} -> 0 | F89: =IF($H89="","",IF($B$6="Debit",SUM($D$9:D89)-SUM($E$9:E89),SUM($E$9:E89)-SUM($D$9:D89))) -> 22666950 | H89: =IFERROR(MATCH($B$5&"-"&81,'Jurnal Umum'!$J$6:$J$909,0)+5,"") -> 386
A90: {=IF($H90="","",INDEX('Jurnal Umum'!$A$6:$A$2564,$H90-5))} -> 46248 | B90: {=IF($H90="","",IFERROR(INDEX('Jurnal Umum'!$C$6:$C$2564, MATCH(1, ('Jurnal Umum'!$A$6:$A$2564=INDEX('Jurnal Umum'!$A$6:$A$2564,$H90-5)) * ('Jurnal Umum'!$C$6:$C$2564=INDEX('Jurnal Umum'!$C$6:$C$2564,$H90-5)) * ('Jurnal Umum'!$D$6:$D$2564<>$B$5) ,0)),""))} -> Pengembalian talangan ongkir tanggal 13 | C90: {=IF($H90="","",INDEX('Jurnal Umum'!$B$6:$B$2564,$H90-5))} | D90: {=IF($H90="","",IF(INDEX('Jurnal Umum'!$F$6:$F$2564,$H90-5)="",0,INDEX('Jurnal Umum'!$F$6:$F$2564,$H90-5)))} -> 130000 | E90: {=IF($H90="","",IF(INDEX('Jurnal Umum'!$G$6:$G$2564,$H90-5)="",0,INDEX('Jurnal Umum'!$G$6:$G$2564,$H90-5)))} -> 0 | F90: =IF($H90="","",IF($B$6="Debit",SUM($D$9:D90)-SUM($E$9:E90),SUM($E$9:E90)-SUM($D$9:D90))) -> 22796950 | H90: =IFERROR(MATCH($B$5&"-"&82,'Jurnal Umum'!$J$6:$J$909,0)+5,"") -> 388
A91: {=IF($H91="","",INDEX('Jurnal Umum'!$A$6:$A$2564,$H91-5))} -> 46249 | B91: {=IF($H91="","",IFERROR(INDEX('Jurnal Umum'!$C$6:$C$2564, MATCH(1, ('Jurnal Umum'!$A$6:$A$2564=INDEX('Jurnal Umum'!$A$6:$A$2564,$H91-5)) * ('Jurnal Umum'!$C$6:$C$2564=INDEX('Jurnal Umum'!$C$6:$C$2564,$H91-5)) * ('Jurnal Umum'!$D$6:$D$2564<>$B$5) ,0)),""))} -> Talangan ongkir DMK Cargo tanggal 14 | C91: {=IF($H91="","",INDEX('Jurnal Umum'!$B$6:$B$2564,$H91-5))} | D91: {=IF($H91="","",IF(INDEX('Jurnal Umum'!$F$6:$F$2564,$H91-5)="",0,INDEX('Jurnal Umum'!$F$6:$F$2564,$H91-5)))} -> 0 | E91: {=IF($H91="","",IF(INDEX('Jurnal Umum'!$G$6:$G$2564,$H91-5)="",0,INDEX('Jurnal Umum'!$G$6:$G$2564,$H91-5)))} -> 4323659 | F91: =IF($H91="","",IF($B$6="Debit",SUM($D$9:D91)-SUM($E$9:E91),SUM($E$9:E91)-SUM($D$9:D91))) -> 18473291 | H91: =IFERROR(MATCH($B$5&"-"&83,'Jurnal Umum'!$J$6:$J$909,0)+5,"") -> 391
A92: {=IF($H92="","",INDEX('Jurnal Umum'!$A$6:$A$2564,$H92-5))} -> 46249 | B92: {=IF($H92="","",IFERROR(INDEX('Jurnal Umum'!$C$6:$C$2564, MATCH(1, ('Jurnal Umum'!$A$6:$A$2564=INDEX('Jurnal Umum'!$A$6:$A$2564,$H92-5)) * ('Jurnal Umum'!$C$6:$C$2564=INDEX('Jurnal Umum'!$C$6:$C$2564,$H92-5)) * ('Jurnal Umum'!$D$6:$D$2564<>$B$5) ,0)),""))} -> Pengembalian talangan ongkir DMK Cargo tgl 14 | C92: {=IF($H92="","",INDEX('Jurnal Umum'!$B$6:$B$2564,$H92-5))} | D92: {=IF($H92="","",IF(INDEX('Jurnal Umum'!$F$6:$F$2564,$H92-5)="",0,INDEX('Jurnal Umum'!$F$6:$F$2564,$H92-5)))} -> 4323659 | E92: {=IF($H92="","",IF(INDEX('Jurnal Umum'!$G$6:$G$2564,$H92-5)="",0,INDEX('Jurnal Umum'!$G$6:$G$2564,$H92-5)))} -> 0 | F92: =IF($H92="","",IF($B$6="Debit",SUM($D$9:D92)-SUM($E$9:E92),SUM($E$9:E92)-SUM($D$9:D92))) -> 22796950 | H92: =IFERROR(MATCH($B$5&"-"&84,'Jurnal Umum'!$J$6:$J$909,0)+5,"") -> 392
A93: {=IF($H93="","",INDEX('Jurnal Umum'!$A$6:$A$2564,$H93-5))} -> 46249 | B93: {=IF($H93="","",IFERROR(INDEX('Jurnal Umum'!$C$6:$C$2564, MATCH(1, ('Jurnal Umum'!$A$6:$A$2564=INDEX('Jurnal Umum'!$A$6:$A$2564,$H93-5)) * ('Jurnal Umum'!$C$6:$C$2564=INDEX('Jurnal Umum'!$C$6:$C$2564,$H93-5)) * ('Jurnal Umum'!$D$6:$D$2564<>$B$5) ,0)),""))} -> Pembayaran penjualan tanggal 14 | C93: {=IF($H93="","",INDEX('Jurnal Umum'!$B$6:$B$2564,$H93-5))} | D93: {=IF($H93="","",IF(INDEX('Jurnal Umum'!$F$6:$F$2564,$H93-5)="",0,INDEX('Jurnal Umum'!$F$6:$F$2564,$H93-5)))} -> 5813000 | E93: {=IF($H93="","",IF(INDEX('Jurnal Umum'!$G$6:$G$2564,$H93-5)="",0,INDEX('Jurnal Umum'!$G$6:$G$2564,$H93-5)))} -> 0 | F93: =IF($H93="","",IF($B$6="Debit",SUM($D$9:D93)-SUM($E$9:E93),SUM($E$9:E93)-SUM($D$9:D93))) -> 28609950 | H93: =IFERROR(MATCH($B$5&"-"&85,'Jurnal Umum'!$J$6:$J$909,0)+5,"") -> 394
A94: {=IF($H94="","",INDEX('Jurnal Umum'!$A$6:$A$2564,$H94-5))} -> 46251 | B94: {=IF($H94="","",IFERROR(INDEX('Jurnal Umum'!$C$6:$C$2564, MATCH(1, ('Jurnal Umum'!$A$6:$A$2564=INDEX('Jurnal Umum'!$A$6:$A$2564,$H94-5)) * ('Jurnal Umum'!$C$6:$C$2564=INDEX('Jurnal Umum'!$C$6:$C$2564,$H94-5)) * ('Jurnal Umum'!$D$6:$D$2564<>$B$5) ,0)),""))} -> Tarik Tunai untuk kas operasional | C94: {=IF($H94="","",INDEX('Jurnal Umum'!$B$6:$B$2564,$H94-5))} | D94: {=IF($H94="","",IF(INDEX('Jurnal Umum'!$F$6:$F$2564,$H94-5)="",0,INDEX('Jurnal Umum'!$F$6:$F$2564,$H94-5)))} -> 0 | E94: {=IF($H94="","",IF(INDEX('Jurnal Umum'!$G$6:$G$2564,$H94-5)="",0,INDEX('Jurnal Umum'!$G$6:$G$2564,$H94-5)))} -> 189000 | F94: =IF($H94="","",IF($B$6="Debit",SUM($D$9:D94)-SUM($E$9:E94),SUM($E$9:E94)-SUM($D$9:D94))) -> 28420950 | H94: =IFERROR(MATCH($B$5&"-"&86,'Jurnal Umum'!$J$6:$J$909,0)+5,"") -> 399
A95: {=IF($H95="","",INDEX('Jurnal Umum'!$A$6:$A$2564,$H95-5))} -> 46251 | B95: {=IF($H95="","",IFERROR(INDEX('Jurnal Umum'!$C$6:$C$2564, MATCH(1, ('Jurnal Umum'!$A$6:$A$2564=INDEX('Jurnal Umum'!$A$6:$A$2564,$H95-5)) * ('Jurnal Umum'!$C$6:$C$2564=INDEX('Jurnal Umum'!$C$6:$C$2564,$H95-5)) * ('Jurnal Umum'!$D$6:$D$2564<>$B$5) ,0)),""))} -> Pembelian bunga di vendor - Mba Ciput | C95: {=IF($H95="","",INDEX('Jurnal Umum'!$B$6:$B$2564,$H95-5))} | D95: {=IF($H95="","",IF(INDEX('Jurnal Umum'!$F$6:$F$2564,$H95-5)="",0,INDEX('Jurnal Umum'!$F$6:$F$2564,$H95-5)))} -> 0 | E95: {=IF($H95="","",IF(INDEX('Jurnal Umum'!$G$6:$G$2564,$H95-5)="",0,INDEX('Jurnal Umum'!$G$6:$G$2564,$H95-5)))} -> 226000 | F95: =IF($H95="","",IF($B$6="Debit",SUM($D$9:D95)-SUM($E$9:E95),SUM($E$9:E95)-SUM($D$9:D95))) -> 28194950 | H95: =IFERROR(MATCH($B$5&"-"&87,'Jurnal Umum'!$J$6:$J$909,0)+5,"") -> 411
A96: {=IF($H96="","",INDEX('Jurnal Umum'!$A$6:$A$2564,$H96-5))} -> 46251 | B96: {=IF($H96="","",IFERROR(INDEX('Jurnal Umum'!$C$6:$C$2564, MATCH(1, ('Jurnal Umum'!$A$6:$A$2564=INDEX('Jurnal Umum'!$A$6:$A$2564,$H96-5)) * ('Jurnal Umum'!$C$6:$C$2564=INDEX('Jurnal Umum'!$C$6:$C$2564,$H96-5)) * ('Jurnal Umum'!$D$6:$D$2564<>$B$5) ,0)),""))} -> Pembelian Bunga di Bunga Bromo - Pembayaran tgl 10 | C96: {=IF($H96="","",INDEX('Jurnal Umum'!$B$6:$B$2564,$H96-5))} | D96: {=IF($H96="","",IF(INDEX('Jurnal Umum'!$F$6:$F$2564,$H96-5)="",0,INDEX('Jurnal Umum'!$F$6:$F$2564,$H96-5)))} -> 0 | E96: {=IF($H96="","",IF(INDEX('Jurnal Umum'!$G$6:$G$2564,$H96-5)="",0,INDEX('Jurnal Umum'!$G$6:$G$2564,$H96-5)))} -> 1290000 | F96: =IF($H96="","",IF($B$6="Debit",SUM($D$9:D96)-SUM($E$9:E96),SUM($E$9:E96)-SUM($D$9:D96))) -> 26904950 | H96: =IFERROR(MATCH($B$5&"-"&88,'Jurnal Umum'!$J$6:$J$909,0)+5,"") -> 413
A97: {=IF($H97="","",INDEX('Jurnal Umum'!$A$6:$A$2564,$H97-5))} -> 46251 | B97: {=IF($H97="","",IFERROR(INDEX('Jurnal Umum'!$C$6:$C$2564, MATCH(1, ('Jurnal Umum'!$A$6:$A$2564=INDEX('Jurnal Umum'!$A$6:$A$2564,$H97-5)) * ('Jurnal Umum'!$C$6:$C$2564=INDEX('Jurnal Umum'!$C$6:$C$2564,$H97-5)) * ('Jurnal Umum'!$D$6:$D$2564<>$B$5) ,0)),""))} -> Pembelian Bunga di Vendor - Mba Yeti | C97: {=IF($H97="","",INDEX('Jurnal Umum'!$B$6:$B$2564,$H97-5))} | D97: {=IF($H97="","",IF(INDEX('Jurnal Umum'!$F$6:$F$2564,$H97-5)="",0,INDEX('Jurnal Umum'!$F$6:$F$2564,$H97-5)))} -> 0 | E97: {=IF($H97="","",IF(INDEX('Jurnal Umum'!$G$6:$G$2564,$H97-5)="",0,INDEX('Jurnal Umum'!$G$6:$G$2564,$H97-5)))} -> 791000 | F97: =IF($H97="","",IF($B$6="Debit",SUM($D$9:D97)-SUM($E$9:E97),SUM($E$9:E97)-SUM($D$9:D97))) -> 26113950 | H97: =IFERROR(MATCH($B$5&"-"&89,'Jurnal Umum'!$J$6:$J$909,0)+5,"") -> 415
A98: {=IF($H98="","",INDEX('Jurnal Umum'!$A$6:$A$2564,$H98-5))} -> 46251 | B98: {=IF($H98="","",IFERROR(INDEX('Jurnal Umum'!$C$6:$C$2564, MATCH(1, ('Jurnal Umum'!$A$6:$A$2564=INDEX('Jurnal Umum'!$A$6:$A$2564,$H98-5)) * ('Jurnal Umum'!$C$6:$C$2564=INDEX('Jurnal Umum'!$C$6:$C$2564,$H98-5)) * ('Jurnal Umum'!$D$6:$D$2564<>$B$5) ,0)),""))} -> Pembayaran Gaji Mas Sandi | C98: {=IF($H98="","",INDEX('Jurnal Umum'!$B$6:$B$2564,$H98-5))} | D98: {=IF($H98="","",IF(INDEX('Jurnal Umum'!$F$6:$F$2564,$H98-5)="",0,INDEX('Jurnal Umum'!$F$6:$F$2564,$H98-5)))} -> 0 | E98: {=IF($H98="","",IF(INDEX('Jurnal Umum'!$G$6:$G$2564,$H98-5)="",0,INDEX('Jurnal Umum'!$G$6:$G$2564,$H98-5)))} -> 500000 | F98: =IF($H98="","",IF($B$6="Debit",SUM($D$9:D98)-SUM($E$9:E98),SUM($E$9:E98)-SUM($D$9:D98))) -> 25613950 | H98: =IFERROR(MATCH($B$5&"-"&90,'Jurnal Umum'!$J$6:$J$909,0)+5,"") -> 417
A99: {=IF($H99="","",INDEX('Jurnal Umum'!$A$6:$A$2564,$H99-5))} -> 46252 | B99: {=IF($H99="","",IFERROR(INDEX('Jurnal Umum'!$C$6:$C$2564, MATCH(1, ('Jurnal Umum'!$A$6:$A$2564=INDEX('Jurnal Umum'!$A$6:$A$2564,$H99-5)) * ('Jurnal Umum'!$C$6:$C$2564=INDEX('Jurnal Umum'!$C$6:$C$2564,$H99-5)) * ('Jurnal Umum'!$D$6:$D$2564<>$B$5) ,0)),""))} -> Tarik Tunai untuk kas operasional | C99: {=IF($H99="","",INDEX('Jurnal Umum'!$B$6:$B$2564,$H99-5))} | D99: {=IF($H99="","",IF(INDEX('Jurnal Umum'!$F$6:$F$2564,$H99-5)="",0,INDEX('Jurnal Umum'!$F$6:$F$2564,$H99-5)))} -> 0 | E99: {=IF($H99="","",IF(INDEX('Jurnal Umum'!$G$6:$G$2564,$H99-5)="",0,INDEX('Jurnal Umum'!$G$6:$G$2564,$H99-5)))} -> 500000 | F99: =IF($H99="","",IF($B$6="Debit",SUM($D$9:D99)-SUM($E$9:E99),SUM($E$9:E99)-SUM($D$9:D99))) -> 25113950 | H99: =IFERROR(MATCH($B$5&"-"&91,'Jurnal Umum'!$J$6:$J$909,0)+5,"") -> 423
A100: {=IF($H100="","",INDEX('Jurnal Umum'!$A$6:$A$2564,$H100-5))} -> 46252 | B100: {=IF($H100="","",IFERROR(INDEX('Jurnal Umum'!$C$6:$C$2564, MATCH(1, ('Jurnal Umum'!$A$6:$A$2564=INDEX('Jurnal Umum'!$A$6:$A$2564,$H100-5)) * ('Jurnal Umum'!$C$6:$C$2564=INDEX('Jurnal Umum'!$C$6:$C$2564,$H100-5)) * ('Jurnal Umum'!$D$6:$D$2564<>$B$5) ,0)),""))} -> Pembelian Bunga di WKF | C100: {=IF($H100="","",INDEX('Jurnal Umum'!$B$6:$B$2564,$H100-5))} -> BK-260818-001 | D100: {=IF($H100="","",IF(INDEX('Jurnal Umum'!$F$6:$F$2564,$H100-5)="",0,INDEX('Jurnal Umum'!$F$6:$F$2564,$H100-5)))} -> 0 | E100: {=IF($H100="","",IF(INDEX('Jurnal Umum'!$G$6:$G$2564,$H100-5)="",0,INDEX('Jurnal Umum'!$G$6:$G$2564,$H100-5)))} -> 165000 | F100: =IF($H100="","",IF($B$6="Debit",SUM($D$9:D100)-SUM($E$9:E100),SUM($E$9:E100)-SUM($D$9:D100))) -> 24948950 | H100: =IFERROR(MATCH($B$5&"-"&92,'Jurnal Umum'!$J$6:$J$909,0)+5,"") -> 437
A101: {=IF($H101="","",INDEX('Jurnal Umum'!$A$6:$A$2564,$H101-5))} -> 46252 | B101: {=IF($H101="","",IFERROR(INDEX('Jurnal Umum'!$C$6:$C$2564, MATCH(1, ('Jurnal Umum'!$A$6:$A$2564=INDEX('Jurnal Umum'!$A$6:$A$2564,$H101-5)) * ('Jurnal Umum'!$C$6:$C$2564=INDEX('Jurnal Umum'!$C$6:$C$2564,$H101-5)) * ('Jurnal Umum'!$D$6:$D$2564<>$B$5) ,0)),""))} -> Tambahan talangan ongkir DMK Cargo tgl 17 | C101: {=IF($H101="","",INDEX('Jurnal Umum'!$B$6:$B$2564,$H101-5))} | D101: {=IF($H101="","",IF(INDEX('Jurnal Umum'!$F$6:$F$2564,$H101-5)="",0,INDEX('Jurnal Umum'!$F$6:$F$2564,$H101-5)))} -> 0 | E101: {=IF($H101="","",IF(INDEX('Jurnal Umum'!$G$6:$G$2564,$H101-5)="",0,INDEX('Jurnal Umum'!$G$6:$G$2564,$H101-5)))} -> 596490 | F101: =IF($H101="","",IF($B$6="Debit",SUM($D$9:D101)-SUM($E$9:E101),SUM($E$9:E101)-SUM($D$9:D101))) -> 24352460 | H101: =IFERROR(MATCH($B$5&"-"&93,'Jurnal Umum'!$J$6:$J$909,0)+5,"") -> 445
A102: {=IF($H102="","",INDEX('Jurnal Umum'!$A$6:$A$2564,$H102-5))} -> 46252 | B102: {=IF($H102="","",IFERROR(INDEX('Jurnal Umum'!$C$6:$C$2564, MATCH(1, ('Jurnal Umum'!$A$6:$A$2564=INDEX('Jurnal Umum'!$A$6:$A$2564,$H102-5)) * ('Jurnal Umum'!$C$6:$C$2564=INDEX('Jurnal Umum'!$C$6:$C$2564,$H102-5)) * ('Jurnal Umum'!$D$6:$D$2564<>$B$5) ,0)),""))} -> Pembelian Bunga di Vendor - Mba Yeti | C102: {=IF($H102="","",INDEX('Jurnal Umum'!$B$6:$B$2564,$H102-5))} | D102: {=IF($H102="","",IF(INDEX('Jurnal Umum'!$F$6:$F$2564,$H102-5)="",0,INDEX('Jurnal Umum'!$F$6:$F$2564,$H102-5)))} -> 0 | E102: {=IF($H102="","",IF(INDEX('Jurnal Umum'!$G$6:$G$2564,$H102-5)="",0,INDEX('Jurnal Umum'!$G$6:$G$2564,$H102-5)))} -> 105000 | F102: =IF($H102="","",IF($B$6="Debit",SUM($D$9:D102)-SUM($E$9:E102),SUM($E$9:E102)-SUM($D$9:D102))) -> 24247460 | H102: =IFERROR(MATCH($B$5&"-"&94,'Jurnal Umum'!$J$6:$J$909,0)+5,"") -> 447
...

Sheet Neraca Saldo
A1: PT BIGATRI INDOFLORAPACIFIC
A2: BLOOMORIST
A3: NERACA SALDO (TRIAL BALANCE) — Periode Agustus 2026
A5: Kode Akun | B5: Nama Akun | C5: Debit (Rp) | D5: Kredit (Rp)
A6: 1101 | B6: Kas | C6: =MAX(0,SUMIFS('Jurnal Umum'!$F$6:$F$909,'Jurnal Umum'!$D$6:$D$909,A6)-SUMIFS('Jurnal Umum'!$G$6:$G$909,'Jurnal Umum'!$D$6:$D$909,A6)) -> 2190500 | D6: =MAX(0,SUMIFS('Jurnal Umum'!$G$6:$G$909,'Jurnal Umum'!$D$6:$D$909,A6)-SUMIFS('Jurnal Umum'!$F$6:$F$909,'Jurnal Umum'!$D$6:$D$909,A6)) -> 0
A7: 1102 | B7: Bank | C7: =MAX(0,SUMIFS('Jurnal Umum'!$F$6:$F$909,'Jurnal Umum'!$D$6:$D$909,A7)-SUMIFS('Jurnal Umum'!$G$6:$G$909,'Jurnal Umum'!$D$6:$D$909,A7)) -> 13450950 | D7: =MAX(0,SUMIFS('Jurnal Umum'!$G$6:$G$909,'Jurnal Umum'!$D$6:$D$909,A7)-SUMIFS('Jurnal Umum'!$F$6:$F$909,'Jurnal Umum'!$D$6:$D$909,A7)) -> 0
A8: 1103 | B8: Piutang Dagang | C8: =MAX(0,SUMIFS('Jurnal Umum'!$F$6:$F$909,'Jurnal Umum'!$D$6:$D$909,A8)-SUMIFS('Jurnal Umum'!$G$6:$G$909,'Jurnal Umum'!$D$6:$D$909,A8)) -> 35000 | D8: =MAX(0,SUMIFS('Jurnal Umum'!$G$6:$G$909,'Jurnal Umum'!$D$6:$D$909,A8)-SUMIFS('Jurnal Umum'!$F$6:$F$909,'Jurnal Umum'!$D$6:$D$909,A8)) -> 0
A9: 1105 | B9: Peralatan | C9: =MAX(0,SUMIFS('Jurnal Umum'!$F$6:$F$909,'Jurnal Umum'!$D$6:$D$909,A9)-SUMIFS('Jurnal Umum'!$G$6:$G$909,'Jurnal Umum'!$D$6:$D$909,A9)) -> 9500 | D9: =MAX(0,SUMIFS('Jurnal Umum'!$G$6:$G$909,'Jurnal Umum'!$D$6:$D$909,A9)-SUMIFS('Jurnal Umum'!$F$6:$F$909,'Jurnal Umum'!$D$6:$D$909,A9)) -> 0
A10: 1106 | B10: Akumulasi Penyusutan Peralatan | C10: =MAX(0,SUMIFS('Jurnal Umum'!$F$6:$F$909,'Jurnal Umum'!$D$6:$D$909,A10)-SUMIFS('Jurnal Umum'!$G$6:$G$909,'Jurnal Umum'!$D$6:$D$909,A10)) -> 0 | D10: =MAX(0,SUMIFS('Jurnal Umum'!$G$6:$G$909,'Jurnal Umum'!$D$6:$D$909,A10)-SUMIFS('Jurnal Umum'!$F$6:$F$909,'Jurnal Umum'!$D$6:$D$909,A10)) -> 2911611
A11: 1107 | B11: Piutang Ongkir | C11: =MAX(0,SUMIFS('Jurnal Umum'!$F$6:$F$909,'Jurnal Umum'!$D$6:$D$909,A11)-SUMIFS('Jurnal Umum'!$G$6:$G$909,'Jurnal Umum'!$D$6:$D$909,A11)) -> 0 | D11: =MAX(0,SUMIFS('Jurnal Umum'!$G$6:$G$909,'Jurnal Umum'!$D$6:$D$909,A11)-SUMIFS('Jurnal Umum'!$F$6:$F$909,'Jurnal Umum'!$D$6:$D$909,A11)) -> 0
A12: 2101 | B12: Utang Dagang | C12: =MAX(0,SUMIFS('Jurnal Umum'!$F$6:$F$909,'Jurnal Umum'!$D$6:$D$909,A12)-SUMIFS('Jurnal Umum'!$G$6:$G$909,'Jurnal Umum'!$D$6:$D$909,A12)) -> 0 | D12: =MAX(0,SUMIFS('Jurnal Umum'!$G$6:$G$909,'Jurnal Umum'!$D$6:$D$909,A12)-SUMIFS('Jurnal Umum'!$F$6:$F$909,'Jurnal Umum'!$D$6:$D$909,A12)) -> 0
A13: 3101 | B13: Modal Pemilik | C13: =MAX(0,SUMIFS('Jurnal Umum'!$F$6:$F$909,'Jurnal Umum'!$D$6:$D$909,A13)-SUMIFS('Jurnal Umum'!$G$6:$G$909,'Jurnal Umum'!$D$6:$D$909,A13)) -> 0 | D13: =MAX(0,SUMIFS('Jurnal Umum'!$G$6:$G$909,'Jurnal Umum'!$D$6:$D$909,A13)-SUMIFS('Jurnal Umum'!$F$6:$F$909,'Jurnal Umum'!$D$6:$D$909,A13)) -> 61870000
A14: 3102 | B14: Prive | C14: =MAX(0,SUMIFS('Jurnal Umum'!$F$6:$F$909,'Jurnal Umum'!$D$6:$D$909,A14)-SUMIFS('Jurnal Umum'!$G$6:$G$909,'Jurnal Umum'!$D$6:$D$909,A14)) -> 0 | D14: =MAX(0,SUMIFS('Jurnal Umum'!$G$6:$G$909,'Jurnal Umum'!$D$6:$D$909,A14)-SUMIFS('Jurnal Umum'!$F$6:$F$909,'Jurnal Umum'!$D$6:$D$909,A14)) -> 0
A15: 4101 | B15: Penjualan | C15: =MAX(0,SUMIFS('Jurnal Umum'!$F$6:$F$909,'Jurnal Umum'!$D$6:$D$909,A15)-SUMIFS('Jurnal Umum'!$G$6:$G$909,'Jurnal Umum'!$D$6:$D$909,A15)) -> 0 | D15: =MAX(0,SUMIFS('Jurnal Umum'!$G$6:$G$909,'Jurnal Umum'!$D$6:$D$909,A15)-SUMIFS('Jurnal Umum'!$F$6:$F$909,'Jurnal Umum'!$D$6:$D$909,A15)) -> 55819250
A16: 5101 | B16: Pembelian Bunga | C16: =MAX(0,SUMIFS('Jurnal Umum'!$F$6:$F$909,'Jurnal Umum'!$D$6:$D$909,A16)-SUMIFS('Jurnal Umum'!$G$6:$G$909,'Jurnal Umum'!$D$6:$D$909,A16)) -> 38700000 | D16: =MAX(0,SUMIFS('Jurnal Umum'!$G$6:$G$909,'Jurnal Umum'!$D$6:$D$909,A16)-SUMIFS('Jurnal Umum'!$F$6:$F$909,'Jurnal Umum'!$D$6:$D$909,A16)) -> 0
A17: 5102 | B17: Retur Pembelian | C17: =MAX(0,SUMIFS('Jurnal Umum'!$F$6:$F$909,'Jurnal Umum'!$D$6:$D$909,A17)-SUMIFS('Jurnal Umum'!$G$6:$G$909,'Jurnal Umum'!$D$6:$D$909,A17)) -> 0 | D17: =MAX(0,SUMIFS('Jurnal Umum'!$G$6:$G$909,'Jurnal Umum'!$D$6:$D$909,A17)-SUMIFS('Jurnal Umum'!$F$6:$F$909,'Jurnal Umum'!$D$6:$D$909,A17)) -> 0
... A25: 4102 | B25: Retur Penjualan | C25: =MAX(0,SUMIFS('Jurnal Umum'!$F$6:$F$909,'Jurnal Umum'!$D$6:$D$909,A25)-SUMIFS('Jurnal Umum'!$G$6:$G$909,'Jurnal Umum'!$D$6:$D$909,A25)) -> 0 | D25: =MAX(0,SUMIFS('Jurnal Umum'!$G$6:$G$909,'Jurnal Umum'!$D$6:$D$909,A25)-SUMIFS('Jurnal Umum'!$F$6:$F$909,'Jurnal Umum'!$D$6:$D$909,A25)) -> 0
A26: 1108 | B26: Perlengkapan | C26: =MAX(0,SUMIFS('Jurnal Umum'!$F$6:$F$909,'Jurnal Umum'!$D$6:$D$909,A26)-SUMIFS('Jurnal Umum'!$G$6:$G$909,'Jurnal Umum'!$D$6:$D$909,A26)) -> 351000 | D26: =MAX(0,SUMIFS('Jurnal Umum'!$G$6:$G$909,'Jurnal Umum'!$D$6:$D$909,A26)-SUMIFS('Jurnal Umum'!$F$6:$F$909,'Jurnal Umum'!$D$6:$D$909,A26)) -> 0
A27: 6107 | B27: Beban Perlengkapan | C27: =MAX(0,SUMIFS('Jurnal Umum'!$F$6:$F$909,'Jurnal Umum'!$D$6:$D$909,A27)-SUMIFS('Jurnal Umum'!$G$6:$G$909,'Jurnal Umum'!$D$6:$D$909,A27)) -> 945000 | D27: =MAX(0,SUMIFS('Jurnal Umum'!$G$6:$G$909,'Jurnal Umum'!$D$6:$D$909,A27)-SUMIFS('Jurnal Umum'!$F$6:$F$909,'Jurnal Umum'!$D$6:$D$909,A27)) -> 0
A28: 6108 | B28: Beban Lain-Lain | C28: =MAX(0,SUMIFS('Jurnal Umum'!$F$6:$F$909,'Jurnal Umum'!$D$6:$D$909,A28)-SUMIFS('Jurnal Umum'!$G$6:$G$909,'Jurnal Umum'!$D$6:$D$909,A28)) -> 2659600 | D28: =MAX(0,SUMIFS('Jurnal Umum'!$G$6:$G$909,'Jurnal Umum'!$D$6:$D$909,A28)-SUMIFS('Jurnal Umum'!$F$6:$F$909,'Jurnal Umum'!$D$6:$D$909,A28)) -> 0
A29: 1109 | B29: Piutang Investasi | C29: =MAX(0,SUMIFS('Jurnal Umum'!$F$6:$F$909,'Jurnal Umum'!$D$6:$D$909,A29)-SUMIFS('Jurnal Umum'!$G$6:$G$909,'Jurnal Umum'!$D$6:$D$909,A29)) -> 33060000 | D29: =MAX(0,SUMIFS('Jurnal Umum'!$G$6:$G$909,'Jurnal Umum'!$D$6:$D$909,A29)-SUMIFS('Jurnal Umum'!$F$6:$F$909,'Jurnal Umum'!$D$6:$D$909,A29)) -> 0
A30: 4103 | B30: Pendapatan Bunga | C30: =MAX(0,SUMIFS('Jurnal Umum'!$F$6:$F$909,'Jurnal Umum'!$D$6:$D$909,A30)-SUMIFS('Jurnal Umum'!$G$6:$G$909,'Jurnal Umum'!$D$6:$D$909,A30)) -> 0 | D30: =MAX(0,SUMIFS('Jurnal Umum'!$G$6:$G$909,'Jurnal Umum'!$D$6:$D$909,A30)-SUMIFS('Jurnal Umum'!$F$6:$F$909,'Jurnal Umum'!$D$6:$D$909,A30)) -> 363000
A31: 1110 | B31: Uang Muka Pembelian Petani | C31: =MAX(0,SUMIFS('Jurnal Umum'!$F$6:$F$909,'Jurnal Umum'!$D$6:$D$909,A31)-SUMIFS('Jurnal Umum'!$G$6:$G$909,'Jurnal Umum'!$D$6:$D$909,A31)) -> 9200000 | D31: =MAX(0,SUMIFS('Jurnal Umum'!$G$6:$G$909,'Jurnal Umum'!$D$6:$D$909,A31)-SUMIFS('Jurnal Umum'!$F$6:$F$909,'Jurnal Umum'!$D$6:$D$909,A31)) -> 0
A32: 4104 | B32: Pendapatan Lain-Lain | C32: =MAX(0,SUMIFS('Jurnal Umum'!$F$6:$F$909,'Jurnal Umum'!$D$6:$D$909,A32)-SUMIFS('Jurnal Umum'!$G$6:$G$909,'Jurnal Umum'!$D$6:$D$909,A32)) -> 0 | D32: =MAX(0,SUMIFS('Jurnal Umum'!$G$6:$G$909,'Jurnal Umum'!$D$6:$D$909,A32)-SUMIFS('Jurnal Umum'!$F$6:$F$909,'Jurnal Umum'!$D$6:$D$909,A32)) -> 95000
A33: 6109 | B33: Beban Akomodasi | C33: =MAX(0,SUMIFS('Jurnal Umum'!$F$6:$F$909,'Jurnal Umum'!$D$6:$D$909,A33)-SUMIFS('Jurnal Umum'!$G$6:$G$909,'Jurnal Umum'!$D$6:$D$909,A33)) -> 0 | D33: =MAX(0,SUMIFS('Jurnal Umum'!$G$6:$G$909,'Jurnal Umum'!$D$6:$D$909,A33)-SUMIFS('Jurnal Umum'!$F$6:$F$909,'Jurnal Umum'!$D$6:$D$909,A33)) -> 0
A34: 1111 | B34: Gaji Bayar di Muka | C34: =MAX(0,SUMIFS('Jurnal Umum'!$F$6:$F$909,'Jurnal Umum'!$D$6:$D$909,A34)-SUMIFS('Jurnal Umum'!$G$6:$G$909,'Jurnal Umum'!$D$6:$D$909,A34)) -> 0 | D34: =MAX(0,SUMIFS('Jurnal Umum'!$G$6:$G$909,'Jurnal Umum'!$D$6:$D$909,A34)-SUMIFS('Jurnal Umum'!$F$6:$F$909,'Jurnal Umum'!$D$6:$D$909,A34)) -> 0
A35: 6110 | B35: Beban Pesangon | C35: =MAX(0,SUMIFS('Jurnal Umum'!$F$6:$F$909,'Jurnal Umum'!$D$6:$D$909,A35)-SUMIFS('Jurnal Umum'!$G$6:$G$909,'Jurnal Umum'!$D$6:$D$909,A35)) -> 1000000 | D35: =MAX(0,SUMIFS('Jurnal Umum'!$G$6:$G$909,'Jurnal Umum'!$D$6:$D$909,A35)-SUMIFS('Jurnal Umum'!$F$6:$F$909,'Jurnal Umum'!$D$6:$D$909,A35)) -> 0
A36: 1104 | B36: Persedian Bunga | C36: =MAX(0,SUMIFS('Jurnal Umum'!$F$6:$F$909,'Jurnal Umum'!$D$6:$D$909,A36)-SUMIFS('Jurnal Umum'!$G$6:$G$909,'Jurnal Umum'!$D$6:$D$909,A36)) -> 2534000 | D36: =MAX(0,SUMIFS('Jurnal Umum'!$G$6:$G$909,'Jurnal Umum'!$D$6:$D$909,A36)-SUMIFS('Jurnal Umum'!$F$6:$F$909,'Jurnal Umum'!$D$6:$D$909,A36)) -> 0
A37: 2102 | B37: Uang Muka Penjualan | C37: =MAX(0,SUMIFS('Jurnal Umum'!$F$6:$F$909,'Jurnal Umum'!$D$6:$D$909,A37)-SUMIFS('Jurnal Umum'!$G$6:$G$909,'Jurnal Umum'!$D$6:$D$909,A37)) -> 0 | D37: =MAX(0,SUMIFS('Jurnal Umum'!$G$6:$G$909,'Jurnal Umum'!$D$6:$D$909,A37)-SUMIFS('Jurnal Umum'!$F$6:$F$909,'Jurnal Umum'!$D$6:$D$909,A37)) -> 0
A38: 1112 | B38: Uang Muka Pembelian Tanah | C38: =MAX(0,SUMIFS('Jurnal Umum'!$F$6:$F$909,'Jurnal Umum'!$D$6:$D$909,A38)-SUMIFS('Jurnal Umum'!$G$6:$G$909,'Jurnal Umum'!$D$6:$D$909,A38)) -> 0 | D38: =MAX(0,SUMIFS('Jurnal Umum'!$G$6:$G$909,'Jurnal Umum'!$D$6:$D$909,A38)-SUMIFS('Jurnal Umum'!$F$6:$F$909,'Jurnal Umum'!$D$6:$D$909,A38)) -> 0
B39: TOTAL (akun double-entry dari Jurnal Umum) | C39: =SUM(C6:C36) -> 121058861 | D39: =SUM(D6:D36) -> 121058861
B40: =IF(C39=D39,"Seimbang (Debit = Kredit)","TIDAK SEIMBANG - cek Buku Besar!") -> Seimbang (Debit = Kredit)
A42: 1104 | B42: Persediaan Bunga (Akhir) - Memo, hasil stock opname | C42: 5852000

Sheet Laba Rugi
A1: PT BIGATRI INDOFLORA PACIFIC
A2: BLOOMORIST
A3: LAPORAN LABA RUGI (PERIODIK - PERUSAHAAN DAGANG) Periode Agustus 2026
A5: PENDAPATAN
B6: Penjualan | C6: ='Neraca Saldo'!C15+'Neraca Saldo'!D15 -> 55819250
B7: Retur Penjualan | C7: =-('Neraca Saldo'!C25+'Neraca Saldo'!D25) -> 0
B8: Penjualan Bersih | C8: =C6+C7 -> 55819250
A10: HARGA POKOK PENJUALAN (HPP)
B11: Pembelian Bunga | C11: ='Neraca Saldo'!C16+'Neraca Saldo'!D16 -> 38700000
B12: Retur Pembelian | C12: =-('Neraca Saldo'!C17+'Neraca Saldo'!D17) -> 0
B13: Pembelian Bersih | C13: =C11+C12 -> 38700000
B14: Beban Angkut Pembelian | C14: ='Neraca Saldo'!C18+'Neraca Saldo'!D18 -> 282500
B15: Persediaan Awal | C15: ='Neraca Saldo'!C36+'Neraca Saldo'!D36 -> 2534000
B16: Barang Tersedia Dijual | C16: =C15+C13+C14 -> 41516500
B17: Persediaan Bunga Akhir (hasil stock opname) | C17: =-('Neraca Saldo'!C42+'Neraca Saldo'!D42) -> -5852000
B18: Harga Pokok Penjualan (HPP) | C18: =C16+C17 -> 35664500
A20: LABA KOTOR | C20: =C8-C18 -> 20154750
A22: BEBAN OPERASIONAL
B23: Beban Gaji | C23: ='Neraca Saldo'!C19+'Neraca Saldo'!D19 -> 11936200
B24: Beban Sewa | C24: ='Neraca Saldo'!C20+'Neraca Saldo'!D20 -> 0
B25: Beban Utilitas | C25: ='Neraca Saldo'!C21+'Neraca Saldo'!D21 -> 678000
B26: Beban Angkut Penjualan | C26: ='Neraca Saldo'!C22+'Neraca Saldo'!D22 -> 0
B27: Beban Penyusutan | C27: ='Neraca Saldo'!C23+'Neraca Saldo'!D23 -> 2911611
B28: Beban Kerugian Bunga Rusak/Layu | C28: ='Neraca Saldo'!C24+'Neraca Saldo'!D24 -> 1115000
B29: Beban Perlengkapan | C29: ='Neraca Saldo'!C27+'Neraca Saldo'!D27 -> 945000
B30: Beban Akomodasi | C30: ='Neraca Saldo'!C33+'Neraca Saldo'!D33 -> 0
B31: Beban Lain-Lain | C31: ='Neraca Saldo'!C28+'Neraca Saldo'!D28 -> 2659600
B32: Beban Pesangon | C32: ='Neraca Saldo'!C35+'Neraca Saldo'!D35 -> 1000000
B33: Total Beban Operasional | C33: =SUM(C23:C32) -> 21245411
A35: LABA USAHA | C35: =C20-C33 -> -1090661
A37: PENDAPATAN DI LUAR USAHA
B38: Pendapatan Bunga Piutang | C38: ='Neraca Saldo'!C30+'Neraca Saldo'!D30 -> 363000
B39: Pendapatan Lain-Lain | C39: ='Neraca Saldo'!C32+'Neraca Saldo'!D32 -> 95000
B40: Total Pendapatan Di Luar Usaha | C40: =SUM(C38:C39) -> 458000
A42: LABA BERSIH | C42: =C35+C40 -> -632661

Sheet Neraca
A1: PT BIGATRI INDOFLORA PACIFIC
A2: BLOOMORIST
A3: NERACA (BALANCE SHEET) 31 Agustus 2026 — Periode Agustus 2026
A5: AKTIVA
A6: Aktiva Lancar
B7: Kas | C7: ='Neraca Saldo'!C6+'Neraca Saldo'!D6 -> 2190500
B8: Bank | C8: ='Neraca Saldo'!C7+'Neraca Saldo'!D7 -> 13450950
B9: Piutang Dagang | C9: ='Neraca Saldo'!C8+'Neraca Saldo'!D8 -> 35000
B10: Piutang Ongkir | C10: ='Neraca Saldo'!C11+'Neraca Saldo'!D11 -> 0
B11: Uang Muka Pembelian Petani | C11: ='Neraca Saldo'!C31+'Neraca Saldo'!D31 -> 9200000
B12: Piutang Investasi | C12: ='Neraca Saldo'!C29+'Neraca Saldo'!D29 -> 33060000
B13: Gaji Bayar di Muka | C13: ='Neraca Saldo'!C34+'Neraca Saldo'!D34 -> 0
B14: Persediaan Bunga (Akhir) | C14: ='Neraca Saldo'!C42+'Neraca Saldo'!D42 -> 5852000
B15: Perlengkapan | C15: ='Neraca Saldo'!C26+'Neraca Saldo'!D26 -> 351000
B16: Total Aktiva Lancar | C16: =SUM(C7:C15) -> 64139450
A18: Aktiva Tetap
B19: Peralatan | C19: ='Neraca Saldo'!C9+'Neraca Saldo'!D9 -> 9500
B20: Akumulasi Penyusutan Peralatan | C20: =-('Neraca Saldo'!C10+'Neraca Saldo'!D10) -> -2911611
B21: Total Aktiva Tetap | C21: =C19+C20 -> -2902111
A23: TOTAL AKTIVA | C23: =C16+C21 -> 61237339
A25: KEWAJIBAN
B26: Hutang Dagang | C26: ='Neraca Saldo'!C12+'Neraca Saldo'!D12 -> 0
B27: Total Kewajiban | C27: =C26 -> 0
A29: MODAL
B30: Modal Pemilik (Awal) | C30: ='Neraca Saldo'!C13+'Neraca Saldo'!D13 -> 61870000
B31: Laba Bersih Periode Berjalan | C31: ='Laba Rugi'!C42 -> -632661
B32: Prive | C32: =-('Neraca Saldo'!C14+'Neraca Saldo'!D14) -> 0
B33: Total Modal (Akhir) | C33: =C30+C31+C32 -> 61237339
A35: TOTAL KEWAJIBAN + MODAL | C35: =C27+C33 -> 61237339
B38: =IF(ROUND(C23-C35,0)=0,"Neraca Seimbang (Balance)","TIDAK SEIMBANG - cek input!") -> Neraca Seimbang (Balance)

Sheet Arus Kas
B1: PT BIGATRI INDOFLORA PACIFIC
B2: BLOOMORIST
B3: LAPORAN ARUS KAS (METODE LANGSUNG) — Periode Agustus 2026
A5: Helper | B5: ARUS KAS DARI AKTIVITAS OPERASI
A6: 4101 | C6: Penerimaan dari Penjualan | D6: =SUMIFS('Jurnal Umum'!$F$6:$F$2564,'Jurnal Umum'!$D$6:$D$2564,"1101",'Jurnal Umum'!$L$6:$L$2564,$A6) +SUMIFS('Jurnal Umum'!$F$6:$F$2564,'Jurnal Umum'!$D$6:$D$2564,"1102",'Jurnal Umum'!$L$6:$L$2564,$A6) -SUMIFS('Jurnal Umum'!$G$6:$G$2564,'Jurnal Umum'!$D$6:$D$2564,"1101",'Jurnal Umum'!$L$6:$L$2564,$A6) -SUMIFS('Jurnal Umum'!$G$6:$G$2564,'Jurnal Umum'!$D$6:$D$2564,"1102",'Jurnal Umum'!$L$6:$L$2564,$A6) -> 1638000
A7: 1103 | C7: Penerimaan Pelunasan Piutang Dagang | D7: =SUMIFS('Jurnal Umum'!$F$6:$F$2564,'Jurnal Umum'!$D$6:$D$2564,"1101",'Jurnal Umum'!$L$6:$L$2564,$A7) +SUMIFS('Jurnal Umum'!$F$6:$F$2564,'Jurnal Umum'!$D$6:$D$2564,"1102",'Jurnal Umum'!$L$6:$L$2564,$A7) -SUMIFS('Jurnal Umum'!$G$6:$G$2564,'Jurnal Umum'!$D$6:$D$2564,"1101",'Jurnal Umum'!$L$6:$L$2564,$A7) -SUMIFS('Jurnal Umum'!$G$6:$G$2564,'Jurnal Umum'!$D$6:$D$2564,"1102",'Jurnal Umum'!$L$6:$L$2564,$A7) -> 51026250
A8: 1107 | C8: Penerimaan Piutang Ongkir | D8: =SUMIFS('Jurnal Umum'!$F$6:$F$2564,'Jurnal Umum'!$D$6:$D$2564,"1101",'Jurnal Umum'!$L$6:$L$2564,$A8) +SUMIFS('Jurnal Umum'!$F$6:$F$2564,'Jurnal Umum'!$D$6:$D$2564,"1102",'Jurnal Umum'!$L$6:$L$2564,$A8) -SUMIFS('Jurnal Umum'!$G$6:$G$2564,'Jurnal Umum'!$D$6:$D$2564,"1101",'Jurnal Umum'!$L$6:$L$2564,$A8) -SUMIFS('Jurnal Umum'!$G$6:$G$2564,'Jurnal Umum'!$D$6:$D$2564,"1102",'Jurnal Umum'!$L$6:$L$2564,$A8) -> 0
A9: 51* | C9: Pembayaran Pembelian Bunga (bersih) | D9: =SUMIFS('Jurnal Umum'!$F$6:$F$2564,'Jurnal Umum'!$D$6:$D$2564,"1101",'Jurnal Umum'!$L$6:$L$2564,$A9) +SUMIFS('Jurnal Umum'!$F$6:$F$2564,'Jurnal Umum'!$D$6:$D$2564,"1102",'Jurnal Umum'!$L$6:$L$2564,$A9) -SUMIFS('Jurnal Umum'!$G$6:$G$2564,'Jurnal Umum'!$D$6:$D$2564,"1101",'Jurnal Umum'!$L$6:$L$2564,$A9) -SUMIFS('Jurnal Umum'!$G$6:$G$2564,'Jurnal Umum'!$D$6:$D$2564,"1102",'Jurnal Umum'!$L$6:$L$2564,$A9) -> -33607500
A10: 2101 | C10: Pembayaran/Pelunasan Hutang Dagang | D10: =SUMIFS('Jurnal Umum'!$F$6:$F$2564,'Jurnal Umum'!$D$6:$D$2564,"1101",'Jurnal Umum'!$L$6:$L$2564,$A10) +SUMIFS('Jurnal Umum'!$F$6:$F$2564,'Jurnal Umum'!$D$6:$D$2564,"1102",'Jurnal Umum'!$L$6:$L$2564,$A10) -SUMIFS('Jurnal Umum'!$G$6:$G$2564,'Jurnal Umum'!$D$6:$D$2564,"1101",'Jurnal Umum'!$L$6:$L$2564,$A10) -SUMIFS('Jurnal Umum'!$G$6:$G$2564,'Jurnal Umum'!$D$6:$D$2564,"1102",'Jurnal Umum'!$L$6:$L$2564,$A10) -> -3370000
A11: 6* | C11: Pembayaran Beban Operasional (Gaji, sewa, utilitas, angkut, dll) | D11: =SUMIFS('Jurnal Umum'!$F$6:$F$2564,'Jurnal Umum'!$D$6:$D$2564,"1101",'Jurnal Umum'!$L$6:$L$2564,$A11) +SUMIFS('Jurnal Umum'!$F$6:$F$2564,'Jurnal Umum'!$D$6:$D$2564,"1102",'Jurnal Umum'!$L$6:$L$2564,$A11) -SUMIFS('Jurnal Umum'!$G$6:$G$2564,'Jurnal Umum'!$D$6:$D$2564,"1101",'Jurnal Umum'!$L$6:$L$2564,$A11) -SUMIFS('Jurnal Umum'!$G$6:$G$2564,'Jurnal Umum'!$D$6:$D$2564,"1102",'Jurnal Umum'!$L$6:$L$2564,$A11) -> -15423800
A12: 1108 | C12: Pembelian Perlengkapan | D12: =SUMIFS('Jurnal Umum'!$F$6:$F$2564,'Jurnal Umum'!$D$6:$D$2564,"1101",'Jurnal Umum'!$L$6:$L$2564,$A12) +SUMIFS('Jurnal Umum'!$F$6:$F$2564,'Jurnal Umum'!$D$6:$D$2564,"1102",'Jurnal Umum'!$L$6:$L$2564,$A12) -SUMIFS('Jurnal Umum'!$G$6:$G$2564,'Jurnal Umum'!$D$6:$D$2564,"1101",'Jurnal Umum'!$L$6:$L$2564,$A12) -SUMIFS('Jurnal Umum'!$G$6:$G$2564,'Jurnal Umum'!$D$6:$D$2564,"1102",'Jurnal Umum'!$L$6:$L$2564,$A12) -> -1296000
A13: 4103 | C13: Penerimaan Pendapatan Bunga | D13: =SUMIFS('Jurnal Umum'!$F$6:$F$2564,'Jurnal Umum'!$D$6:$D$2564,"1101",'Jurnal Umum'!$L$6:$L$2564,$A13) +SUMIFS('Jurnal Umum'!$F$6:$F$2564,'Jurnal Umum'!$D$6:$D$2564,"1102",'Jurnal Umum'!$L$6:$L$2564,$A13) -SUMIFS('Jurnal Umum'!$G$6:$G$2564,'Jurnal Umum'!$D$6:$D$2564,"1101",'Jurnal Umum'!$L$6:$L$2564,$A13) -SUMIFS('Jurnal Umum'!$G$6:$G$2564,'Jurnal Umum'!$D$6:$D$2564,"1102",'Jurnal Umum'!$L$6:$L$2564,$A13) -> 363000
A14: 1110 | C14: Uang Muka Pembelian Petani | D14: =SUMIFS('Jurnal Umum'!$F$6:$F$2564,'Jurnal Umum'!$D$6:$D$2564,"1101",'Jurnal Umum'!$L$6:$L$2564,$A14) +SUMIFS('Jurnal Umum'!$F$6:$F$2564,'Jurnal Umum'!$D$6:$D$2564,"1102",'Jurnal Umum'!$L$6:$L$2564,$A14) -SUMIFS('Jurnal Umum'!$G$6:$G$2564,'Jurnal Umum'!$D$6:$D$2564,"1101",'Jurnal Umum'!$L$6:$L$2564,$A14) -SUMIFS('Jurnal Umum'!$G$6:$G$2564,'Jurnal Umum'!$D$6:$D$2564,"1102",'Jurnal Umum'!$L$6:$L$2564,$A14) -> -9200000
A15: 1111 | C15: Gaji Bayar di Muka | D15: =SUMIFS('Jurnal Umum'!$F$6:$F$2564,'Jurnal Umum'!$D$6:$D$2564,"1101",'Jurnal Umum'!$L$6:$L$2564,$A15) +SUMIFS('Jurnal Umum'!$F$6:$F$2564,'Jurnal Umum'!$D$6:$D$2564,"1102",'Jurnal Umum'!$L$6:$L$2564,$A15) -SUMIFS('Jurnal Umum'!$G$6:$G$2564,'Jurnal Umum'!$D$6:$D$2564,"1101",'Jurnal Umum'!$L$6:$L$2564,$A15) -SUMIFS('Jurnal Umum'!$G$6:$G$2564,'Jurnal Umum'!$D$6:$D$2564,"1102",'Jurnal Umum'!$L$6:$L$2564,$A15) -> -850000
A16: 4104 | C16: Penerimaan Pendapatan Lain-Lain | D16: =SUMIFS('Jurnal Umum'!$F$6:$F$2564,'Jurnal Umum'!$D$6:$D$2564,"1101",'Jurnal Umum'!$L$6:$L$2564,$A16) +SUMIFS('Jurnal Umum'!$F$6:$F$2564,'Jurnal Umum'!$D$6:$D$2564,"1102",'Jurnal Umum'!$L$6:$L$2564,$A16) -SUMIFS('Jurnal Umum'!$G$6:$G$2564,'Jurnal Umum'!$D$6:$D$2564,"1101",'Jurnal Umum'!$L$6:$L$2564,$A16) -SUMIFS('Jurnal Umum'!$G$6:$G$2564,'Jurnal Umum'!$D$6:$D$2564,"1102",'Jurnal Umum'!$L$6:$L$2564,$A16) -> 95000
A17: 2102 | C17: Penerimaan Uang Muka Penjuala | D17: =SUMIFS('Jurnal Umum'!$F$6:$F$2564,'Jurnal Umum'!$D$6:$D$2564,"1101",'Jurnal Umum'!$L$6:$L$2564,$A17) +SUMIFS('Jurnal Umum'!$F$6:$F$2564,'Jurnal Umum'!$D$6:$D$2564,"1102",'Jurnal Umum'!$L$6:$L$2564,$A17) -SUMIFS('Jurnal Umum'!$G$6:$G$2564,'Jurnal Umum'!$D$6:$D$2564,"1101",'Jurnal Umum'!$L$6:$L$2564,$A17) -SUMIFS('Jurnal Umum'!$G$6:$G$2564,'Jurnal Umum'!$D$6:$D$2564,"1102",'Jurnal Umum'!$L$6:$L$2564,$A17) -> 0
C18: Kas Bersih dari Aktivitas Operasi | D18: =SUM(D6:D17) -> -10625050
B20: ARUS KAS DARI AKTIVITAS INVESTASI
A21: 1105 | C21: Pembelian Peralatan | D21: =SUMIFS('Jurnal Umum'!$F$6:$F$2564,'Jurnal Umum'!$D$6:$D$2564,"1101",'Jurnal Umum'!$L$6:$L$2564,$A21) +SUMIFS('Jurnal Umum'!$F$6:$F$909,'Jurnal Umum'!$D$6:$D$909,"1102",'Jurnal Umum'!$L$6:$L$909,$A21) -SUMIFS('Jurnal Umum'!$G$6:$G$909,'Jurnal Umum'!$D$6:$D$909,"1101",'Jurnal Umum'!$L$6:$L$909,$A21) -SUMIFS('Jurnal Umum'!$G$6:$G$909,'Jurnal Umum'!$D$6:$D$909,"1102",'Jurnal Umum'!$L$6:$L$909,$A21) -> -9500
A22: 1109 | C22: Pinjaman/Piutang Investasi | D22: =SUMIFS('Jurnal Umum'!$F$6:$F$2564,'Jurnal Umum'!$D$6:$D$2564,"1101",'Jurnal Umum'!$L$6:$L$2564,$A22) +SUMIFS('Jurnal Umum'!$F$6:$F$909,'Jurnal Umum'!$D$6:$D$909,"1102",'Jurnal Umum'!$L$6:$L$909,$A22) -SUMIFS('Jurnal Umum'!$G$6:$G$909,'Jurnal Umum'!$D$6:$D$909,"1101",'Jurnal Umum'!$L$6:$L$909,$A22) -SUMIFS('Jurnal Umum'!$G$6:$G$909,'Jurnal Umum'!$D$6:$D$909,"1102",'Jurnal Umum'!$L$6:$L$909,$A22) -> -33060000
A23: 1112 | C23: Uang Muka Pembelian Tanah | D23: =SUMIFS('Jurnal Umum'!$F$6:$F$2564,'Jurnal Umum'!$D$6:$D$2564,"1101",'Jurnal Umum'!$L$6:$L$2564,$A23) +SUMIFS('Jurnal Umum'!$F$6:$F$909,'Jurnal Umum'!$D$6:$D$909,"1102",'Jurnal Umum'!$L$6:$L$909,$A23) -SUMIFS('Jurnal Umum'!$G$6:$G$909,'Jurnal Umum'!$D$6:$D$909,"1101",'Jurnal Umum'!$L$6:$L$909,$A23) -SUMIFS('Jurnal Umum'!$G$6:$G$909,'Jurnal Umum'!$D$6:$D$909,"1102",'Jurnal Umum'!$L$6:$L$909,$A23) -> 0
C24: Kas Bersih dari Aktivitas Investasi | D24: =SUM(D21:D22) -> -33069500
B26: ARUS KAS DARI AKTIVITAS PENDANAAN
A27: 3101 | C27: Setoran Modal Pemilik | D27: =SUMIFS('Jurnal Umum'!$F$6:$F$2564,'Jurnal Umum'!$D$6:$D$2564,"1101",'Jurnal Umum'!$L$6:$L$2564,$A27) +SUMIFS('Jurnal Umum'!$F$6:$F$2564,'Jurnal Umum'!$D$6:$D2564,"1102",'Jurnal Umum'!$L$6:$L$2564,$A27) -SUMIFS('Jurnal Umum'!$G$6:$G$2564,'Jurnal Umum'!$D$6:$D$2564,"1101",'Jurnal Umum'!$L$6:$L$2564,$A27) -SUMIFS('Jurnal Umum'!$G$6:$G$2564,'Jurnal Umum'!$D$6:$D$2564,"1102",'Jurnal Umum'!$L$6:$L$2564,$A27) -> 59336000
A28: 3102 | C28: Prive Pemilik | D28: =SUMIFS('Jurnal Umum'!$F$6:$F$909,'Jurnal Umum'!$D$6:$D$909,"1101",'Jurnal Umum'!$L$6:$L$909,$A28) +SUMIFS('Jurnal Umum'!$F$6:$F$909,'Jurnal Umum'!$D$6:$D$909,"1102",'Jurnal Umum'!$L$6:$L$909,$A28) -SUMIFS('Jurnal Umum'!$G$6:$G$909,'Jurnal Umum'!$D$6:$D$909,"1101",'Jurnal Umum'!$L$6:$L$909,$A28) -SUMIFS('Jurnal Umum'!$G$6:$G$909,'Jurnal Umum'!$D$6:$D$909,"1102",'Jurnal Umum'!$L$6:$L$909,$A28) -> 0
C29: Kas Bersih dari Aktivitas Pendanaan | D29: =SUM(D27:D28) -> 59336000
B31: KENAIKAN (PENURUNAN) KAS & BANK BERSIH | D31: =D18+D24+D29 -> 15641450
C32: Saldo Kas & Bank Awal Periode | D32: 0
B33: Saldo Kas & Bank Akhir Periode | D33: =D31+D32 -> 15641450
C36: =IF(ROUND(D33-('Neraca Saldo'!C6+'Neraca Saldo'!C7),0)=0,"Cocok dengan saldo Kas+Bank di Neraca Saldo","Cek kembali - tidak cocok") -> Cocok dengan saldo Kas+Bank di Neraca Saldo

Sheet Data Bulanan
A1: PT BIGATRI INDONESIA PACIFIC
A2: BLOOMORIST
A3: REKAP DATA BULANAN — Periode Agustus 2026
A5: Bulan | B5: Penjualan Bersih | C5: HPP | D5: Laba Kotor | E5: Beban Operasional | F5: Laba Bersih | G5: Kas & Bank Akhir
A6: Agustus 2026 | B6: ='Laba Rugi'!C8 -> 55819250 | C6: ='Laba Rugi'!C18 -> 35664500 | D6: ='Laba Rugi'!C20 -> 20154750 | E6: ='Laba Rugi'!C33 -> 21245411 | F6: ='Laba Rugi'!C42 -> -632661 | G6: ='Arus Kas'!D33 -> 15641450
